Workbook

Sheet employee_data
A1: EmpID | B1: Full Name | C1: StartDate | D1: ExitDate | E1: Title | F1: Supervisor | G1: ADEmail | H1: BusinessUnit | I1: EmployeeStatus | J1: EmployeeType | K1: PayZone | L1: EmployeeClassificationType | M1: TerminationType | N1: TerminationDescription | O1: DepartmentType | P1: Division | Q1: DOB | R1: State | S1: JobFunctionDescription | T1: GenderCode | U1: LocationCode | V1: RaceDesc | W1: MaritalDesc | X1: Performance Score | Y1: Current Employee Rating
A2: 1001 | B2: Susan Exantus | C2: 43706 | D2: N/A | E2: Software Engineer | F2: Angela Carlson | G2: susan.exantus@bilearner.com | H2: BPC | I2: Active | J2: Part-Time | K2: Zone A | L2: Part-Time | M2: Unk | N2: N/A | O2: Software Engineering | P2: Engineers | Q2: 21084 | R2: MA | S2: Engineer | T2: Female | U2: 1749 | V2: Black | W2: Married | X2: Fully Meets | Y2: 3 | AB2: EMPLOYE STATUS COUNT | AD2: Percentage Calculation
A3: 1002 | B3: Sandra Martin | C3: 44907 | D3: 45074 | E3: Software Engineer | F3: Angela Hayes | G3: sandra.martin@bilearner.com | H3: NEL | I3: Terminated for Cause | J3: Part-Time | K3: Zone A | L3: Temporary | M3: Involuntary | N3: Behind buy our of very claim. | O3: Software Engineering | P3: Catv | Q3: 18452 | R3: MA | S3: Foreman | T3: Female | U3: 2135 | V3: Asian | W3: Widowed | X3: Fully Meets | Y3: 3 | AB3: Total Headcount | AC3: =COUNTA(Table4[EmpID]) -> 3000
A4: 1003 | B4: Keyla Del Bosque | C4: 44993 | D4: 45000 | E4: Software Engineer | F4: Christina Copeland | G4: keyla.delbosque@bilearner.com | H4: WBL | I4: Voluntarily Terminated | J4: Contract | K4: Zone A | L4: Part-Time | M4: Voluntary | N4: Some make teach quite range seem conference. | O4: Software Engineering | P4: Field Operations | Q4: 26991 | R4: MA | S4: Foreman | T4: Female | U4: 2176 | V4: White | W4: Married | X4: Fully Meets | Y4: 3 | AB4: Active Count | AC4: =COUNTIF(Table4[EmployeeStatus],"Active") -> 1661 | AD4: =AC4/AC3 -> 0.55366667
A5: 1004 | B5: Andrew Szabo | C5: 43980 | D5: 44260 | E5: Software Engineer | F5: Jennifer Cohen | G5: andrew.szabo@bilearner.com | H5: PYZ | I5: Terminated for Cause | J5: Part-Time | K5: Zone C | L5: Part-Time | M5: Involuntary | N5: Enter beautiful social store. | O5: Software Engineering | P5: Project Management - Con | Q5: 20847 | R5: MA | S5: Coordinator | T5: Male | U5: 2140 | V5: Black | W5: Single | X5: Fully Meets | Y5: 3 | AB5: Voluntarily Terminated Count | AC5: =COUNTIF(Table4[EmployeeStatus],"Voluntarily Terminated") -> 935 | AD5: =AC5/AC3 -> 0.31166667
A6: 1005 | B6: Luke Patronick | C6: 44820 | D6: N/A | E6: Software Engineer | F6: Mr. Jesus Richards | G6: colby.andreola@bilearner.com | H6: SVG | I6: Voluntarily Terminated | J6: Full-Time | K6: Zone B | L6: S | M6: Unk | N6: N/A | O6: Software Engineering | P6: Field Operations | Q6: 25777 | R6: MA | S6: Project Manager | T6: Male | U6: 1844 | V6: Black | W6: Divorced | X6: Fully Meets | Y6: 3 | AB6: Terminated for Cause Count | AC6: =COUNTIF(Table4[EmployeeStatus],"Terminated for Cause") -> 272 | AD6: =AC6/AC3 -> 0.090666667
A7: 1006 | B7: Colby Andreola | C7: 44423 | D7: 44520 | E7: Software Engineer | F7: Beth Johnson | G7: edward.true@bilearner.com | H7: MSC | I7: Voluntarily Terminated | J7: Full-Time | K7: Zone C | L7: Part-Time | M7: Resignation | N7: Throughout yet in serious here wish. | O7: Software Engineering | P7: Engineers | Q7: 21600 | R7: MA | S7: Administrative | T7: Female | U7: 2110 | V7: White | W7: Widowed | X7: Fully Meets | Y7: 3 | AB7: Leave of Absence | AC7: =COUNTIF(Table4[EmployeeStatus],"Leave of Absence") -> 74 | AD7: =AC7/AC3 -> 0.024666667
A8: 1007 | B8: Edward TRUE | C8: 44129 | D8: 44465 | E8: Software Engineer | F8: Raymond Adams | G8: judith.carabbio@bilearner.com | H8: SVG | I8: Voluntarily Terminated | J8: Part-Time | K8: Zone A | L8: Part-Time | M8: Involuntary | N8: Recently however meeting economic. | O8: Software Engineering | P8: General - Con | Q8: 36603 | R8: MA | S8: Lineman | T8: Male | U8: 2451 | V8: Black | W8: Widowed | X8: Fully Meets | Y8: 3 | AB8: Future Start | AC8: =COUNTIF(Table4[EmployeeStatus],"Future Start") -> 58 | AD8: =AC8/AC3 -> 0.019333333
A9: 1008 | B9: Judith Carabbio | C9: 43705 | D9: 43955 | E9: Software Engineer | F9: Jessica Rhodes | G9: adell.saada@bilearner.com | H9: BPC | I9: Voluntarily Terminated | J9: Contract | K9: Zone B | L9: Temporary | M9: Voluntary | N9: Instead story skill financial who. | O9: Software Engineering | P9: General - Con | Q9: 29941 | R9: MA | S9: Foreman | T9: Female | U9: 2132 | V9: Hispanic | W9: Married | X9: Fully Meets | Y9: 3
A10: 1009 | B10: Adell Saada | C10: 43629 | D10: 44938 | E10: Software Engineer | F10: Steven Tran | G10: kamari.hunter@bilearner.com | H10: NEL | I10: Terminated for Cause | J10: Part-Time | K10: Zone C | L10: Temporary | M10: Retirement | N10: Exactly vote including easy. | O10: Software Engineering | P10: General - Con | Q10: 31837 | R10: MA | S10: Model Assistant | T10: Female | U10: 2132 | V10: Other | W10: Single | X10: Fully Meets | Y10: 3
A11: 1010 | B11: Kamari Hunter | C11: 44208 | D11: 44638 | E11: Software Engineer | F11: Kristen Collier | G11: sarah.malone@bilearner.com | H11: EW | I11: Terminated for Cause | J11: Part-Time | K11: Zone C | L11: Temporary | M11: Voluntary | N11: West note present Mr woman family. | O11: Software Engineering | P11: Field Operations | Q11: 33898 | R11: MA | S11: Supervisor | T11: Male | U11: 12889 | V11: Hispanic | W11: Divorced | X11: Fully Meets | Y11: 3
A12: 1011 | B12: Sarah Malone | C12: 44599 | D12: 44969 | E12: Software Engineer | F12: David Lopez | G12: skyler.blackwell@bilearner.com | H12: MSC | I12: Terminated for Cause | J12: Contract | K12: Zone A | L12: Temporary | M12: Resignation | N12: Professor situation they bag interest there. | O12: Software Engineering | P12: General - Con | Q12: 17585 | R12: MA | S12: Foreman | T12: Male | U12: 21340 | V12: Hispanic | W12: Married | X12: Fully Meets | Y12: 3
A13: 1012 | B13: Skyler Blackwell | C13: 44144 | D13: 44353 | E13: Software Engineer | F13: Candice Schmidt | G13: kole.quinn@bilearner.com | H13: TNS | I13: Voluntarily Terminated | J13: Contract | K13: Zone A | L13: Temporary | M13: Involuntary | N13: Get apply economy artist right benefit ground. | O13: Software Engineering | P13: General - Eng | Q13: 28766 | R13: MA | S13: Administrative | T13: Male | U13: 67544 | V13: White | W13: Single | X13: Fully Meets | Y13: 3
A14: 1013 | B14: Jasmin Shah | C14: 43964 | D14: N/A | E14: Software Engineer | F14: Christy Craig | G14: jayda.reese@bilearner.com | H14: PYZ | I14: Terminated for Cause | J14: Part-Time | K14: Zone B | L14: Full-Time | M14: Unk | N14: N/A | O14: Software Engineering | P14: Engineers | Q14: 27352 | R14: MA | S14: Engineer | T14: Male | U14: 36398 | V14: Asian | W14: Single | X14: Fully Meets | Y14: 3
A15: 1014 | B15: Kole Quinn | C15: 44926 | D15: 45120 | E15: Shared Services Manager | F15: Jermaine Weaver | G15: julien.whitehead@bilearner.com | H15: WBL | I15: Voluntarily Terminated | J15: Part-Time | K15: Zone A | L15: Full-Time | M15: Retirement | N15: I back place no three offer economic. | O15: Software Engineering | P15: Catv | Q15: 19553 | R15: MA | S15: Clerk | T15: Male | U15: 2562 | V15: Other | W15: Single | X15: Fully Meets | Y15: 3
A16: 1015 | B16: Ansley Jackson | C16: 43437 | D16: N/A | E16: Shared Services Manager | F16: James Barajas | G16: alan.haynes@bilearner.com | H16: NEL | I16: Voluntarily Terminated | J16: Contract | K16: Zone A | L16: Part-Time | M16: Unk | N16: N/A | O16: Software Engineering | P16: People Services | Q16: 22619 | R16: MA | S16: Vp | T16: Female | U16: 22621 | V16: White | W16: Married | X16: Fully Meets | Y16: 3
A17: 1016 | B17: Jayda Reese | C17: 43882 | D17: 44345 | E17: Senior BI Developer | F17: Tyler Davis | G17: kamryn.herrera@bilearner.com | H17: PL | I17: Voluntarily Terminated | J17: Part-Time | K17: Zone B | L17: Part-Time | M17: Involuntary | N17: Friend agree stock teach price fish. | O17: Admin Offices | P17: Shop (Fleet) | Q17: 20522 | R17: MA | S17: Mechanic | T17: Female | U17: 64065 | V17: White | W17: Single | X17: Fully Meets | Y17: 3
A18: 1017 | B18: Julien Whitehead | C18: 44081 | D18: 44545 | E18: Senior BI Developer | F18: Joshua Gonzalez | G18: kelvin.foster@bilearner.com | H18: BPC | I18: Voluntarily Terminated | J18: Full-Time | K18: Zone B | L18: Full-Time | M18: Involuntary | N18: True system strong often experience. | O18: Admin Offices | P18: Field Operations | Q18: 17353 | R18: MA | S18: Laborer | T18: Female | U18: 97374 | V18: Black | W18: Single | X18: Fully Meets | Y18: 3
A19: 1018 | B19: Alan Haynes | C19: 44001 | D19: 44538 | E19: Senior BI Developer | F19: Justin Sherman | G19: joe.fletcher@bilearner.com | H19: CCDR | I19: Voluntarily Terminated | J19: Part-Time | K19: Zone A | L19: Part-Time | M19: Involuntary | N19: When price group admit fall fly around. | O19: Admin Offices | P19: General - Con | Q19: 15396 | R19: MA | S19: Laborer | T19: Female | U19: 87646 | V19: White | W19: Married | X19: Fully Meets | Y19: 3
A20: 1019 | B20: Kamryn Herrera | C20: 44848 | D20: 45135 | E20: Software Engineer | F20: Sara Holland | G20: nickolas.davila@bilearner.com | H20: EW | I20: Voluntarily Terminated | J20: Full-Time | K20: Zone A | L20: Temporary | M20: Retirement | N20: Article tough away forward home. Night author so. | O20: Software Engineering | P20: Fielders | Q20: 28822 | R20: MA | S20: Engineer | T20: Male | U20: 77974 | V20: Hispanic | W20: Widowed | X20: Fully Meets | Y20: 3
A21: 1020 | B21: Kelvin Foster | C21: 45097 | D21: 45125 | E21: Software Engineer | F21: Shelia Graham | G21: kasey.boyer@bilearner.com | H21: MSC | I21: Terminated for Cause | J21: Contract | K21: Zone C | L21: Full-Time | M21: Resignation | N21: Man issue never strategy will maintain resource. | O21: Software Engineering | P21: Field Operations | Q21: 33227 | R21: MA | S21: Supervisor | T21: Female | U21: 42126 | V21: Black | W21: Widowed | X21: Fully Meets | Y21: 3
A22: 1021 | B22: Joe Fletcher | C22: 44144 | D22: 45124 | E22: Software Engineer | F22: Amanda Hayden | G22: giovanni.jenkins@bilearner.com | H22: TNS | I22: Terminated for Cause | J22: Full-Time | K22: Zone C | L22: Full-Time | M22: Resignation | N22: Section hospital clearly season history. | O22: Software Engineering | P22: General - Eng | Q22: 32533 | R22: MA | S22: Billing | T22: Male | U22: 51613 | V22: Hispanic | W22: Single | X22: Fully Meets | Y22: 3
A23: 1022 | B23: Frederick Howe | C23: 44823 | D23: N/A | E23: Software Engineer | F23: Nicole Haynes | G23: alexis.moss@bilearner.com | H23: PYZ | I23: Voluntarily Terminated | J23: Part-Time | K23: Zone A | L23: Temporary | M23: Unk | N23: N/A | O23: Software Engineering | P23: Field Operations | Q23: 22808 | R23: MA | S23: Engineer | T23: Male | U23: 12765 | V23: Black | W23: Divorced | X23: Fully Meets | Y23: 3
A24: 1023 | B24: Nickolas Davila | C24: 43413 | D24: 44479 | E24: Shared Services Manager | F24: Debra Morales | G24: joanna.murphy@bilearner.com | H24: WBL | I24: Voluntarily Terminated | J24: Contract | K24: Zone C | L24: Part-Time | M24: Voluntary | N24: Each wish foot person morning per significant. | O24: Software Engineering | P24: General - Con | Q24: 33699 | R24: MA | S24: Clerk | T24: Male | U24: 64122 | V24: Hispanic | W24: Divorced | X24: Fully Meets | Y24: 3
A25: 1024 | B25: Kasey Boyer | C25: 43464 | D25: 44370 | E25: Shared Services Manager | F25: Chad Andrews | G25: joseph.schmidt@bilearner.com | H25: NEL | I25: Voluntarily Terminated | J25: Contract | K25: Zone A | L25: Part-Time | M25: Involuntary | N25: Free may every real agency as blue maintain. | O25: Software Engineering | P25: Fielders | Q25: 31866 | R25: MA | S25: Coordinator | T25: Female | U25: 91332 | V25: Other | W25: Divorced | X25: Fully Meets | Y25: 3
A26: 1025 | B26: Giovanni Jenkins | C26: 45057 | D26: 45061 | E26: Senior BI Developer | F26: John Wallace | G26: kiley.haynes@bilearner.com | H26: PL | I26: Voluntarily Terminated | J26: Full-Time | K26: Zone A | L26: Temporary | M26: Retirement | N26: Quite none ten order. | O26: Admin Offices | P26: Field Operations | Q26: 22233 | R26: MA | S26: Foreman | T26: Female | U26: 39827 | V26: Other | W26: Divorced | X26: Fully Meets | Y26: 3
A27: 1026 | B27: Alexis Moss | C27: 44868 | D27: 44966 | E27: Senior BI Developer | F27: Benjamin Frederick | G27: kody.jimenez@bilearner.com | H27: BPC | I27: Voluntarily Terminated | J27: Contract | K27: Zone A | L27: Part-Time | M27: Resignation | N27: Where forward evening huge cost share eat. | O27: Admin Offices | P27: Engineers | Q27: 18574 | R27: MA | S27: Engineer | T27: Female | U27: 27418 | V27: Other | W27: Widowed | X27: Fully Meets | Y27: 3
A28: 1027 | B28: Joanna Murphy | C28: 43996 | D28: 44345 | E28: Senior BI Developer | F28: Michael Ramos | G28: zoe.colon@bilearner.com | H28: CCDR | I28: Voluntarily Terminated | J28: Part-Time | K28: Zone A | L28: Full-Time | M28: Voluntary | N28: Open test message part risk. | O28: Admin Offices | P28: General - Con | Q28: 23001 | R28: MA | S28: Flagger | T28: Male | U28: 24931 | V28: Other | W28: Single | X28: Fully Meets | Y28: 3
A29: 1028 | B29: Joseph Schmidt | C29: 43753 | D29: 44927 | E29: Software Engineer | F29: Donna Boone | G29: nolan.perez@bilearner.com | H29: PYZ | I29: Voluntarily Terminated | J29: Full-Time | K29: Zone C | L29: Part-Time | M29: Resignation | N29: Federal less every character section think white. | O29: Software Engineering | P29: General - Con | Q29: 36821 | R29: MA | S29: Model Assistant | T29: Male | U29: 2121 | V29: Asian | W29: Single | X29: Fully Meets | Y29: 3
A30: 1029 | B30: Brittany Hurley | C30: 43949 | D30: N/A | E30: Software Engineer | F30: Jeffrey Johnston | G30: katrina.farrell@bilearner.com | H30: SVG | I30: Voluntarily Terminated | J30: Part-Time | K30: Zone B | L30: Part-Time | M30: Unk | N30: N/A | O30: Software Engineering | P30: Field Operations | Q30: 29007 | R30: MA | S30: Specialist | T30: Female | U30: 97697 | V30: Asian | W30: Divorced | X30: Fully Meets | Y30: 3
A31: 1030 | B31: Niko Hamilton | C31: 43767 | D31: N/A | E31: Software Engineer | F31: Sarah King | G31: camden.kelly@bilearner.com | H31: TNS | I31: Voluntarily Terminated | J31: Contract | K31: Zone C | L31: Temporary | M31: Unk | N31: N/A | O31: Software Engineering | P31: Field Operations | Q31: 20276 | R31: MA | S31: Foreman | T31: Male | U31: 75783 | V31: Black | W31: Single | X31: Fully Meets | Y31: 3
A32: 1031 | B32: Ruben Martinez | C32: 44314 | D32: N/A | E32: Software Engineer | F32: Cynthia Delgado | G32: kale.lang@bilearner.com | H32: WBL | I32: Voluntarily Terminated | J32: Part-Time | K32: Zone B | L32: Temporary | M32: Unk | N32: N/A | O32: Software Engineering | P32: General - Con | Q32: 26601 | R32: MA | S32: Lineman | T32: Male | U32: 26111 | V32: White | W32: Widowed | X32: Fully Meets | Y32: 3
A33: 1032 | B33: Kiley Haynes | C33: 44670 | D33: 44799 | E33: Software Engineer | F33: Dominique Bailey | G33: elliott.ashley@bilearner.com | H33: PYZ | I33: Voluntarily Terminated | J33: Full-Time | K33: Zone C | L33: Part-Time | M33: Voluntary | N33: Off part culture choose strong public. | O33: Software Engineering | P33: Aerial | Q33: 19906 | R33: MA | S33: Laborer | T33: Male | U33: 50656 | V33: Asian | W33: Widowed | X33: Fully Meets | Y33: 3
A34: 1033 | B34: Blaine Brooks | C34: 45013 | D34: N/A | E34: Shared Services Manager | F34: Teresa Meyer | G34: genesis.todd@bilearner.com | H34: WBL | I34: Voluntarily Terminated | J34: Contract | K34: Zone B | L34: Full-Time | M34: Unk | N34: N/A | O34: Software Engineering | P34: Field Operations | Q34: 35517 | R34: MA | S34: Operator | T34: Male | U34: 71808 | V34: Other | W34: Single | X34: Fully Meets | Y34: 3
A35: 1034 | B35: Dennis Livingston | C35: 43591 | D35: N/A | E35: Shared Services Manager | F35: Sarah Carey | G35: demarion.morrow@bilearner.com | H35: NEL | I35: Voluntarily Terminated | J35: Full-Time | K35: Zone C | L35: Part-Time | M35: Unk | N35: N/A | O35: Software Engineering | P35: Project Management - Con | Q35: 28467 | R35: MA | S35: Manager | T35: Female | U35: 1043 | V35: Black | W35: Single | X35: Fully Meets | Y35: 3
A36: 1035 | B36: Case Russell | C36: 44117 | D36: N/A | E36: Senior BI Developer | F36: Taylor Wright | G36: devon.hinton@bilearner.com | H36: PL | I36: Voluntarily Terminated | J36: Full-Time | K36: Zone A | L36: Temporary | M36: Unk | N36: N/A | O36: Admin Offices | P36: Underground | Q36: 28902 | R36: MA | S36: Laborer | T36: Female | U36: 41260 | V36: Asian | W36: Divorced | X36: Fully Meets | Y36: 3
A37: 1036 | B37: Kody Jimenez | C37: 44383 | D37: 44525 | E37: Senior BI Developer | F37: Daniel Moore | G37: jacquelyn.johns@bilearner.com | H37: BPC | I37: Terminated for Cause | J37: Part-Time | K37: Zone A | L37: Part-Time | M37: Resignation | N37: Teacher door money tend song. | O37: Admin Offices | P37: Field Operations | Q37: 34189 | R37: MA | S37: Foreman | T37: Male | U37: 15346 | V37: Asian | W37: Single | X37: Fully Meets | Y37: 3
A38: 1037 | B38: Zoe Colon | C38: 44098 | D38: 44137 | E38: Software Engineer | F38: Stacey Vargas | G38: blaine.keith@bilearner.com | H38: CCDR | I38: Terminated for Cause | J38: Part-Time | K38: Zone C | L38: Full-Time | M38: Voluntary | N38: Accept knowledge drop bar understand. | O38: Software Engineering | P38: Fielders | Q38: 34177 | R38: MA | S38: Engineer | T38: Male | U38: 4876 | V38: Other | W38: Widowed | X38: Fully Meets | Y38: 3
A39: 1038 | B39: Courtney Cowan | C39: 44944 | D39: N/A | E39: Software Engineer | F39: Beth Anderson | G39: frida.livingston@bilearner.com | H39: SVG | I39: Voluntarily Terminated | J39: Contract | K39: Zone B | L39: Part-Time | M39: Unk | N39: N/A | O39: Software Engineering | P39: Field Operations | Q39: 26057 | R39: MA | S39: Crew Leader | T39: Male | U39: 14886 | V39: Hispanic | W39: Married | X39: Fully Meets | Y39: 3
A40: 1039 | B40: Nolan Perez | C40: 43699 | D40: 44645 | E40: Software Engineer | F40: Joshua Daniels | G40: travis.vasquez@bilearner.com | H40: EW | I40: Terminated for Cause | J40: Part-Time | K40: Zone B | L40: Part-Time | M40: Involuntary | N40: Under follow guess lot minute able history face. | O40: Software Engineering | P40: Finance & Accounting | Q40: 30272 | R40: MA | S40: Administrative | T40: Female | U40: 46407 | V40: Other | W40: Widowed | X40: Fully Meets | Y40: 3
A41: 1040 | B41: Katrina Farrell | C41: 43671 | D41: 44912 | E41: Software Engineer | F41: Mark Mays | G41: wyatt.donovan@bilearner.com | H41: MSC | I41: Voluntarily Terminated | J41: Contract | K41: Zone A | L41: Part-Time | M41: Retirement | N41: Main customer television phone staff family. | O41: Software Engineering | P41: Field Operations | Q41: 26414 | R41: MA | S41: Technician | T41: Male | U41: 74234 | V41: White | W41: Divorced | X41: Fully Meets | Y41: 3
A42: 1041 | B42: Camden Kelly | C42: 43780 | D42: 43840 | E42: Software Engineer | F42: Brandon Ortiz | G42: gage.weeks@bilearner.com | H42: TNS | I42: Voluntarily Terminated | J42: Full-Time | K42: Zone A | L42: Full-Time | M42: Retirement | N42: Suffer consider store find up. | O42: Software Engineering | P42: Engineers | Q42: 28068 | R42: MA | S42: Administrative | T42: Male | U42: 45272 | V42: White | W42: Single | X42: Fully Meets | Y42: 3
A43: 1042 | B43: Milo Hood | C43: 44758 | D43: N/A | E43: Software Engineer | F43: Cheryl Swanson | G43: wyatt.edwards@bilearner.com | H43: PYZ | I43: Terminated for Cause | J43: Contract | K43: Zone B | L43: Temporary | M43: Unk | N43: N/A | O43: Software Engineering | P43: Field Operations | Q43: 15571 | R43: MA | S43: Driller | T43: Male | U43: 96170 | V43: Black | W43: Widowed | X43: Fully Meets | Y43: 3
A44: 1043 | B44: Kale Lang | C44: 44914 | D44: 45056 | E44: Shared Services Manager | F44: Matthew Patel | G44: karla.reed@bilearner.com | H44: WBL | I44: Voluntarily Terminated | J44: Full-Time | K44: Zone C | L44: Part-Time | M44: Resignation | N44: Agreement particular scene also war who. | O44: Software Engineering | P44: Splicing | Q44: 20439 | R44: MA | S44: Billing | T44: Female | U44: 65963 | V44: White | W44: Married | X44: Fully Meets | Y44: 3
A45: 1044 | B45: Shyanne Stark | C45: 44089 | D45: N/A | E45: Shared Services Manager | F45: Jennifer Adams | G45: yadira.mcmillan@bilearner.com | H45: NEL | I45: Terminated for Cause | J45: Contract | K45: Zone A | L45: Temporary | M45: Unk | N45: N/A | O45: Software Engineering | P45: Field Operations | Q45: 20714 | R45: MA | S45: Foreman | T45: Female | U45: 75123 | V45: Hispanic | W45: Divorced | X45: Fully Meets | Y45: 3
A46: 1045 | B46: Elliott Ashley | C46: 44108 | D46: 44984 | E46: Senior BI Developer | F46: Kelly Williams | G46: lilianna.mccall@bilearner.com | H46: PL | I46: Terminated for Cause | J46: Full-Time | K46: Zone C | L46: Temporary | M46: Involuntary | N46: Artist technology ever body provide today doctor. | O46: Admin Offices | P46: Catv | Q46: 23172 | R46: MA | S46: Foreman | T46: Female | U46: 11164 | V46: Black | W46: Single | X46: Fully Meets | Y46: 3
A47: 1046 | B47: Genesis Todd | C47: 44674 | D47: 44776 | E47: Software Engineer | F47: Jose Daniel | G47: salvador.thomas@bilearner.com | H47: CCDR | I47: Terminated for Cause | J47: Full-Time | K47: Zone A | L47: Temporary | M47: Involuntary | N47: Former treat check special economy. | O47: Software Engineering | P47: Underground | Q47: 22967 | R47: MA | S47: Laborer | T47: Male | U47: 65978 | V47: White | W47: Single | X47: Fully Meets | Y47: 3
A48: 1047 | B48: Sincere Jimenez | C48: 44527 | D48: N/A | E48: Software Engineer | F48: Vanessa Ramirez | G48: jair.silva@bilearner.com | H48: SVG | I48: Voluntarily Terminated | J48: Contract | K48: Zone A | L48: Part-Time | M48: Unk | N48: N/A | O48: Software Engineering | P48: Field Operations | Q48: 17495 | R48: MA | S48: Technician | T48: Female | U48: 73877 | V48: Hispanic | W48: Single | X48: Fully Meets | Y48: 3
A49: 1048 | B49: Stephen Daugherty | C49: 43798 | D49: N/A | E49: Software Engineer | F49: Joshua Pittman | G49: litzy.conner@bilearner.com | H49: EW | I49: Voluntarily Terminated | J49: Part-Time | K49: Zone A | L49: Temporary | M49: Unk | N49: N/A | O49: Software Engineering | P49: General - Con | Q49: 20655 | R49: MA | S49: Helper | T49: Male | U49: 48971 | V49: Asian | W49: Widowed | X49: Fully Meets | Y49: 3
A50: 1049 | B50: Demarion Morrow | C50: 43615 | D50: 44184 | E50: Software Engineer | F50: Patricia Brewer | G50: joanna.burnett@bilearner.com | H50: MSC | I50: Voluntarily Terminated | J50: Part-Time | K50: Zone B | L50: Part-Time | M50: Involuntary | N50: Plan capital firm foreign. | O50: Software Engineering | P50: Field Operations | Q50: 19993 | R50: MA | S50: Technician | T50: Male | U50: 16259 | V50: White | W50: Married | X50: Fully Meets | Y50: 3
A51: 1050 | B51: Steven Schneider | C51: 44158 | D51: N/A | E51: Software Engineer | F51: Jerry Suarez | G51: armani.porter@bilearner.com | H51: TNS | I51: Voluntarily Terminated | J51: Contract | K51: Zone B | L51: Temporary | M51: Unk | N51: N/A | O51: Software Engineering | P51: Finance & Accounting | Q51: 34154 | R51: MA | S51: Accounting | T51: Male | U51: 64114 | V51: Black | W51: Widowed | X51: Fully Meets | Y51: 3
A52: 1051 | B52: Devon Hinton | C52: 44659 | D52: 44937 | E52: Software Engineer | F52: Allison York | G52: taylor.sanders@bilearner.com | H52: PYZ | I52: Terminated for Cause | J52: Full-Time | K52: Zone C | L52: Part-Time | M52: Involuntary | N52: Her office place. | O52: Software Engineering | P52: Field Operations | Q52: 29705 | R52: MA | S52: Operator | T52: Male | U52: 14669 | V52: White | W52: Divorced | X52: Fully Meets | Y52: 3
A53: 1052 | B53: Jacquelyn Johns | C53: 44252 | D53: 44351 | E53: Shared Services Manager | F53: Christopher Romero | G53: ava.pace@bilearner.com | H53: WBL | I53: Voluntarily Terminated | J53: Contract | K53: Zone B | L53: Part-Time | M53: Voluntary | N53: Plant enjoy these drive themselves never hit PM. | O53: Software Engineering | P53: General - Con | Q53: 29393 | R53: MA | S53: Foreman | T53: Female | U53: 52448 | V53: Hispanic | W53: Single | X53: Fully Meets | Y53: 3
A54: 1053 | B54: Blaine Keith | C54: 43537 | D54: 44293 | E54: Shared Services Manager | F54: Timothy Hansen | G54: delaney.bruce@bilearner.com | H54: NEL | I54: Voluntarily Terminated | J54: Contract | K54: Zone C | L54: Full-Time | M54: Resignation | N54: Wind commercial in ahead will realize. | O54: Software Engineering | P54: Project Management - Con | Q54: 17373 | R54: MA | S54: Project Manager | T54: Female | U54: 43336 | V54: Hispanic | W54: Divorced | X54: Fully Meets | Y54: 3
A55: 1054 | B55: Phillip Salazar | C55: 44969 | D55: N/A | E55: Software Engineer | F55: Christopher Romero | G55: jair.bullock@bilearner.com | H55: PL | I55: Voluntarily Terminated | J55: Part-Time | K55: Zone A | L55: Full-Time | M55: Unk | N55: N/A | O55: Software Engineering | P55: Engineers | Q55: 34099 | R55: MA | S55: Project Manager | T55: Male | U55: 56271 | V55: White | W55: Single | X55: Fully Meets | Y55: 3
A56: 1055 | B56: Chaz Webb | C56: 43351 | D56: N/A | E56: Software Engineer | F56: Alec Hernandez | G56: kayla.farrell@bilearner.com | H56: PYZ | I56: Terminated for Cause | J56: Contract | K56: Zone C | L56: Full-Time | M56: Unk | N56: N/A | O56: Software Engineering | P56: Field Operations | Q56: 35027 | R56: MA | S56: Laborer | T56: Female | U56: 56708 | V56: White | W56: Widowed | X56: Fully Meets | Y56: 3
A57: 1056 | B57: Desmond Anderson | C57: 44518 | D57: N/A | E57: Software Engineer | F57: Kari Bishop | G57: carl.desimone@bilearner.com | H57: SVG | I57: Voluntarily Terminated | J57: Contract | K57: Zone C | L57: Temporary | M57: Unk | N57: N/A | O57: Software Engineering | P57: Wireline Construction | Q57: 15950 | R57: MA | S57: Driver | T57: Male | U57: 12869 | V57: Hispanic | W57: Widowed | X57: Fully Meets | Y57: 3
A58: 1057 | B58: Sophie Decker | C58: 45108 | D58: N/A | E58: Software Engineer | F58: Justin Grant | G58: linda.anderson@bilearner.com | H58: TNS | I58: Voluntarily Terminated | J58: Full-Time | K58: Zone A | L58: Full-Time | M58: Unk | N58: N/A | O58: Software Engineering | P58: Wireline Construction | Q58: 36095 | R58: MA | S58: Foreman | T58: Male | U58: 18240 | V58: Asian | W58: Widowed | X58: Fully Meets | Y58: 3
A59: 1058 | B59: Lena Bryan | C59: 44669 | D59: N/A | E59: Software Engineer | F59: Sarah Sims | G59: nilson.fernandes@bilearner.com | H59: WBL | I59: Voluntarily Terminated | J59: Contract | K59: Zone C | L59: Temporary | M59: Unk | N59: N/A | O59: Software Engineering | P59: Billable Consultants | Q59: 15413 | R59: MA | S59: Technician | T59: Male | U59: 77311 | V59: Hispanic | W59: Married | X59: Fully Meets | Y59: 3
A60: 1059 | B60: Kelsie Mccormick | C60: 45045 | D60: N/A | E60: Software Engineer | F60: Emily Brennan | G60: alain.robinson@bilearner.com | H60: BPC | I60: Voluntarily Terminated | J60: Part-Time | K60: Zone C | L60: Full-Time | M60: Unk | N60: N/A | O60: Software Engineering | P60: Engineers | Q60: 27172 | R60: MA | S60: Engineer | T60: Female | U60: 63959 | V60: Asian | W60: Widowed | X60: Fully Meets | Y60: 3
A61: 1060 | B61: Frida Livingston | C61: 43383 | D61: 43459 | E61: Shared Services Manager | F61: Sandra Black | G61: seffi.shields@bilearner.com | H61: CCDR | I61: Voluntarily Terminated | J61: Part-Time | K61: Zone B | L61: Full-Time | M61: Voluntary | N61: Improve center sure Mr respond for recent. | O61: Software Engineering | P61: General - Con | Q61: 27795 | R61: MA | S61: Project Manager | T61: Female | U61: 20331 | V61: Black | W61: Single | X61: Fully Meets | Y61: 3
A62: 1061 | B62: Isai Alvarado | C62: 44885 | D62: N/A | E62: Shared Services Manager | F62: Laura Norman | G62: samuel.maclennan@bilearner.com | H62: EW | I62: Voluntarily Terminated | J62: Part-Time | K62: Zone C | L62: Part-Time | M62: Unk | N62: N/A | O62: Software Engineering | P62: General - Sga | Q62: 34110 | R62: MA | S62: Specialist | T62: Female | U62: 45515 | V62: Other | W62: Single | X62: Fully Meets | Y62: 3
A63: 1062 | B63: Travis Vasquez | C63: 43603 | D63: 43844 | E63: Software Engineer | F63: Amanda Hale | G63: shakira.perry@bilearner.com | H63: BPC | I63: Voluntarily Terminated | J63: Part-Time | K63: Zone A | L63: Part-Time | M63: Involuntary | N63: Rise activity learn step power simple sure. | O63: Software Engineering | P63: Engineers | Q63: 25510 | R63: MA | S63: Program Manager | T63: Male | U63: 59717 | V63: Hispanic | W63: Married | X63: Fully Meets | Y63: 3
A64: 1063 | B64: Jazlene Maynard | C64: 44369 | D64: N/A | E64: Software Engineer | F64: James Baker | G64: enola.chivukula@bilearner.com | H64: CCDR | I64: Terminated for Cause | J64: Full-Time | K64: Zone B | L64: Temporary | M64: Unk | N64: N/A | O64: Software Engineering | P64: Aerial | Q64: 16546 | R64: MA | S64: Foreman | T64: Female | U64: 15748 | V64: Black | W64: Single | X64: Fully Meets | Y64: 3
A65: 1064 | B65: Wyatt Donovan | C65: 44650 | D65: 44664 | E65: Software Engineer | F65: Terry Durham | G65: alexandra.kirill@bilearner.com | H65: SVG | I65: Voluntarily Terminated | J65: Part-Time | K65: Zone A | L65: Part-Time | M65: Retirement | N65: North help rock stage someone book. | O65: Software Engineering | P65: Field Operations | Q65: 31832 | R65: MA | S65: Technician | T65: Male | U65: 67106 | V65: White | W65: Divorced | X65: Fully Meets | Y65: 3
A66: 1065 | B66: Nathaly Cooper | C66: 43340 | D66: N/A | E66: Software Engineer | F66: Erik Simon | G66: ryker.logan@bilearner.com | H66: EW | I66: Voluntarily Terminated | J66: Contract | K66: Zone C | L66: Temporary | M66: Unk | N66: N/A | O66: Software Engineering | P66: Engineers | Q66: 34876 | R66: MA | S66: Engineer | T66: Male | U66: 33438 | V66: Other | W66: Widowed | X66: Fully Meets | Y66: 3
A67: 1066 | B67: Gage Weeks | C67: 44557 | D67: 44931 | E67: Software Engineer | F67: Summer Moreno | G67: payten.middleton@bilearner.com | H67: MSC | I67: Voluntarily Terminated | J67: Full-Time | K67: Zone C | L67: Temporary | M67: Voluntary | N67: Face garden central since several food. | O67: Software Engineering | P67: Catv | Q67: 29699 | R67: MA | S67: Operator | T67: Male | U67: 61106 | V67: Hispanic | W67: Single | X67: Fully Meets | Y67: 3
A68: 1067 | B68: Gavin Frye | C68: 44149 | D68: N/A | E68: Software Engineer | F68: Carla Cox | G68: harrison.hunt@bilearner.com | H68: TNS | I68: Voluntarily Terminated | J68: Part-Time | K68: Zone A | L68: Temporary | M68: Unk | N68: N/A | O68: Software Engineering | P68: Field Operations | Q68: 17874 | R68: MA | S68: Technician | T68: Female | U68: 25160 | V68: White | W68: Married | X68: Fully Meets | Y68: 3
A69: 1068 | B69: Amber Ross | C69: 44470 | D69: N/A | E69: Software Engineer | F69: Mary Mendoza | G69: orlando.henderson@bilearner.com | H69: PYZ | I69: Voluntarily Terminated | J69: Full-Time | K69: Zone B | L69: Part-Time | M69: Unk | N69: N/A | O69: Software Engineering | P69: Wireline Construction | Q69: 36153 | R69: MA | S69: Project Manager | T69: Female | U69: 52694 | V69: Black | W69: Widowed | X69: Fully Meets | Y69: 3
A70: 1069 | B70: Wyatt Edwards | C70: 43386 | D70: 45074 | E70: Shared Services Manager | F70: Cassandra Smith | G70: sierra.macias@bilearner.com | H70: WBL | I70: Voluntarily Terminated | J70: Full-Time | K70: Zone B | L70: Part-Time | M70: Resignation | N70: Really full stand face explain would keep energy. | O70: Software Engineering | P70: General - Con | Q70: 27650 | R70: MA | S70: Foreman | T70: Female | U70: 30264 | V70: Other | W70: Widowed | X70: Fully Meets | Y70: 3
A71: 1070 | B71: Karla Reed | C71: 43449 | D71: 44709 | E71: Shared Services Manager | F71: Warren Baker | G71: pierce.robbins@bilearner.com | H71: NEL | I71: Voluntarily Terminated | J71: Full-Time | K71: Zone C | L71: Temporary | M71: Resignation | N71: Or add data indicate account father early these. | O71: Software Engineering | P71: General - Sga | Q71: 36103 | R71: MA | S71: Project Manager | T71: Male | U71: 22326 | V71: Black | W71: Married | X71: Fully Meets | Y71: 3
A72: 1071 | B72: Yadira Mcmillan | C72: 43552 | D72: 44121 | E72: Software Engineer | F72: Amy Bell | G72: gretchen.richard@bilearner.com | H72: PL | I72: Voluntarily Terminated | J72: Contract | K72: Zone A | L72: Part-Time | M72: Involuntary | N72: Guy ten dream. Thing he care series. | O72: Software Engineering | P72: Field Operations | Q72: 25012 | R72: MA | S72: Laborer | T72: Male | U72: 30139 | V72: Black | W72: Married | X72: Fully Meets | Y72: 3
A73: 1072 | B73: Fernando Mcconnell | C73: 43461 | D73: N/A | E73: Software Engineer | F73: Teresa Lopez | G73: maximilian.craig@bilearner.com | H73: BPC | I73: Voluntarily Terminated | J73: Part-Time | K73: Zone C | L73: Part-Time | M73: Unk | N73: N/A | O73: Software Engineering | P73: Field Operations | Q73: 28145 | R73: MA | S73: Operator | T73: Female | U73: 93329 | V73: Asian | W73: Widowed | X73: Fully Meets | Y73: 3
A74: 1073 | B74: Sean Bean | C74: 43596 | D74: N/A | E74: Software Engineer | F74: Kimberly Holland | G74: raymond.ayers@bilearner.com | H74: CCDR | I74: Terminated for Cause | J74: Full-Time | K74: Zone A | L74: Full-Time | M74: Unk | N74: N/A | O74: Software Engineering | P74: Field Operations | Q74: 36062 | R74: MA | S74: Foreman | T74: Male | U74: 67825 | V74: White | W74: Single | X74: Fully Meets | Y74: 3
A75: 1074 | B75: Lilianna Mccall | C75: 44246 | D75: 44981 | E75: Software Engineer | F75: Robert Garcia | G75: vincent.wyatt@bilearner.com | H75: SVG | I75: Terminated for Cause | J75: Full-Time | K75: Zone A | L75: Temporary | M75: Voluntary | N75: Professional usually hospital worker among. | O75: Software Engineering | P75: General - Con | Q75: 30505 | R75: MA | S75: Laborer | T75: Male | U75: 86545 | V75: Asian | W75: Divorced | X75: Fully Meets | Y75: 3
A76: 1075 | B76: Salvador Thomas | C76: 44870 | D76: 45032 | E76: Software Engineer | F76: Nicholas Martinez | G76: micah.stanley@bilearner.com | H76: EW | I76: Voluntarily Terminated | J76: Part-Time | K76: Zone B | L76: Full-Time | M76: Involuntary | N76: Health American identify meeting. | O76: Software Engineering | P76: Engineers | Q76: 24951 | R76: MA | S76: Engineer | T76: Male | U76: 76670 | V76: Asian | W76: Married | X76: Fully Meets | Y76: 3
A77: 1076 | B77: Jair Silva | C77: 43912 | D77: 44102 | E77: Software Engineer | F77: Carlos Barnes | G77: calvin.braun@bilearner.com | H77: MSC | I77: Terminated for Cause | J77: Contract | K77: Zone C | L77: Part-Time | M77: Retirement | N77: Gun bill spend anyone. | O77: Software Engineering | P77: General - Eng | Q77: 15734 | R77: MA | S77: Administrative | T77: Female | U77: 29368 | V77: White | W77: Widowed | X77: Fully Meets | Y77: 3
A78: 1077 | B78: Derek Moreno | C78: 43498 | D78: N/A | E78: Software Engineer | F78: Allison Jacobs | G78: cale.bender@bilearner.com | H78: TNS | I78: Terminated for Cause | J78: Contract | K78: Zone B | L78: Temporary | M78: Unk | N78: N/A | O78: Software Engineering | P78: Wireless | Q78: 33734 | R78: MA | S78: Foreman | T78: Female | U78: 97585 | V78: Black | W78: Single | X78: Fully Meets | Y78: 3
A79: 1078 | B79: Litzy Conner | C79: 43885 | D79: 44363 | E79: Software Engineer | F79: Angela Ramsey | G79: elianna.schmitt@bilearner.com | H79: PYZ | I79: Voluntarily Terminated | J79: Contract | K79: Zone C | L79: Temporary | M79: Voluntary | N79: Crime west best industry right alone begin. | O79: Software Engineering | P79: Aerial | Q79: 35508 | R79: MA | S79: Foreman | T79: Female | U79: 42710 | V79: Asian | W79: Divorced | X79: Fully Meets | Y79: 3
A80: 1079 | B80: Joanna Burnett | C80: 44293 | D80: 44682 | E80: Shared Services Manager | F80: Malik Smith | G80: ernest.willis@bilearner.com | H80: WBL | I80: Voluntarily Terminated | J80: Part-Time | K80: Zone B | L80: Full-Time | M80: Resignation | N80: Story knowledge policy. Board tax treatment. | O80: Software Engineering | P80: Project Management - Eng | Q80: 36627 | R80: MA | S80: Manager | T80: Female | U80: 21279 | V80: Hispanic | W80: Divorced | X80: Fully Meets | Y80: 3
A81: 1080 | B81: Abdullah Frederick | C81: 44149 | D81: N/A | E81: Shared Services Manager | F81: Jessica Lewis | G81: davis.roberts@bilearner.com | H81: NEL | I81: Voluntarily Terminated | J81: Part-Time | K81: Zone C | L81: Full-Time | M81: Unk | N81: N/A | O81: Software Engineering | P81: Fielders | Q81: 32359 | R81: MA | S81: Engineer | T81: Male | U81: 17976 | V81: Black | W81: Widowed | X81: Fully Meets | Y81: 3
A82: 1081 | B82: Armani Porter | C82: 44578 | D82: 44783 | E82: Software Engineer | F82: Kayla Ibarra | G82: meadow.avery@bilearner.com | H82: EW | I82: Voluntarily Terminated | J82: Contract | K82: Zone B | L82: Part-Time | M82: Involuntary | N82: Imagine plant southern sound reduce. | O82: Software Engineering | P82: General - Con | Q82: 23978 | R82: MA | S82: Laborer | T82: Male | U82: 53628 | V82: Asian | W82: Divorced | X82: Fully Meets | Y82: 3
A83: 1082 | B83: Taylor Sanders | C83: 44441 | D83: 45104 | E83: Software Engineer | F83: Ryan Mathews | G83: allyson.owen@bilearner.com | H83: MSC | I83: Voluntarily Terminated | J83: Part-Time | K83: Zone B | L83: Part-Time | M83: Retirement | N83: Resource top fear shake green view great which. | O83: Software Engineering | P83: General - Con | Q83: 27822 | R83: MA | S83: Technician | T83: Male | U83: 84761 | V83: Other | W83: Married | X83: Fully Meets | Y83: 3
A84: 1083 | B84: Iliana Randall | C84: 45137 | D84: N/A | E84: Software Engineer | F84: Melissa Scott | G84: francisco.simon@bilearner.com | H84: NEL | I84: Voluntarily Terminated | J84: Part-Time | K84: Zone A | L84: Full-Time | M84: Unk | N84: N/A | O84: Software Engineering | P84: Aerial | Q84: 23020 | R84: MA | S84: Supervisor | T84: Female | U84: 2187 | V84: Asian | W84: Divorced | X84: Fully Meets | Y84: 3
A85: 1084 | B85: Luke Henderson | C85: 45104 | D85: N/A | E85: Software Engineer | F85: Robert Schmitt | G85: chaya.boyd@bilearner.com | H85: PL | I85: Voluntarily Terminated | J85: Contract | K85: Zone C | L85: Part-Time | M85: Unk | N85: N/A | O85: Software Engineering | P85: Executive | Q85: 32732 | R85: MA | S85: Administrator | T85: Male | U85: 76615 | V85: White | W85: Single | X85: Fully Meets | Y85: 3
A86: 1085 | B86: Madelyn Lambert | C86: 44647 | D86: N/A | E86: Software Engineer | F86: Patricia Wallace | G86: wyatt.spence@bilearner.com | H86: PYZ | I86: Voluntarily Terminated | J86: Contract | K86: Zone B | L86: Full-Time | M86: Unk | N86: N/A | O86: Software Engineering | P86: General - Con | Q86: 19063 | R86: MA | S86: Lineman | T86: Male | U86: 18707 | V86: Other | W86: Divorced | X86: Fully Meets | Y86: 3
A87: 1086 | B87: Ava Pace | C87: 44785 | D87: 44854 | E87: Software Engineer | F87: Justin Young | G87: jayleen.oconnell@bilearner.com | H87: SVG | I87: Voluntarily Terminated | J87: Contract | K87: Zone A | L87: Temporary | M87: Voluntary | N87: Thousand both simple network let. | O87: Software Engineering | P87: Field Operations | Q87: 26875 | R87: MA | S87: Supervisor | T87: Female | U87: 23203 | V87: Black | W87: Single | X87: Fully Meets | Y87: 3
A88: 1087 | B88: Delaney Bruce | C88: 44750 | D88: 45142 | E88: Software Engineer | F88: Robert Salinas | G88: carlie.wilkerson@bilearner.com | H88: TNS | I88: Voluntarily Terminated | J88: Part-Time | K88: Zone A | L88: Part-Time | M88: Voluntary | N88: Party explain perhaps. | O88: Software Engineering | P88: Field Operations | Q88: 27246 | R88: MA | S88: Tower Hand | T88: Female | U88: 18844 | V88: Other | W88: Married | X88: Fully Meets | Y88: 3
A89: 1088 | B89: Jair Bullock | C89: 44058 | D89: 44219 | E89: Software Engineer | F89: Mary Anderson | G89: kaylyn.patrick@bilearner.com | H89: WBL | I89: Voluntarily Terminated | J89: Contract | K89: Zone B | L89: Part-Time | M89: Resignation | N89: Specific fire rate fly clearly. | O89: Software Engineering | P89: General - Con | Q89: 33336 | R89: MA | S89: Foreman | T89: Female | U89: 64815 | V89: White | W89: Widowed | X89: Fully Meets | Y89: 3
A90: 1089 | B90: Kayla Farrell | C90: 45073 | D90: 45091 | E90: Software Engineer | F90: Jennifer Stevens | G90: evie.pope@bilearner.com | H90: BPC | I90: Voluntarily Terminated | J90: Full-Time | K90: Zone A | L90: Temporary | M90: Involuntary | N90: Your plant win seem hair him career style. | O90: Software Engineering | P90: Wireline Construction | Q90: 19478 | R90: MA | S90: Groundman | T90: Female | U90: 69860 | V90: Black | W90: Married | X90: Fully Meets | Y90: 3
A91: 1090 | B91: Taylor Gamble | C91: 44928 | D91: N/A | E91: Shared Services Manager | F91: Jennifer Murphy | G91: nayeli.kelley@bilearner.com | H91: CCDR | I91: Voluntarily Terminated | J91: Part-Time | K91: Zone C | L91: Full-Time | M91: Unk | N91: N/A | O91: Software Engineering | P91: Field Operations | Q91: 23982 | R91: MA | S91: Technician | T91: Female | U91: 93542 | V91: Black | W91: Divorced | X91: Fully Meets | Y91: 3
A92: 1091 | B92: Carl Desimone | C92: 43420 | D92: 44289 | E92: Production Technician I | F92: Daniel Booth | G92: dorian.fox@bilearner.com | H92: PYZ | I92: Voluntarily Terminated | J92: Contract | K92: Zone B | L92: Temporary | M92: Involuntary | N92: Fine use card current agent. | O92: Production | P92: General - Sga | Q92: 31650 | R92: MA | S92: Supervisor | T92: Male | U92: 2061 | V92: Asian | W92: Single | X92: Fully Meets | Y92: 3
A93: 1092 | B93: Sophia Theamstern | C93: 44754 | D93: N/A | E93: Production Technician I | F93: Martin Jackson | G93: gunnar.webster@bilearner.com | H93: PYZ | I93: Voluntarily Terminated | J93: Part-Time | K93: Zone C | L93: Full-Time | M93: Unk | N93: N/A | O93: Production | P93: Field Operations | Q93: 25595 | R93: MA | S93: Clerk | T93: Female | U93: 2066 | V93: Hispanic | W93: Divorced | X93: Fully Meets | Y93: 3
A94: 1093 | B94: Kara Harrison | C94: 44911 | D94: N/A | E94: Production Technician I | F94: Elizabeth Richards | G94: patrick.mckinney@bilearner.com | H94: NEL | I94: Voluntarily Terminated | J94: Contract | K94: Zone B | L94: Part-Time | M94: Unk | N94: N/A | O94: Production | P94: Engineers | Q94: 28971 | R94: MA | S94: Engineer | T94: Female | U94: 1886 | V94: Asian | W94: Widowed | X94: Fully Meets | Y94: 3
A95: 1094 | B95: Ming Huynh | C95: 45054 | D95: N/A | E95: Production Technician II | F95: Jose Bray | G95: reagan.odonnell@bilearner.com | H95: EW | I95: Terminated for Cause | J95: Part-Time | K95: Zone A | L95: Full-Time | M95: Unk | N95: N/A | O95: Production | P95: Field Operations | Q95: 34411 | R95: MA | S95: Foreman | T95: Female | U95: 1742 | V95: Other | W95: Single | X95: Fully Meets | Y95: 3
A96: 1095 | B96: Karen Mancuso | C96: 45023 | D96: N/A | E96: Production Technician II | F96: Jamie Frye | G96: roy.morse@bilearner.com | H96: WBL | I96: Voluntarily Terminated | J96: Full-Time | K96: Zone A | L96: Temporary | M96: Unk | N96: N/A | O96: Production | P96: Engineers | Q96: 15308 | R96: MA | S96: Engineer | T96: Female | U96: 2176 | V96: Hispanic | W96: Divorced | X96: Fully Meets | Y96: 3
A97: 1096 | B97: Linda Anderson | C97: 44607 | D97: 44853 | E97: Production Technician I | F97: Adam Hunt | G97: rafael.buchanan@bilearner.com | H97: PYZ | I97: Voluntarily Terminated | J97: Part-Time | K97: Zone C | L97: Part-Time | M97: Voluntary | N97: Issue loss day provide everyone white. | O97: Production | P97: Shop (Fleet) | Q97: 26675 | R97: MA | S97: Mechanic | T97: Female | U97: 1844 | V97: Asian | W97: Married | X97: Fully Meets | Y97: 3
A98: 1097 | B98: Nilson Fernandes | C98: 45124 | D98: 45141 | E98: Production Technician I | F98: Jeffrey Saunders | G98: jamarion.mitchell@bilearner.com | H98: SVG | I98: Voluntarily Terminated | J98: Contract | K98: Zone B | L98: Part-Time | M98: Involuntary | N98: Blue star hospital work. | O98: Production | P98: Field Operations | Q98: 36374 | R98: MA | S98: Technician | T98: Male | U98: 2132 | V98: Hispanic | W98: Divorced | X98: Fully Meets | Y98: 3
A99: 1098 | B99: Alain Robinson | C99: 43588 | D99: 45079 | E99: Production Technician I | F99: Stephanie Griffin | G99: gabrielle.hardy@bilearner.com | H99: PL | I99: Voluntarily Terminated | J99: Part-Time | K99: Zone A | L99: Temporary | M99: Involuntary | N99: Meet fight night. Image room nation. | O99: Production | P99: General - Eng | Q99: 33979 | R99: MA | S99: Engineer | T99: Male | U99: 1420 | V99: Asian | W99: Widowed | X99: Fully Meets | Y99: 3
A100: 1099 | B100: Seffi Shields | C100: 44645 | D100: 44673 | E100: Production Technician I | F100: Robert Sullivan | G100: savion.stokes@bilearner.com | H100: SVG | I100: Voluntarily Terminated | J100: Part-Time | K100: Zone A | L100: Part-Time | M100: Retirement | N100: Person say might throw war scientist. | O100: Production | P100: Field Operations | Q100: 26291 | R100: MA | S100: Laborer | T100: Female | U100: 2149 | V100: Other | W100: Single | X100: Fully Meets | Y100: 3
...

Sheet training_and_development
A1: Employee ID | B1: Training Date | C1: Training Program Name | D1: Training Type | E1: Training Outcome | F1: Location | G1: Trainer | H1: Training Duration(Days) | I1: Training Cost
A2: 1001 | B2: 44825 | C2: Customer Service | D2: Internal | E2: Failed | F2: Port Greg | G2: Amanda Daniels | H2: 4 | I2: 510.83
A3: 1002 | B3: 45126 | C3: Leadership Development | D3: Internal | E3: Failed | F3: Brandonview | G3: Brittany Chambers | H3: 2 | I3: 582.37
A4: 1003 | B4: 44981 | C4: Technical Skills | D4: Internal | E4: Failed | F4: Port Briannahaven | G4: Mark Roberson | H4: 4 | I4: 777.06
A5: 1004 | B5: 45261 | C5: Customer Service | D5: Internal | E5: Completed | F5: Knightborough | G5: Richard Fisher | H5: 2 | I5: 824.3
A6: 1005 | B6: 45265 | C6: Communication Skills | D6: External | E6: Completed | F6: Bruceshire | G6: Heather Shaffer | H6: 4 | I6: 145.99
A7: 1006 | B7: 45143 | C7: Project Management | D7: Internal | E7: Failed | F7: Erinfort | G7: Michael Duke | H7: 2 | I7: 838.07
A8: 1007 | B8: 45060 | C8: Leadership Development | D8: External | E8: Failed | F8: New Christopher | G8: Virginia Clayton DVM | H8: 2 | I8: 667.32
A9: 1008 | B9: 44965 | C9: Technical Skills | D9: External | E9: Failed | F9: Lowemouth | G9: Erica Maxwell | H9: 2 | I9: 758.18
A10: 1009 | B10: 44794 | C10: Customer Service | D10: Internal | E10: Failed | F10: Johnland | G10: Katelyn Hartman | H10: 2 | I10: 101.21
A11: 1010 | B11: 44792 | C11: Communication Skills | D11: External | E11: Failed | F11: Lake Kimfurt | G11: Rhonda Clark | H11: 5 | I11: 332.25
A12: 1011 | B12: 44723 | C12: Communication Skills | D12: Internal | E12: Completed | F12: Smithshire | G12: Natalie Fields | H12: 1 | I12: 803.98
A13: 1012 | B13: 45013 | C13: Technical Skills | D13: External | E13: Failed | F13: Howardburgh | G13: Theresa Martinez | H13: 3 | I13: 887.08
... A3001: 4000 | B3001: 44722 | C3001: Leadership Development | D3001: Internal | E3001: Completed | F3001: Jamesfurt | G3001: Michael Mckenzie | H3001: 4 | I3001: 951.27

Sheet employee_engagement survey data
A1: Employee ID | B1: Survey Date | C1: Engagement Score | D1: Satisfaction Score | E1: Work/Life Balance Score
A2: 1001 | B2: 44844 | C2: 2 | D2: 5 | E2: 5 | I2: Calculation table | J2: Column1
A3: 1002 | B3: 45141 | C3: 4 | D3: 5 | E3: 3 | I3: Engagement_Total | J3: =SUM(Table3[Engagement Score]) -> 8819
A4: 1003 | B4: 44929 | C4: 2 | D4: 5 | E4: 2 | I4: Engagement_ Average | J4: =AVERAGE(Table3[Engagement Score]) -> 2.9396667
A5: 1004 | B5: 45137 | C5: 3 | D5: 5 | E5: 3 | I5: Total_Satisfaction_Score | J5: =SUM(Table3[Satisfaction Score]) -> 9066
A6: 1005 | B6: 45096 | C6: 2 | D6: 4 | E6: 5 | I6: Average_Satisfaction_Score | J6: =AVERAGE(Table3[Satisfaction Score]) -> 3.022
A7: 1006 | B7: 45049 | C7: 5 | D7: 2 | E7: 1 | I7: Total_Work/Life Balance Score | J7: =SUM(Table3[Work/Life Balance Score]) -> 8967
A8: 1007 | B8: 45125 | C8: 2 | D8: 1 | E8: 5 | I8: Average_Work/Life_Score | J8: =AVERAGE(Table3[Work/Life Balance Score]) -> 2.989
A9: 1008 | B9: 45098 | C9: 5 | D9: 2 | E9: 2
A10: 1009 | B10: 45083 | C10: 2 | D10: 5 | E10: 1
A11: 1010 | B11: 44819 | C11: 2 | D11: 4 | E11: 2
A12: 1011 | B12: 44903 | C12: 1 | D12: 2 | E12: 3
A13: 1012 | B13: 44939 | C13: 3 | D13: 5 | E13: 4
A14: 1013 | B14: 44908 | C14: 5 | D14: 4 | E14: 3
A15: 1014 | B15: 45105 | C15: 4 | D15: 4 | E15: 1
A16: 1015 | B16: 45118 | C16: 1 | D16: 1 | E16: 3
A17: 1016 | B17: 44904 | C17: 2 | D17: 3 | E17: 2
A18: 1017 | B18: 45123 | C18: 4 | D18: 1 | E18: 3
A19: 1018 | B19: 45098 | C19: 4 | D19: 1 | E19: 4
A20: 1019 | B20: 45098 | C20: 1 | D20: 3 | E20: 5
... A3001: 4000 | B3001: 45037 | C3001: 3 | D3001: 2 | E3001: 1

Sheet recruitment_data
A1: Applicant ID | B1: Application Date | C1: Full Name | D1: Gender | E1: Date of Birth | F1: Phone | G1: Email | H1: Address | I1: City | J1: State | K1: Zip Code | L1: Country | M1: Education Level | N1: Years of Experience | O1: Desired Salary | P1: Job Title | Q1: Status
A2: 1001 | B2: 45080 | C2: Scott Sheppard | D2: Male | E2: 33847 | F2: 4214297655x39421 | G2: perezjanet@example.org | H2: 597, Smith Point | I2: Hollandfort | J2: NV | K2: 57588 | L2: Micronesia | M2: High School | N2: 8 | O2: 60103.21 | P2: Chief Technology Officer | Q2: Interviewing
A3: 1002 | B3: 45061 | C3: Stanley Lewis | D3: Male | E3: 23861 | F3: 14515745308x1681 | G3: grossmark@example.com | H3: 8116, Stuart Loop | I3: Port Margaretfurt | J3: TN | K3: 14726 | L3: Greenland | M3: Bachelor's Degree | N3: 17 | O3: 64575.84 | P3: Designer, furniture | Q3: Rejected
A4: 1003 | B4: 45142 | C4: Javier Li | D4: Female | E4: 26733 | F4: 8589015499 | G4: katiemaldonado@example.com | H4: 5940, Barr Villages Suite 075 | I4: Dianaland | J4: TX | K4: 4699 | L4: China | M4: PhD | N4: 20 | O4: 39422.71 | P4: Sound technician, broadcasting/film/video | Q4: Rejected
A5: 1004 | B5: 45135 | C5: Christopher Johnston | D5: Other | E5: 36985 | F5: 8536811839x2010 | G5: sheila73@example.com | H5: 442, Lewis Mount | I5: Youngfurt | J5: GA | K5: 34455 | L5: Ghana | M5: High School | N5: 8 | O5: 51045.11 | P5: Air cabin crew | Q5: Rejected
A6: 1005 | B6: 45082 | C6: Melissa Hicks | D6: Other | E6: 28658 | F6: 3645758478x67812 | G6: emilypatterson@example.org | H6: 95961, Taylor Circles Apt. 169 | I6: East Ashleyborough | J6: IN | K6: 21014 | L6: Solomon Islands | M6: Master's Degree | N6: 0 | O6: 52792.86 | P6: Art therapist | Q6: Interviewing
A7: 1006 | B7: 45133 | C7: Christian Maddox | D7: Female | E7: 30481 | F7: 8949402919 | G7: pvelasquez@example.net | H7: 3030, Bell Islands | I7: Boonefort | J7: NC | K7: 34763 | L7: Liberia | M7: Master's Degree | N7: 18 | O7: 97746.62 | P7: Engineer, electronics | Q7: In Review
A8: 1007 | B8: 45086 | C8: Paul Hammond | D8: Female | E8: 23239 | F8: Unknown | G8: aclayton@example.net | H8: 58473, Jenna Trail | I8: Port Barry | J8: GA | K8: 57472 | L8: Congo | M8: High School | N8: 11 | O8: 80119.39 | P8: Scientist, research (maths) | Q8: Offered
A9: 1008 | B9: 45122 | C9: Madison Williamson | D9: Male | E9: 28740 | F9: 0019029929557x692 | G9: jeffreyellis@example.com | H9: 24740, Gregory Stravenue Suite 212 | I9: New Luisfort | J9: VA | K9: 71682 | L9: Pitcairn Islands | M9: Bachelor's Degree | N9: 0 | O9: 41578.78 | P9: Teacher, primary school | Q9: Offered
A10: 1009 | B10: 45093 | C10: Rachael Duran | D10: Male | E10: 35684 | F10: 17385836354x63335 | G10: hamptontimothy@example.net | H10: 375, Flowers Well | I10: Amandashire | J10: PW | K10: 25218 | L10: Spain | M10: High School | N10: 15 | O10: 44489.6 | P10: Phytotherapist | Q10: Interviewing
A11: 1010 | B11: 45071 | C11: Sherri Taylor | D11: Male | E11: 30430 | F11: 9153720499 | G11: cshaw@example.net | H11: 037, Quinn Route | I11: Garrisonmouth | J11: CA | K11: 82074 | L11: Gabon | M11: Master's Degree | N11: 4 | O11: 97363.53 | P11: Pilot, airline | Q11: Offered
A12: 1011 | B12: 45060 | C12: Jennifer Weaver | D12: Other | E12: 36090 | F12: 8524358495 | G12: sloankrista@example.org | H12: 700, Quinn Green Suite 066 | I12: Haileyville | J12: MS | K12: 37729 | L12: Switzerland | M12: PhD | N12: 19 | O12: 39252.38 | P12: Theatre director | Q12: In Review
A13: 1012 | B13: 45081 | C13: Kyle Blake | D13: Other | E13: 36975 | F13: 0015279079332x4819 | G13: shelia63@example.net | H13: 611, Thomas Dam Suite 296 | I13: East Melinda | J13: OH | K13: 62970 | L13: China | M13: Bachelor's Degree | N13: 7 | O13: 79650.82 | P13: Corporate treasurer | Q13: Applied
... A3001: 4000 | B3001: 45114 | C3001: Charles Hernandez | D3001: Female | E3001: 29373 | F3001: 7727672580 | G3001: murrayallison@example.com | H3001: 146, Cheryl Highway | I3001: Hallland | J3001: OR | K3001: 8592 | L3001: Netherlands | M3001: Bachelor's Degree | N3001: 1 | O3001: 89853.85 | P3001: Loss adjuster, chartered | Q3001: Rejected

Sheet VLOOKUP_table
A1: EmpID | B1: Full Name | C1: StartDate | D1: ExitDate | E1: Title | F1: Supervisor | G1: ADEmail | H1: BusinessUnit | I1: EmployeeStatus | J1: EmployeeType | K1: PayZone | L1: EmployeeClassificationType | M1: TerminationType | N1: TerminationDescription | O1: DepartmentType | P1: Division | Q1: DOB | R1: State | S1: JobFunctionDescription | T1: GenderCode | U1: LocationCode | V1: RaceDesc | W1: MaritalDesc | X1: Performance Score | Y1: Current Employee Rating | Z1: Engagement Score | AA1: Satisfaction Score | AB1: Work/Life Balance Score | AC1: Training Program Name | AD1: Training Type | AE1: Training Outcome | AF1: Location | AG1: Trainer | AH1: Training Duration(Days)
A2: 1001 | B2: Susan Exantus | C2: 43706 | D2: N/A | E2: Software Engineer | F2: Angela Carlson | G2: susan.exantus@bilearner.com | H2: BPC | I2: Active | J2: Part-Time | K2: Zone A | L2: Part-Time | M2: Unk | N2: N/A | O2: Software Engineering | P2: Engineers | Q2: 21084 | R2: MA | S2: Engineer | T2: Female | U2: 1749 | V2: Black | W2: Married | X2: Fully Meets | Y2: 3 | Z2: =VLOOKUP(A2,Table3[],3,0) -> 2 | AA2: =VLOOKUP(A2,'employee_engagement survey data'!A2:E466,4,0) -> 5 | AB2: =VLOOKUP(A2,'employee_engagement survey data'!A2:E241,5,0) -> 5 | AC2: =VLOOKUP(A2,training_and_development!A2:F39,3,0) -> Customer Service | AD2: =VLOOKUP(A2,training_and_development!A2:E391,4,0) -> Internal | AE2: =VLOOKUP(A2,training_and_development!A2:F2999,5,0) -> Failed | AF2: =VLOOKUP(A2,training_and_development!A1:G21,6,0) -> Port Greg | AG2: =VLOOKUP(A2,training_and_development!A2:H10,7,0) -> Amanda Daniels | AH2: =VLOOKUP(A2,training_and_development!A2:H5,8,0) -> 4
A3: 1002 | B3: Sandra Martin | C3: 44907 | D3: 45074 | E3: Software Engineer | F3: Angela Hayes | G3: sandra.martin@bilearner.com | H3: NEL | I3: Terminated for Cause | J3: Part-Time | K3: Zone A | L3: Temporary | M3: Involuntary | N3: Behind buy our of very claim. | O3: Software Engineering | P3: Catv | Q3: 18452 | R3: MA | S3: Foreman | T3: Female | U3: 2135 | V3: Asian | W3: Widowed | X3: Fully Meets | Y3: 3 | Z3: =VLOOKUP(A3,Table3[],3,0) -> 4 | AA3: =VLOOKUP(A3,'employee_engagement survey data'!A3:E467,4,0) -> 5 | AB3: =VLOOKUP(A3,'employee_engagement survey data'!A3:E242,5,0) -> 3 | AC3: =VLOOKUP(A3,training_and_development!A3:F40,3,0) -> Leadership Development | AD3: =VLOOKUP(A3,training_and_development!A3:E392,4,0) -> Internal | AE3: =VLOOKUP(A3,training_and_development!A3:F3000,5,0) -> Failed | AF3: =VLOOKUP(A3,training_and_development!A2:G22,6,0) -> Brandonview | AG3: =VLOOKUP(A3,training_and_development!A3:H11,7,0) -> Brittany Chambers | AH3: =VLOOKUP(A3,training_and_development!A3:H6,8,0) -> 2
A4: 1003 | B4: Keyla Del Bosque | C4: 44993 | D4: 45000 | E4: Software Engineer | F4: Christina Copeland | G4: keyla.delbosque@bilearner.com | H4: WBL | I4: Voluntarily Terminated | J4: Contract | K4: Zone A | L4: Part-Time | M4: Voluntary | N4: Some make teach quite range seem conference. | O4: Software Engineering | P4: Field Operations | Q4: 26991 | R4: MA | S4: Foreman | T4: Female | U4: 2176 | V4: White | W4: Married | X4: Fully Meets | Y4: 3 | Z4: =VLOOKUP(A4,Table3[],3,0) -> 2 | AA4: =VLOOKUP(A4,'employee_engagement survey data'!A4:E468,4,0) -> 5 | AB4: =VLOOKUP(A4,'employee_engagement survey data'!A4:E243,5,0) -> 2 | AC4: =VLOOKUP(A4,training_and_development!A4:F41,3,0) -> Technical Skills | AD4: =VLOOKUP(A4,training_and_development!A4:E393,4,0) -> Internal | AE4: =VLOOKUP(A4,training_and_development!A4:F3001,5,0) -> Failed | AF4: =VLOOKUP(A4,training_and_development!A3:G23,6,0) -> Port Briannahaven | AG4: =VLOOKUP(A4,training_and_development!A4:H12,7,0) -> Mark Roberson | AH4: =VLOOKUP(A4,training_and_development!A4:H7,8,0) -> 4
A5: 1004 | B5: Andrew Szabo | C5: 43980 | D5: 44260 | E5: Software Engineer | F5: Jennifer Cohen | G5: andrew.szabo@bilearner.com | H5: PYZ | I5: Terminated for Cause | J5: Part-Time | K5: Zone C | L5: Part-Time | M5: Involuntary | N5: Enter beautiful social store. | O5: Software Engineering | P5: Project Management - Con | Q5: 20847 | R5: MA | S5: Coordinator | T5: Male | U5: 2140 | V5: Black | W5: Single | X5: Fully Meets | Y5: 3 | Z5: =VLOOKUP(A5,Table3[],3,0) -> 3 | AA5: =VLOOKUP(A5,'employee_engagement survey data'!A5:E469,4,0) -> 5 | AB5: =VLOOKUP(A5,'employee_engagement survey data'!A5:E244,5,0) -> 3 | AC5: =VLOOKUP(A5,training_and_development!A5:F42,3,0) -> Customer Service | AD5: =VLOOKUP(A5,training_and_development!A5:E394,4,0) -> Internal | AE5: =VLOOKUP(A5,training_and_development!A5:F3002,5,0) -> Completed | AF5: =VLOOKUP(A5,training_and_development!A4:G24,6,0) -> Knightborough | AG5: =VLOOKUP(A5,training_and_development!A5:H13,7,0) -> Richard Fisher | AH5: =VLOOKUP(A5,training_and_development!A5:H8,8,0) -> 2
A6: 1005 | B6: Luke Patronick | C6: 44820 | D6: N/A | E6: Software Engineer | F6: Mr. Jesus Richards | G6: colby.andreola@bilearner.com | H6: SVG | I6: Voluntarily Terminated | J6: Full-Time | K6: Zone B | L6: S | M6: Unk | N6: N/A | O6: Software Engineering | P6: Field Operations | Q6: 25777 | R6: MA | S6: Project Manager | T6: Male | U6: 1844 | V6: Black | W6: Divorced | X6: Fully Meets | Y6: 3 | Z6: =VLOOKUP(A6,Table3[],3,0) -> 2 | AA6: =VLOOKUP(A6,'employee_engagement survey data'!A6:E470,4,0) -> 4 | AB6: =VLOOKUP(A6,'employee_engagement survey data'!A6:E245,5,0) -> 5 | AC6: =VLOOKUP(A6,training_and_development!A6:F43,3,0) -> Communication Skills | AD6: =VLOOKUP(A6,training_and_development!A6:E395,4,0) -> External | AE6: =VLOOKUP(A6,training_and_development!A6:F3003,5,0) -> Completed | AF6: =VLOOKUP(A6,training_and_development!A5:G25,6,0) -> Bruceshire | AG6: =VLOOKUP(A6,training_and_development!A6:H14,7,0) -> Heather Shaffer | AH6: =VLOOKUP(A6,training_and_development!A6:H9,8,0) -> 4
A7: 1006 | B7: Colby Andreola | C7: 44423 | D7: 44520 | E7: Software Engineer | F7: Beth Johnson | G7: edward.true@bilearner.com | H7: MSC | I7: Voluntarily Terminated | J7: Full-Time | K7: Zone C | L7: Part-Time | M7: Resignation | N7: Throughout yet in serious here wish. | O7: Software Engineering | P7: Engineers | Q7: 21600 | R7: MA | S7: Administrative | T7: Female | U7: 2110 | V7: White | W7: Widowed | X7: Fully Meets | Y7: 3 | Z7: =VLOOKUP(A7,Table3[],3,0) -> 5 | AA7: =VLOOKUP(A7,'employee_engagement survey data'!A7:E471,4,0) -> 2 | AB7: =VLOOKUP(A7,'employee_engagement survey data'!A7:E246,5,0) -> 1 | AC7: =VLOOKUP(A7,training_and_development!A7:F44,3,0) -> Project Management | AD7: =VLOOKUP(A7,training_and_development!A7:E396,4,0) -> Internal | AE7: =VLOOKUP(A7,training_and_development!A7:F3004,5,0) -> Failed | AF7: =VLOOKUP(A7,training_and_development!A6:G26,6,0) -> Erinfort | AG7: =VLOOKUP(A7,training_and_development!A7:H15,7,0) -> Michael Duke | AH7: =VLOOKUP(A7,training_and_development!A7:H10,8,0) -> 2
A8: 1007 | B8: Edward TRUE | C8: 44129 | D8: 44465 | E8: Software Engineer | F8: Raymond Adams | G8: judith.carabbio@bilearner.com | H8: SVG | I8: Voluntarily Terminated | J8: Part-Time | K8: Zone A | L8: Part-Time | M8: Involuntary | N8: Recently however meeting economic. | O8: Software Engineering | P8: General - Con | Q8: 36603 | R8: MA | S8: Lineman | T8: Male | U8: 2451 | V8: Black | W8: Widowed | X8: Fully Meets | Y8: 3 | Z8: =VLOOKUP(A8,Table3[],3,0) -> 2 | AA8: =VLOOKUP(A8,'employee_engagement survey data'!A8:E472,4,0) -> 1 | AB8: =VLOOKUP(A8,'employee_engagement survey data'!A8:E247,5,0) -> 5 | AC8: =VLOOKUP(A8,training_and_development!A8:F45,3,0) -> Leadership Development | AD8: =VLOOKUP(A8,training_and_development!A8:E397,4,0) -> External | AE8: =VLOOKUP(A8,training_and_development!A8:F3005,5,0) -> Failed | AF8: =VLOOKUP(A8,training_and_development!A7:G27,6,0) -> New Christopher | AG8: =VLOOKUP(A8,training_and_development!A8:H16,7,0) -> Virginia Clayton DVM | AH8: =VLOOKUP(A8,training_and_development!A8:H11,8,0) -> 2
A9: 1008 | B9: Judith Carabbio | C9: 43705 | D9: 43955 | E9: Software Engineer | F9: Jessica Rhodes | G9: adell.saada@bilearner.com | H9: BPC | I9: Voluntarily Terminated | J9: Contract | K9: Zone B | L9: Temporary | M9: Voluntary | N9: Instead story skill financial who. | O9: Software Engineering | P9: General - Con | Q9: 29941 | R9: MA | S9: Foreman | T9: Female | U9: 2132 | V9: Hispanic | W9: Married | X9: Fully Meets | Y9: 3 | Z9: =VLOOKUP(A9,Table3[],3,0) -> 5 | AA9: =VLOOKUP(A9,'employee_engagement survey data'!A9:E473,4,0) -> 2 | AB9: =VLOOKUP(A9,'employee_engagement survey data'!A9:E248,5,0) -> 2 | AC9: =VLOOKUP(A9,training_and_development!A9:F46,3,0) -> Technical Skills | AD9: =VLOOKUP(A9,training_and_development!A9:E398,4,0) -> External | AE9: =VLOOKUP(A9,training_and_development!A9:F3006,5,0) -> Failed | AF9: =VLOOKUP(A9,training_and_development!A8:G28,6,0) -> Lowemouth | AG9: =VLOOKUP(A9,training_and_development!A9:H17,7,0) -> Erica Maxwell | AH9: =VLOOKUP(A9,training_and_development!A9:H12,8,0) -> 2
A10: 1009 | B10: Adell Saada | C10: 43629 | D10: 44938 | E10: Software Engineer | F10: Steven Tran | G10: kamari.hunter@bilearner.com | H10: NEL | I10: Terminated for Cause | J10: Part-Time | K10: Zone C | L10: Temporary | M10: Retirement | N10: Exactly vote including easy. | O10: Software Engineering | P10: General - Con | Q10: 31837 | R10: MA | S10: Model Assistant | T10: Female | U10: 2132 | V10: Other | W10: Single | X10: Fully Meets | Y10: 3 | Z10: =VLOOKUP(A10,Table3[],3,0) -> 2 | AA10: =VLOOKUP(A10,'employee_engagement survey data'!A10:E474,4,0) -> 5 | AB10: =VLOOKUP(A10,'employee_engagement survey data'!A10:E249,5,0) -> 1 | AC10: =VLOOKUP(A10,training_and_development!A10:F47,3,0) -> Customer Service | AD10: =VLOOKUP(A10,training_and_development!A10:E399,4,0) -> Internal | AE10: =VLOOKUP(A10,training_and_development!A10:F3007,5,0) -> Failed | AF10: =VLOOKUP(A10,training_and_development!A9:G29,6,0) -> Johnland | AG10: =VLOOKUP(A10,training_and_development!A10:H18,7,0) -> Katelyn Hartman | AH10: =VLOOKUP(A10,training_and_development!A10:H13,8,0) -> 2
A11: 1010 | B11: Kamari Hunter | C11: 44208 | D11: 44638 | E11: Software Engineer | F11: Kristen Collier | G11: sarah.malone@bilearner.com | H11: EW | I11: Terminated for Cause | J11: Part-Time | K11: Zone C | L11: Temporary | M11: Voluntary | N11: West note present Mr woman family. | O11: Software Engineering | P11: Field Operations | Q11: 33898 | R11: MA | S11: Supervisor | T11: Male | U11: 12889 | V11: Hispanic | W11: Divorced | X11: Fully Meets | Y11: 3 | Z11: =VLOOKUP(A11,Table3[],3,0) -> 2 | AA11: =VLOOKUP(A11,'employee_engagement survey data'!A11:E475,4,0) -> 4 | AB11: =VLOOKUP(A11,'employee_engagement survey data'!A11:E250,5,0) -> 2 | AC11: =VLOOKUP(A11,training_and_development!A11:F48,3,0) -> Communication Skills | AD11: =VLOOKUP(A11,training_and_development!A11:E400,4,0) -> External | AE11: =VLOOKUP(A11,training_and_development!A11:F3008,5,0) -> Failed | AF11: =VLOOKUP(A11,training_and_development!A10:G30,6,0) -> Lake Kimfurt | AG11: =VLOOKUP(A11,training_and_development!A11:H19,7,0) -> Rhonda Clark | AH11: =VLOOKUP(A11,training_and_development!A11:H14,8,0) -> 5
A12: 1011 | B12: Sarah Malone | C12: 44599 | D12: 44969 | E12: Software Engineer | F12: David Lopez | G12: skyler.blackwell@bilearner.com | H12: MSC | I12: Terminated for Cause | J12: Contract | K12: Zone A | L12: Temporary | M12: Resignation | N12: Professor situation they bag interest there. | O12: Software Engineering | P12: General - Con | Q12: 17585 | R12: MA | S12: Foreman | T12: Male | U12: 21340 | V12: Hispanic | W12: Married | X12: Fully Meets | Y12: 3 | Z12: =VLOOKUP(A12,Table3[],3,0) -> 1 | AA12: =VLOOKUP(A12,'employee_engagement survey data'!A12:E476,4,0) -> 2 | AB12: =VLOOKUP(A12,'employee_engagement survey data'!A12:E251,5,0) -> 3 | AC12: =VLOOKUP(A12,training_and_development!A12:F49,3,0) -> Communication Skills | AD12: =VLOOKUP(A12,training_and_development!A12:E401,4,0) -> Internal | AE12: =VLOOKUP(A12,training_and_development!A12:F3009,5,0) -> Completed | AF12: =VLOOKUP(A12,training_and_development!A11:G31,6,0) -> Smithshire | AG12: =VLOOKUP(A12,training_and_development!A12:H20,7,0) -> Natalie Fields | AH12: =VLOOKUP(A12,training_and_development!A12:H15,8,0) -> 1
A13: 1012 | B13: Skyler Blackwell | C13: 44144 | D13: 44353 | E13: Software Engineer | F13: Candice Schmidt | G13: kole.quinn@bilearner.com | H13: TNS | I13: Voluntarily Terminated | J13: Contract | K13: Zone A | L13: Temporary | M13: Involuntary | N13: Get apply economy artist right benefit ground. | O13: Software Engineering | P13: General - Eng | Q13: 28766 | R13: MA | S13: Administrative | T13: Male | U13: 67544 | V13: White | W13: Single | X13: Fully Meets | Y13: 3 | Z13: =VLOOKUP(A13,Table3[],3,0) -> 3 | AA13: =VLOOKUP(A13,'employee_engagement survey data'!A13:E477,4,0) -> 5 | AB13: =VLOOKUP(A13,'employee_engagement survey data'!A13:E252,5,0) -> 4 | AC13: =VLOOKUP(A13,training_and_development!A13:F50,3,0) -> Technical Skills | AD13: =VLOOKUP(A13,training_and_development!A13:E402,4,0) -> External | AE13: =VLOOKUP(A13,training_and_development!A13:F3010,5,0) -> Failed | AF13: =VLOOKUP(A13,training_and_development!A12:G32,6,0) -> Howardburgh | AG13: =VLOOKUP(A13,training_and_development!A13:H21,7,0) -> Theresa Martinez | AH13: =VLOOKUP(A13,training_and_development!A13:H16,8,0) -> 3
A14: 1013 | B14: Jasmin Shah | C14: 43964 | D14: N/A | E14: Software Engineer | F14: Christy Craig | G14: jayda.reese@bilearner.com | H14: PYZ | I14: Terminated for Cause | J14: Part-Time | K14: Zone B | L14: Full-Time | M14: Unk | N14: N/A | O14: Software Engineering | P14: Engineers | Q14: 27352 | R14: MA | S14: Engineer | T14: Male | U14: 36398 | V14: Asian | W14: Single | X14: Fully Meets | Y14: 3 | Z14: =VLOOKUP(A14,Table3[],3,0) -> 5 | AA14: =VLOOKUP(A14,'employee_engagement survey data'!A14:E478,4,0) -> 4 | AB14: =VLOOKUP(A14,'employee_engagement survey data'!A14:E253,5,0) -> 3 | AC14: =VLOOKUP(A14,training_and_development!A14:F51,3,0) -> Project Management | AD14: =VLOOKUP(A14,training_and_development!A14:E403,4,0) -> External | AE14: =VLOOKUP(A14,training_and_development!A14:F3011,5,0) -> Failed | AF14: =VLOOKUP(A14,training_and_development!A13:G33,6,0) -> East Jessicatown | AG14: =VLOOKUP(A14,training_and_development!A14:H22,7,0) -> Michael Marks | AH14: =VLOOKUP(A14,training_and_development!A14:H17,8,0) -> 2
A15: 1014 | B15: Kole Quinn | C15: 44926 | D15: 45120 | E15: Shared Services Manager | F15: Jermaine Weaver | G15: julien.whitehead@bilearner.com | H15: WBL | I15: Voluntarily Terminated | J15: Part-Time | K15: Zone A | L15: Full-Time | M15: Retirement | N15: I back place no three offer economic. | O15: Software Engineering | P15: Catv | Q15: 19553 | R15: MA | S15: Clerk | T15: Male | U15: 2562 | V15: Other | W15: Single | X15: Fully Meets | Y15: 3 | Z15: =VLOOKUP(A15,Table3[],3,0) -> 4 | AA15: =VLOOKUP(A15,'employee_engagement survey data'!A15:E479,4,0) -> 4 | AB15: =VLOOKUP(A15,'employee_engagement survey data'!A15:E254,5,0) -> 1 | AC15: =VLOOKUP(A15,training_and_development!A15:F52,3,0) -> Customer Service | AD15: =VLOOKUP(A15,training_and_development!A15:E404,4,0) -> External | AE15: =VLOOKUP(A15,training_and_development!A15:F3012,5,0) -> Failed | AF15: =VLOOKUP(A15,training_and_development!A14:G34,6,0) -> Watersview | AG15: =VLOOKUP(A15,training_and_development!A15:H23,7,0) -> Rachel Jones | AH15: =VLOOKUP(A15,training_and_development!A15:H18,8,0) -> 2
A16: 1015 | B16: Ansley Jackson | C16: 43437 | D16: N/A | E16: Shared Services Manager | F16: James Barajas | G16: alan.haynes@bilearner.com | H16: NEL | I16: Voluntarily Terminated | J16: Contract | K16: Zone A | L16: Part-Time | M16: Unk | N16: N/A | O16: Software Engineering | P16: People Services | Q16: 22619 | R16: MA | S16: Vp | T16: Female | U16: 22621 | V16: White | W16: Married | X16: Fully Meets | Y16: 3 | Z16: =VLOOKUP(A16,Table3[],3,0) -> 1 | AA16: =VLOOKUP(A16,'employee_engagement survey data'!A16:E480,4,0) -> 1 | AB16: =VLOOKUP(A16,'employee_engagement survey data'!A16:E255,5,0) -> 3 | AC16: =VLOOKUP(A16,training_and_development!A16:F53,3,0) -> Leadership Development | AD16: =VLOOKUP(A16,training_and_development!A16:E405,4,0) -> External | AE16: =VLOOKUP(A16,training_and_development!A16:F3013,5,0) -> Completed | AF16: =VLOOKUP(A16,training_and_development!A15:G35,6,0) -> Port Ninaland | AG16: =VLOOKUP(A16,training_and_development!A16:H24,7,0) -> Jennifer Olson | AH16: =VLOOKUP(A16,training_and_development!A16:H19,8,0) -> 1
A17: 1016 | B17: Jayda Reese | C17: 43882 | D17: 44345 | E17: Senior BI Developer | F17: Tyler Davis | G17: kamryn.herrera@bilearner.com | H17: PL | I17: Voluntarily Terminated | J17: Part-Time | K17: Zone B | L17: Part-Time | M17: Involuntary | N17: Friend agree stock teach price fish. | O17: Admin Offices | P17: Shop (Fleet) | Q17: 20522 | R17: MA | S17: Mechanic | T17: Female | U17: 64065 | V17: White | W17: Single | X17: Fully Meets | Y17: 3 | Z17: =VLOOKUP(A17,Table3[],3,0) -> 2 | AA17: =VLOOKUP(A17,'employee_engagement survey data'!A17:E481,4,0) -> 3 | AB17: =VLOOKUP(A17,'employee_engagement survey data'!A17:E256,5,0) -> 2 | AC17: =VLOOKUP(A17,training_and_development!A17:F54,3,0) -> Communication Skills | AD17: =VLOOKUP(A17,training_and_development!A17:E406,4,0) -> External | AE17: =VLOOKUP(A17,training_and_development!A17:F3014,5,0) -> Completed | AF17: =VLOOKUP(A17,training_and_development!A16:G36,6,0) -> Lake Stuartfurt | AG17: =VLOOKUP(A17,training_and_development!A17:H25,7,0) -> Eric Johnson | AH17: =VLOOKUP(A17,training_and_development!A17:H20,8,0) -> 2
A18: 1017 | B18: Julien Whitehead | C18: 44081 | D18: 44545 | E18: Senior BI Developer | F18: Joshua Gonzalez | G18: kelvin.foster@bilearner.com | H18: BPC | I18: Voluntarily Terminated | J18: Full-Time | K18: Zone B | L18: Full-Time | M18: Involuntary | N18: True system strong often experience. | O18: Admin Offices | P18: Field Operations | Q18: 17353 | R18: MA | S18: Laborer | T18: Female | U18: 97374 | V18: Black | W18: Single | X18: Fully Meets | Y18: 3 | Z18: =VLOOKUP(A18,Table3[],3,0) -> 4 | AA18: =VLOOKUP(A18,'employee_engagement survey data'!A18:E482,4,0) -> 1 | AB18: =VLOOKUP(A18,'employee_engagement survey data'!A18:E257,5,0) -> 3 | AC18: =VLOOKUP(A18,training_and_development!A18:F55,3,0) -> Technical Skills | AD18: =VLOOKUP(A18,training_and_development!A18:E407,4,0) -> External | AE18: =VLOOKUP(A18,training_and_development!A18:F3015,5,0) -> Completed | AF18: =VLOOKUP(A18,training_and_development!A17:G37,6,0) -> Cooleybury | AG18: =VLOOKUP(A18,training_and_development!A18:H26,7,0) -> Joseph Mcintyre | AH18: =VLOOKUP(A18,training_and_development!A18:H21,8,0) -> 3
A19: 1018 | B19: Alan Haynes | C19: 44001 | D19: 44538 | E19: Senior BI Developer | F19: Justin Sherman | G19: joe.fletcher@bilearner.com | H19: CCDR | I19: Voluntarily Terminated | J19: Part-Time | K19: Zone A | L19: Part-Time | M19: Involuntary | N19: When price group admit fall fly around. | O19: Admin Offices | P19: General - Con | Q19: 15396 | R19: MA | S19: Laborer | T19: Female | U19: 87646 | V19: White | W19: Married | X19: Fully Meets | Y19: 3 | Z19: =VLOOKUP(A19,Table3[],3,0) -> 4 | AA19: =VLOOKUP(A19,'employee_engagement survey data'!A19:E483,4,0) -> 1 | AB19: =VLOOKUP(A19,'employee_engagement survey data'!A19:E258,5,0) -> 4 | AC19: =VLOOKUP(A19,training_and_development!A19:F56,3,0) -> Project Management | AD19: =VLOOKUP(A19,training_and_development!A19:E408,4,0) -> Internal | AE19: =VLOOKUP(A19,training_and_development!A19:F3016,5,0) -> Failed | AF19: =VLOOKUP(A19,training_and_development!A18:G38,6,0) -> Larsonborough | AG19: =VLOOKUP(A19,training_and_development!A19:H27,7,0) -> Whitney Morgan DVM | AH19: =VLOOKUP(A19,training_and_development!A19:H22,8,0) -> 2
A20: 1019 | B20: Kamryn Herrera | C20: 44848 | D20: 45135 | E20: Software Engineer | F20: Sara Holland | G20: nickolas.davila@bilearner.com | H20: EW | I20: Voluntarily Terminated | J20: Full-Time | K20: Zone A | L20: Temporary | M20: Retirement | N20: Article tough away forward home. Night author so. | O20: Software Engineering | P20: Fielders | Q20: 28822 | R20: MA | S20: Engineer | T20: Male | U20: 77974 | V20: Hispanic | W20: Widowed | X20: Fully Meets | Y20: 3 | Z20: =VLOOKUP(A20,Table3[],3,0) -> 1 | AA20: =VLOOKUP(A20,'employee_engagement survey data'!A20:E484,4,0) -> 3 | AB20: =VLOOKUP(A20,'employee_engagement survey data'!A20:E259,5,0) -> 5 | AC20: =VLOOKUP(A20,training_and_development!A20:F57,3,0) -> Project Management | AD20: =VLOOKUP(A20,training_and_development!A20:E409,4,0) -> External | AE20: =VLOOKUP(A20,training_and_development!A20:F3017,5,0) -> Completed | AF20: =VLOOKUP(A20,training_and_development!A19:G39,6,0) -> Powellland | AG20: =VLOOKUP(A20,training_and_development!A20:H28,7,0) -> Jon Garcia | AH20: =VLOOKUP(A20,training_and_development!A20:H23,8,0) -> 5
A21: 1020 | B21: Kelvin Foster | C21: 45097 | D21: 45125 | E21: Software Engineer | F21: Shelia Graham | G21: kasey.boyer@bilearner.com | H21: MSC | I21: Terminated for Cause | J21: Contract | K21: Zone C | L21: Full-Time | M21: Resignation | N21: Man issue never strategy will maintain resource. | O21: Software Engineering | P21: Field Operations | Q21: 33227 | R21: MA | S21: Supervisor | T21: Female | U21: 42126 | V21: Black | W21: Widowed | X21: Fully Meets | Y21: 3 | Z21: =VLOOKUP(A21,Table3[],3,0) -> 2 | AA21: =VLOOKUP(A21,'employee_engagement survey data'!A21:E485,4,0) -> 1 | AB21: =VLOOKUP(A21,'employee_engagement survey data'!A21:E260,5,0) -> 2 | AC21: =VLOOKUP(A21,training_and_development!A21:F58,3,0) -> Technical Skills | AD21: =VLOOKUP(A21,training_and_development!A21:E410,4,0) -> External | AE21: =VLOOKUP(A21,training_and_development!A21:F3018,5,0) -> Completed | AF21: =VLOOKUP(A21,training_and_development!A20:G40,6,0) -> Chadport | AG21: =VLOOKUP(A21,training_and_development!A21:H29,7,0) -> Nicole Taylor | AH21: =VLOOKUP(A21,training_and_development!A21:H24,8,0) -> 4
A22: 1021 | B22: Joe Fletcher | C22: 44144 | D22: 45124 | E22: Software Engineer | F22: Amanda Hayden | G22: giovanni.jenkins@bilearner.com | H22: TNS | I22: Terminated for Cause | J22: Full-Time | K22: Zone C | L22: Full-Time | M22: Resignation | N22: Section hospital clearly season history. | O22: Software Engineering | P22: General - Eng | Q22: 32533 | R22: MA | S22: Billing | T22: Male | U22: 51613 | V22: Hispanic | W22: Single | X22: Fully Meets | Y22: 3 | Z22: =VLOOKUP(A22,Table3[],3,0) -> 5 | AA22: =VLOOKUP(A22,'employee_engagement survey data'!A22:E486,4,0) -> 1 | AB22: =VLOOKUP(A22,'employee_engagement survey data'!A22:E261,5,0) -> 4 | AC22: =VLOOKUP(A22,training_and_development!A22:F59,3,0) -> Technical Skills | AD22: =VLOOKUP(A22,training_and_development!A22:E411,4,0) -> Internal | AE22: =VLOOKUP(A22,training_and_development!A22:F3019,5,0) -> Failed | AF22: =VLOOKUP(A22,training_and_development!A21:G41,6,0) -> Patrickhaven | AG22: =VLOOKUP(A22,training_and_development!A22:H30,7,0) -> Crystal Nelson | AH22: =VLOOKUP(A22,training_and_development!A22:H25,8,0) -> 1
A23: 1022 | B23: Frederick Howe | C23: 44823 | D23: N/A | E23: Software Engineer | F23: Nicole Haynes | G23: alexis.moss@bilearner.com | H23: PYZ | I23: Voluntarily Terminated | J23: Part-Time | K23: Zone A | L23: Temporary | M23: Unk | N23: N/A | O23: Software Engineering | P23: Field Operations | Q23: 22808 | R23: MA | S23: Engineer | T23: Male | U23: 12765 | V23: Black | W23: Divorced | X23: Fully Meets | Y23: 3 | Z23: =VLOOKUP(A23,Table3[],3,0) -> 1 | AA23: =VLOOKUP(A23,'employee_engagement survey data'!A23:E487,4,0) -> 4 | AB23: =VLOOKUP(A23,'employee_engagement survey data'!A23:E262,5,0) -> 4 | AC23: =VLOOKUP(A23,training_and_development!A23:F60,3,0) -> Project Management | AD23: =VLOOKUP(A23,training_and_development!A23:E412,4,0) -> Internal | AE23: =VLOOKUP(A23,training_and_development!A23:F3020,5,0) -> Failed | AF23: =VLOOKUP(A23,training_and_development!A22:G42,6,0) -> Lindseyburgh | AG23: =VLOOKUP(A23,training_and_development!A23:H31,7,0) -> Kevin Nichols | AH23: =VLOOKUP(A23,training_and_development!A23:H26,8,0) -> 1
A24: 1023 | B24: Nickolas Davila | C24: 43413 | D24: 44479 | E24: Shared Services Manager | F24: Debra Morales | G24: joanna.murphy@bilearner.com | H24: WBL | I24: Voluntarily Terminated | J24: Contract | K24: Zone C | L24: Part-Time | M24: Voluntary | N24: Each wish foot person morning per significant. | O24: Software Engineering | P24: General - Con | Q24: 33699 | R24: MA | S24: Clerk | T24: Male | U24: 64122 | V24: Hispanic | W24: Divorced | X24: Fully Meets | Y24: 3 | Z24: =VLOOKUP(A24,Table3[],3,0) -> 4 | AA24: =VLOOKUP(A24,'employee_engagement survey data'!A24:E488,4,0) -> 4 | AB24: =VLOOKUP(A24,'employee_engagement survey data'!A24:E263,5,0) -> 3 | AC24: =VLOOKUP(A24,training_and_development!A24:F61,3,0) -> Project Management | AD24: =VLOOKUP(A24,training_and_development!A24:E413,4,0) -> Internal | AE24: =VLOOKUP(A24,training_and_development!A24:F3021,5,0) -> Failed | AF24: =VLOOKUP(A24,training_and_development!A23:G43,6,0) -> West Justinborough | AG24: =VLOOKUP(A24,training_and_development!A24:H32,7,0) -> Angela Good | AH24: =VLOOKUP(A24,training_and_development!A24:H27,8,0) -> 4
A25: 1024 | B25: Kasey Boyer | C25: 43464 | D25: 44370 | E25: Shared Services Manager | F25: Chad Andrews | G25: joseph.schmidt@bilearner.com | H25: NEL | I25: Voluntarily Terminated | J25: Contract | K25: Zone A | L25: Part-Time | M25: Involuntary | N25: Free may every real agency as blue maintain. | O25: Software Engineering | P25: Fielders | Q25: 31866 | R25: MA | S25: Coordinator | T25: Female | U25: 91332 | V25: Other | W25: Divorced | X25: Fully Meets | Y25: 3 | Z25: =VLOOKUP(A25,Table3[],3,0) -> 5 | AA25: =VLOOKUP(A25,'employee_engagement survey data'!A25:E489,4,0) -> 3 | AB25: =VLOOKUP(A25,'employee_engagement survey data'!A25:E264,5,0) -> 1 | AC25: =VLOOKUP(A25,training_and_development!A25:F62,3,0) -> Project Management | AD25: =VLOOKUP(A25,training_and_development!A25:E414,4,0) -> External | AE25: =VLOOKUP(A25,training_and_development!A25:F3022,5,0) -> Completed | AF25: =VLOOKUP(A25,training_and_development!A24:G44,6,0) -> Hullmouth | AG25: =VLOOKUP(A25,training_and_development!A25:H33,7,0) -> Keith Curtis | AH25: =VLOOKUP(A25,training_and_development!A25:H28,8,0) -> 5
A26: 1025 | B26: Giovanni Jenkins | C26: 45057 | D26: 45061 | E26: Senior BI Developer | F26: John Wallace | G26: kiley.haynes@bilearner.com | H26: PL | I26: Voluntarily Terminated | J26: Full-Time | K26: Zone A | L26: Temporary | M26: Retirement | N26: Quite none ten order. | O26: Admin Offices | P26: Field Operations | Q26: 22233 | R26: MA | S26: Foreman | T26: Female | U26: 39827 | V26: Other | W26: Divorced | X26: Fully Meets | Y26: 3 | Z26: =VLOOKUP(A26,Table3[],3,0) -> 4 | AA26: =VLOOKUP(A26,'employee_engagement survey data'!A26:E490,4,0) -> 1 | AB26: =VLOOKUP(A26,'employee_engagement survey data'!A26:E265,5,0) -> 4 | AC26: =VLOOKUP(A26,training_and_development!A26:F63,3,0) -> Project Management | AD26: =VLOOKUP(A26,training_and_development!A26:E415,4,0) -> Internal | AE26: =VLOOKUP(A26,training_and_development!A26:F3023,5,0) -> Failed | AF26: =VLOOKUP(A26,training_and_development!A25:G45,6,0) -> Thompsonbury | AG26: =VLOOKUP(A26,training_and_development!A26:H34,7,0) -> Nina Rodriguez | AH26: =VLOOKUP(A26,training_and_development!A26:H29,8,0) -> 5
A27: 1026 | B27: Alexis Moss | C27: 44868 | D27: 44966 | E27: Senior BI Developer | F27: Benjamin Frederick | G27: kody.jimenez@bilearner.com | H27: BPC | I27: Voluntarily Terminated | J27: Contract | K27: Zone A | L27: Part-Time | M27: Resignation | N27: Where forward evening huge cost share eat. | O27: Admin Offices | P27: Engineers | Q27: 18574 | R27: MA | S27: Engineer | T27: Female | U27: 27418 | V27: Other | W27: Widowed | X27: Fully Meets | Y27: 3 | Z27: =VLOOKUP(A27,Table3[],3,0) -> 5 | AA27: =VLOOKUP(A27,'employee_engagement survey data'!A27:E491,4,0) -> 2 | AB27: =VLOOKUP(A27,'employee_engagement survey data'!A27:E266,5,0) -> 5 | AC27: =VLOOKUP(A27,training_and_development!A27:F64,3,0) -> Communication Skills | AD27: =VLOOKUP(A27,training_and_development!A27:E416,4,0) -> External | AE27: =VLOOKUP(A27,training_and_development!A27:F3024,5,0) -> Failed | AF27: =VLOOKUP(A27,training_and_development!A26:G46,6,0) -> Cynthiachester | AG27: =VLOOKUP(A27,training_and_development!A27:H35,7,0) -> Jennifer Robinson | AH27: =VLOOKUP(A27,training_and_development!A27:H30,8,0) -> 4
A28: 1027 | B28: Joanna Murphy | C28: 43996 | D28: 44345 | E28: Senior BI Developer | F28: Michael Ramos | G28: zoe.colon@bilearner.com | H28: CCDR | I28: Voluntarily Terminated | J28: Part-Time | K28: Zone A | L28: Full-Time | M28: Voluntary | N28: Open test message part risk. | O28: Admin Offices | P28: General - Con | Q28: 23001 | R28: MA | S28: Flagger | T28: Male | U28: 24931 | V28: Other | W28: Single | X28: Fully Meets | Y28: 3 | Z28: =VLOOKUP(A28,Table3[],3,0) -> 2 | AA28: =VLOOKUP(A28,'employee_engagement survey data'!A28:E492,4,0) -> 3 | AB28: =VLOOKUP(A28,'employee_engagement survey data'!A28:E267,5,0) -> 5 | AC28: =VLOOKUP(A28,training_and_development!A28:F65,3,0) -> Communication Skills | AD28: =VLOOKUP(A28,training_and_development!A28:E417,4,0) -> External | AE28: =VLOOKUP(A28,training_and_development!A28:F3025,5,0) -> Failed | AF28: =VLOOKUP(A28,training_and_development!A27:G47,6,0) -> East Jackstad | AG28: =VLOOKUP(A28,training_and_development!A28:H36,7,0) -> Mr. Robert Byrd MD | AH28: =VLOOKUP(A28,training_and_development!A28:H31,8,0) -> 4
A29: 1028 | B29: Joseph Schmidt | C29: 43753 | D29: 44927 | E29: Software Engineer | F29: Donna Boone | G29: nolan.perez@bilearner.com | H29: PYZ | I29: Voluntarily Terminated | J29: Full-Time | K29: Zone C | L29: Part-Time | M29: Resignation | N29: Federal less every character section think white. | O29: Software Engineering | P29: General - Con | Q29: 36821 | R29: MA | S29: Model Assistant | T29: Male | U29: 2121 | V29: Asian | W29: Single | X29: Fully Meets | Y29: 3 | Z29: =VLOOKUP(A29,Table3[],3,0) -> 5 | AA29: =VLOOKUP(A29,'employee_engagement survey data'!A29:E493,4,0) -> 5 | AB29: =VLOOKUP(A29,'employee_engagement survey data'!A29:E268,5,0) -> 4 | AC29: =VLOOKUP(A29,training_and_development!A29:F66,3,0) -> Technical Skills | AD29: =VLOOKUP(A29,training_and_development!A29:E418,4,0) -> Internal | AE29: =VLOOKUP(A29,training_and_development!A29:F3026,5,0) -> Failed | AF29: =VLOOKUP(A29,training_and_development!A28:G48,6,0) -> East Christopher | AG29: =VLOOKUP(A29,training_and_development!A29:H37,7,0) -> Gina Moore | AH29: =VLOOKUP(A29,training_and_development!A29:H32,8,0) -> 3
A30: 1029 | B30: Brittany Hurley | C30: 43949 | D30: N/A | E30: Software Engineer | F30: Jeffrey Johnston | G30: katrina.farrell@bilearner.com | H30: SVG | I30: Voluntarily Terminated | J30: Part-Time | K30: Zone B | L30: Part-Time | M30: Unk | N30: N/A | O30: Software Engineering | P30: Field Operations | Q30: 29007 | R30: MA | S30: Specialist | T30: Female | U30: 97697 | V30: Asian | W30: Divorced | X30: Fully Meets | Y30: 3 | Z30: =VLOOKUP(A30,Table3[],3,0) -> 3 | AA30: =VLOOKUP(A30,'employee_engagement survey data'!A30:E494,4,0) -> 5 | AB30: =VLOOKUP(A30,'employee_engagement survey data'!A30:E269,5,0) -> 4 | AC30: =VLOOKUP(A30,training_and_development!A30:F67,3,0) -> Project Management | AD30: =VLOOKUP(A30,training_and_development!A30:E419,4,0) -> Internal | AE30: =VLOOKUP(A30,training_and_development!A30:F3027,5,0) -> Failed | AF30: =VLOOKUP(A30,training_and_development!A29:G49,6,0) -> Lake Anthonyton | AG30: =VLOOKUP(A30,training_and_development!A30:H38,7,0) -> Christopher Rowland | AH30: =VLOOKUP(A30,training_and_development!A30:H33,8,0) -> 5
A31: 1030 | B31: Niko Hamilton | C31: 43767 | D31: N/A | E31: Software Engineer | F31: Sarah King | G31: camden.kelly@bilearner.com | H31: TNS | I31: Voluntarily Terminated | J31: Contract | K31: Zone C | L31: Temporary | M31: Unk | N31: N/A | O31: Software Engineering | P31: Field Operations | Q31: 20276 | R31: MA | S31: Foreman | T31: Male | U31: 75783 | V31: Black | W31: Single | X31: Fully Meets | Y31: 3 | Z31: =VLOOKUP(A31,Table3[],3,0) -> 4 | AA31: =VLOOKUP(A31,'employee_engagement survey data'!A31:E495,4,0) -> 4 | AB31: =VLOOKUP(A31,'employee_engagement survey data'!A31:E270,5,0) -> 1 | AC31: =VLOOKUP(A31,training_and_development!A31:F68,3,0) -> Communication Skills | AD31: =VLOOKUP(A31,training_and_development!A31:E420,4,0) -> Internal | AE31: =VLOOKUP(A31,training_and_development!A31:F3028,5,0) -> Completed | AF31: =VLOOKUP(A31,training_and_development!A30:G50,6,0) -> Longton | AG31: =VLOOKUP(A31,training_and_development!A31:H39,7,0) -> Wendy Gibson | AH31: =VLOOKUP(A31,training_and_development!A31:H34,8,0) -> 1
A32: 1031 | B32: Ruben Martinez | C32: 44314 | D32: N/A | E32: Software Engineer | F32: Cynthia Delgado | G32: kale.lang@bilearner.com | H32: WBL | I32: Voluntarily Terminated | J32: Part-Time | K32: Zone B | L32: Temporary | M32: Unk | N32: N/A | O32: Software Engineering | P32: General - Con | Q32: 26601 | R32: MA | S32: Lineman | T32: Male | U32: 26111 | V32: White | W32: Widowed | X32: Fully Meets | Y32: 3 | Z32: =VLOOKUP(A32,Table3[],3,0) -> 5 | AA32: =VLOOKUP(A32,'employee_engagement survey data'!A32:E496,4,0) -> 3 | AB32: =VLOOKUP(A32,'employee_engagement survey data'!A32:E271,5,0) -> 2 | AC32: =VLOOKUP(A32,training_and_development!A32:F69,3,0) -> Communication Skills | AD32: =VLOOKUP(A32,training_and_development!A32:E421,4,0) -> Internal | AE32: =VLOOKUP(A32,training_and_development!A32:F3029,5,0) -> Failed | AF32: =VLOOKUP(A32,training_and_development!A31:G51,6,0) -> New Williamland | AG32: =VLOOKUP(A32,training_and_development!A32:H40,7,0) -> Ashley Gonzalez | AH32: =VLOOKUP(A32,training_and_development!A32:H35,8,0) -> 1
A33: 1032 | B33: Kiley Haynes | C33: 44670 | D33: 44799 | E33: Software Engineer | F33: Dominique Bailey | G33: elliott.ashley@bilearner.com | H33: PYZ | I33: Voluntarily Terminated | J33: Full-Time | K33: Zone C | L33: Part-Time | M33: Voluntary | N33: Off part culture choose strong public. | O33: Software Engineering | P33: Aerial | Q33: 19906 | R33: MA | S33: Laborer | T33: Male | U33: 50656 | V33: Asian | W33: Widowed | X33: Fully Meets | Y33: 3 | Z33: =VLOOKUP(A33,Table3[],3,0) -> 5 | AA33: =VLOOKUP(A33,'employee_engagement survey data'!A33:E497,4,0) -> 4 | AB33: =VLOOKUP(A33,'employee_engagement survey data'!A33:E272,5,0) -> 4 | AC33: =VLOOKUP(A33,training_and_development!A33:F70,3,0) -> Technical Skills | AD33: =VLOOKUP(A33,training_and_development!A33:E422,4,0) -> External | AE33: =VLOOKUP(A33,training_and_development!A33:F3030,5,0) -> Completed | AF33: =VLOOKUP(A33,training_and_development!A32:G52,6,0) -> New Jackie | AG33: =VLOOKUP(A33,training_and_development!A33:H41,7,0) -> Cynthia Bradley | AH33: =VLOOKUP(A33,training_and_development!A33:H36,8,0) -> 3
A34: 1033 | B34: Blaine Brooks | C34: 45013 | D34: N/A | E34: Shared Services Manager | F34: Teresa Meyer | G34: genesis.todd@bilearner.com | H34: WBL | I34: Voluntarily Terminated | J34: Contract | K34: Zone B | L34: Full-Time | M34: Unk | N34: N/A | O34: Software Engineering | P34: Field Operations | Q34: 35517 | R34: MA | S34: Operator | T34: Male | U34: 71808 | V34: Other | W34: Single | X34: Fully Meets | Y34: 3 | Z34: =VLOOKUP(A34,Table3[],3,0) -> 3 | AA34: =VLOOKUP(A34,'employee_engagement survey data'!A34:E498,4,0) -> 1 | AB34: =VLOOKUP(A34,'employee_engagement survey data'!A34:E273,5,0) -> 3 | AC34: =VLOOKUP(A34,training_and_development!A34:F71,3,0) -> Communication Skills | AD34: =VLOOKUP(A34,training_and_development!A34:E423,4,0) -> Internal | AE34: =VLOOKUP(A34,training_and_development!A34:F3031,5,0) -> Failed | AF34: =VLOOKUP(A34,training_and_development!A33:G53,6,0) -> Smithshire | AG34: =VLOOKUP(A34,training_and_development!A34:H42,7,0) -> William Smith | AH34: =VLOOKUP(A34,training_and_development!A34:H37,8,0) -> 4
A35: 1034 | B35: Dennis Livingston | C35: 43591 | D35: N/A | E35: Shared Services Manager | F35: Sarah Carey | G35: demarion.morrow@bilearner.com | H35: NEL | I35: Voluntarily Terminated | J35: Full-Time | K35: Zone C | L35: Part-Time | M35: Unk | N35: N/A | O35: Software Engineering | P35: Project Management - Con | Q35: 28467 | R35: MA | S35: Manager | T35: Female | U35: 1043 | V35: Black | W35: Single | X35: Fully Meets | Y35: 3 | Z35: =VLOOKUP(A35,Table3[],3,0) -> 2 | AA35: =VLOOKUP(A35,'employee_engagement survey data'!A35:E499,4,0) -> 5 | AB35: =VLOOKUP(A35,'employee_engagement survey data'!A35:E274,5,0) -> 1 | AC35: =VLOOKUP(A35,training_and_development!A35:F72,3,0) -> Leadership Development | AD35: =VLOOKUP(A35,training_and_development!A35:E424,4,0) -> Internal | AE35: =VLOOKUP(A35,training_and_development!A35:F3032,5,0) -> Failed | AF35: =VLOOKUP(A35,training_and_development!A34:G54,6,0) -> Lake Anthony | AG35: =VLOOKUP(A35,training_and_development!A35:H43,7,0) -> Cynthia Brown | AH35: =VLOOKUP(A35,training_and_development!A35:H38,8,0) -> 1
A36: 1035 | B36: Case Russell | C36: 44117 | D36: N/A | E36: Senior BI Developer | F36: Taylor Wright | G36: devon.hinton@bilearner.com | H36: PL | I36: Voluntarily Terminated | J36: Full-Time | K36: Zone A | L36: Temporary | M36: Unk | N36: N/A | O36: Admin Offices | P36: Underground | Q36: 28902 | R36: MA | S36: Laborer | T36: Female | U36: 41260 | V36: Asian | W36: Divorced | X36: Fully Meets | Y36: 3 | Z36: =VLOOKUP(A36,Table3[],3,0) -> 1 | AA36: =VLOOKUP(A36,'employee_engagement survey data'!A36:E500,4,0) -> 5 | AB36: =VLOOKUP(A36,'employee_engagement survey data'!A36:E275,5,0) -> 5 | AC36: =VLOOKUP(A36,training_and_development!A36:F73,3,0) -> Communication Skills | AD36: =VLOOKUP(A36,training_and_development!A36:E425,4,0) -> Internal | AE36: =VLOOKUP(A36,training_and_development!A36:F3033,5,0) -> Completed | AF36: =VLOOKUP(A36,training_and_development!A35:G55,6,0) -> New Nancy | AG36: =VLOOKUP(A36,training_and_development!A36:H44,7,0) -> Joseph Mendoza | AH36: =VLOOKUP(A36,training_and_development!A36:H39,8,0) -> 2
A37: 1036 | B37: Kody Jimenez | C37: 44383 | D37: 44525 | E37: Senior BI Developer | F37: Daniel Moore | G37: jacquelyn.johns@bilearner.com | H37: BPC | I37: Terminated for Cause | J37: Part-Time | K37: Zone A | L37: Part-Time | M37: Resignation | N37: Teacher door money tend song. | O37: Admin Offices | P37: Field Operations | Q37: 34189 | R37: MA | S37: Foreman | T37: Male | U37: 15346 | V37: Asian | W37: Single | X37: Fully Meets | Y37: 3 | Z37: =VLOOKUP(A37,Table3[],3,0) -> 5 | AA37: =VLOOKUP(A37,'employee_engagement survey data'!A37:E501,4,0) -> 2 | AB37: =VLOOKUP(A37,'employee_engagement survey data'!A37:E276,5,0) -> 1 | AC37: =VLOOKUP(A37,training_and_development!A37:F74,3,0) -> Customer Service | AD37: =VLOOKUP(A37,training_and_development!A37:E426,4,0) -> External | AE37: =VLOOKUP(A37,training_and_development!A37:F3034,5,0) -> Failed | AF37: =VLOOKUP(A37,training_and_development!A36:G56,6,0) -> Michaelmouth | AG37: =VLOOKUP(A37,training_and_development!A37:H45,7,0) -> Laura Gonzalez | AH37: =VLOOKUP(A37,training_and_development!A37:H40,8,0) -> 3
A38: 1037 | B38: Zoe Colon | C38: 44098 | D38: 44137 | E38: Software Engineer | F38: Stacey Vargas | G38: blaine.keith@bilearner.com | H38: CCDR | I38: Terminated for Cause | J38: Part-Time | K38: Zone C | L38: Full-Time | M38: Voluntary | N38: Accept knowledge drop bar understand. | O38: Software Engineering | P38: Fielders | Q38: 34177 | R38: MA | S38: Engineer | T38: Male | U38: 4876 | V38: Other | W38: Widowed | X38: Fully Meets | Y38: 3 | Z38: =VLOOKUP(A38,Table3[],3,0) -> 5 | AA38: =VLOOKUP(A38,'employee_engagement survey data'!A38:E502,4,0) -> 1 | AB38: =VLOOKUP(A38,'employee_engagement survey data'!A38:E277,5,0) -> 4 | AC38: =VLOOKUP(A38,training_and_development!A38:F75,3,0) -> Leadership Development | AD38: =VLOOKUP(A38,training_and_development!A38:E427,4,0) -> Internal | AE38: =VLOOKUP(A38,training_and_development!A38:F3035,5,0) -> Failed | AF38: =VLOOKUP(A38,training_and_development!A37:G57,6,0) -> North Stephanie | AG38: =VLOOKUP(A38,training_and_development!A38:H46,7,0) -> Alexandra Hall | AH38: =VLOOKUP(A38,training_and_development!A38:H41,8,0) -> 2
A39: 1038 | B39: Courtney Cowan | C39: 44944 | D39: N/A | E39: Software Engineer | F39: Beth Anderson | G39: frida.livingston@bilearner.com | H39: SVG | I39: Voluntarily Terminated | J39: Contract | K39: Zone B | L39: Part-Time | M39: Unk | N39: N/A | O39: Software Engineering | P39: Field Operations | Q39: 26057 | R39: MA | S39: Crew Leader | T39: Male | U39: 14886 | V39: Hispanic | W39: Married | X39: Fully Meets | Y39: 3 | Z39: =VLOOKUP(A39,Table3[],3,0) -> 5 | AA39: =VLOOKUP(A39,'employee_engagement survey data'!A39:E503,4,0) -> 1 | AB39: =VLOOKUP(A39,'employee_engagement survey data'!A39:E278,5,0) -> 2 | AC39: =VLOOKUP(A39,training_and_development!A39:F76,3,0) -> Customer Service | AD39: =VLOOKUP(A39,training_and_development!A39:E428,4,0) -> External | AE39: =VLOOKUP(A39,training_and_development!A39:F3036,5,0) -> Failed | AF39: =VLOOKUP(A39,training_and_development!A38:G58,6,0) -> Jamesland | AG39: =VLOOKUP(A39,training_and_development!A39:H47,7,0) -> Eric Davis | AH39: =VLOOKUP(A39,training_and_development!A39:H42,8,0) -> 2
A40: 1039 | B40: Nolan Perez | C40: 43699 | D40: 44645 | E40: Software Engineer | F40: Joshua Daniels | G40: travis.vasquez@bilearner.com | H40: EW | I40: Terminated for Cause | J40: Part-Time | K40: Zone B | L40: Part-Time | M40: Involuntary | N40: Under follow guess lot minute able history face. | O40: Software Engineering | P40: Finance & Accounting | Q40: 30272 | R40: MA | S40: Administrative | T40: Female | U40: 46407 | V40: Other | W40: Widowed | X40: Fully Meets | Y40: 3 | Z40: =VLOOKUP(A40,Table3[],3,0) -> 2 | AA40: =VLOOKUP(A40,'employee_engagement survey data'!A40:E504,4,0) -> 4 | AB40: =VLOOKUP(A40,'employee_engagement survey data'!A40:E279,5,0) -> 5 | AC40: =VLOOKUP(A40,training_and_development!A40:F77,3,0) -> Customer Service | AD40: =VLOOKUP(A40,training_and_development!A40:E429,4,0) -> External | AE40: =VLOOKUP(A40,training_and_development!A40:F3037,5,0) -> Completed | AF40: =VLOOKUP(A40,training_and_development!A39:G59,6,0) -> East Williamport | AG40: =VLOOKUP(A40,training_and_development!A40:H48,7,0) -> Heather Silva | AH40: =VLOOKUP(A40,training_and_development!A40:H43,8,0) -> 5
A41: 1040 | B41: Katrina Farrell | C41: 43671 | D41: 44912 | E41: Software Engineer | F41: Mark Mays | G41: wyatt.donovan@bilearner.com | H41: MSC | I41: Voluntarily Terminated | J41: Contract | K41: Zone A | L41: Part-Time | M41: Retirement | N41: Main customer television phone staff family. | O41: Software Engineering | P41: Field Operations | Q41: 26414 | R41: MA | S41: Technician | T41: Male | U41: 74234 | V41: White | W41: Divorced | X41: Fully Meets | Y41: 3 | Z41: =VLOOKUP(A41,Table3[],3,0) -> 5 | AA41: =VLOOKUP(A41,'employee_engagement survey data'!A41:E505,4,0) -> 3 | AB41: =VLOOKUP(A41,'employee_engagement survey data'!A41:E280,5,0) -> 1 | AC41: =VLOOKUP(A41,training_and_development!A41:F78,3,0) -> Technical Skills | AD41: =VLOOKUP(A41,training_and_development!A41:E430,4,0) -> Internal | AE41: =VLOOKUP(A41,training_and_development!A41:F3038,5,0) -> Completed | AF41: =VLOOKUP(A41,training_and_development!A40:G60,6,0) -> Robertsmouth | AG41: =VLOOKUP(A41,training_and_development!A41:H49,7,0) -> Robert Johnson | AH41: =VLOOKUP(A41,training_and_development!A41:H44,8,0) -> 5
A42: 1041 | B42: Camden Kelly | C42: 43780 | D42: 43840 | E42: Software Engineer | F42: Brandon Ortiz | G42: gage.weeks@bilearner.com | H42: TNS | I42: Voluntarily Terminated | J42: Full-Time | K42: Zone A | L42: Full-Time | M42: Retirement | N42: Suffer consider store find up. | O42: Software Engineering | P42: Engineers | Q42: 28068 | R42: MA | S42: Administrative | T42: Male | U42: 45272 | V42: White | W42: Single | X42: Fully Meets | Y42: 3 | Z42: =VLOOKUP(A42,Table3[],3,0) -> 3 | AA42: =VLOOKUP(A42,'employee_engagement survey data'!A42:E506,4,0) -> 1 | AB42: =VLOOKUP(A42,'employee_engagement survey data'!A42:E281,5,0) -> 4 | AC42: =VLOOKUP(A42,training_and_development!A42:F79,3,0) -> Customer Service | AD42: =VLOOKUP(A42,training_and_development!A42:E431,4,0) -> Internal | AE42: =VLOOKUP(A42,training_and_development!A42:F3039,5,0) -> Completed | AF42: =VLOOKUP(A42,training_and_development!A41:G61,6,0) -> Reesefurt | AG42: =VLOOKUP(A42,training_and_development!A42:H50,7,0) -> Taylor Baker | AH42: =VLOOKUP(A42,training_and_development!A42:H45,8,0) -> 3
A43: 1042 | B43: Milo Hood | C43: 44758 | D43: N/A | E43: Software Engineer | F43: Cheryl Swanson | G43: wyatt.edwards@bilearner.com | H43: PYZ | I43: Terminated for Cause | J43: Contract | K43: Zone B | L43: Temporary | M43: Unk | N43: N/A | O43: Software Engineering | P43: Field Operations | Q43: 15571 | R43: MA | S43: Driller | T43: Male | U43: 96170 | V43: Black | W43: Widowed | X43: Fully Meets | Y43: 3 | Z43: =VLOOKUP(A43,Table3[],3,0) -> 1 | AA43: =VLOOKUP(A43,'employee_engagement survey data'!A43:E507,4,0) -> 3 | AB43: =VLOOKUP(A43,'employee_engagement survey data'!A43:E282,5,0) -> 4 | AC43: =VLOOKUP(A43,training_and_development!A43:F80,3,0) -> Project Management | AD43: =VLOOKUP(A43,training_and_development!A43:E432,4,0) -> Internal | AE43: =VLOOKUP(A43,training_and_development!A43:F3040,5,0) -> Completed | AF43: =VLOOKUP(A43,training_and_development!A42:G62,6,0) -> New Jesusfort | AG43: =VLOOKUP(A43,training_and_development!A43:H51,7,0) -> Brian Maynard | AH43: =VLOOKUP(A43,training_and_development!A43:H46,8,0) -> 1
A44: 1043 | B44: Kale Lang | C44: 44914 | D44: 45056 | E44: Shared Services Manager | F44: Matthew Patel | G44: karla.reed@bilearner.com | H44: WBL | I44: Voluntarily Terminated | J44: Full-Time | K44: Zone C | L44: Part-Time | M44: Resignation | N44: Agreement particular scene also war who. | O44: Software Engineering | P44: Splicing | Q44: 20439 | R44: MA | S44: Billing | T44: Female | U44: 65963 | V44: White | W44: Married | X44: Fully Meets | Y44: 3 | Z44: =VLOOKUP(A44,Table3[],3,0) -> 1 | AA44: =VLOOKUP(A44,'employee_engagement survey data'!A44:E508,4,0) -> 1 | AB44: =VLOOKUP(A44,'employee_engagement survey data'!A44:E283,5,0) -> 3 | AC44: =VLOOKUP(A44,training_and_development!A44:F81,3,0) -> Communication Skills | AD44: =VLOOKUP(A44,training_and_development!A44:E433,4,0) -> External | AE44: =VLOOKUP(A44,training_and_development!A44:F3041,5,0) -> Completed | AF44: =VLOOKUP(A44,training_and_development!A43:G63,6,0) -> West Danielside | AG44: =VLOOKUP(A44,training_and_development!A44:H52,7,0) -> Todd Mason | AH44: =VLOOKUP(A44,training_and_development!A44:H47,8,0) -> 2
A45: 1044 | B45: Shyanne Stark | C45: 44089 | D45: N/A | E45: Shared Services Manager | F45: Jennifer Adams | G45: yadira.mcmillan@bilearner.com | H45: NEL | I45: Terminated for Cause | J45: Contract | K45: Zone A | L45: Temporary | M45: Unk | N45: N/A | O45: Software Engineering | P45: Field Operations | Q45: 20714 | R45: MA | S45: Foreman | T45: Female | U45: 75123 | V45: Hispanic | W45: Divorced | X45: Fully Meets | Y45: 3 | Z45: =VLOOKUP(A45,Table3[],3,0) -> 2 | AA45: =VLOOKUP(A45,'employee_engagement survey data'!A45:E509,4,0) -> 4 | AB45: =VLOOKUP(A45,'employee_engagement survey data'!A45:E284,5,0) -> 5 | AC45: =VLOOKUP(A45,training_and_development!A45:F82,3,0) -> Technical Skills | AD45: =VLOOKUP(A45,training_and_development!A45:E434,4,0) -> External | AE45: =VLOOKUP(A45,training_and_development!A45:F3042,5,0) -> Failed | AF45: =VLOOKUP(A45,training_and_development!A44:G64,6,0) -> Smithborough | AG45: =VLOOKUP(A45,training_and_development!A45:H53,7,0) -> Stephanie Navarro | AH45: =VLOOKUP(A45,training_and_development!A45:H48,8,0) -> 4
A46: 1045 | B46: Elliott Ashley | C46: 44108 | D46: 44984 | E46: Senior BI Developer | F46: Kelly Williams | G46: lilianna.mccall@bilearner.com | H46: PL | I46: Terminated for Cause | J46: Full-Time | K46: Zone C | L46: Temporary | M46: Involuntary | N46: Artist technology ever body provide today doctor. | O46: Admin Offices | P46: Catv | Q46: 23172 | R46: MA | S46: Foreman | T46: Female | U46: 11164 | V46: Black | W46: Single | X46: Fully Meets | Y46: 3 | Z46: =VLOOKUP(A46,Table3[],3,0) -> 1 | AA46: =VLOOKUP(A46,'employee_engagement survey data'!A46:E510,4,0) -> 4 | AB46: =VLOOKUP(A46,'employee_engagement survey data'!A46:E285,5,0) -> 1 | AC46: =VLOOKUP(A46,training_and_development!A46:F83,3,0) -> Customer Service | AD46: =VLOOKUP(A46,training_and_development!A46:E435,4,0) -> External | AE46: =VLOOKUP(A46,training_and_development!A46:F3043,5,0) -> Completed | AF46: =VLOOKUP(A46,training_and_development!A45:G65,6,0) -> West Josephport | AG46: =VLOOKUP(A46,training_and_development!A46:H54,7,0) -> Jay Wilkins | AH46: =VLOOKUP(A46,training_and_development!A46:H49,8,0) -> 2
A47: 1046 | B47: Genesis Todd | C47: 44674 | D47: 44776 | E47: Software Engineer | F47: Jose Daniel | G47: salvador.thomas@bilearner.com | H47: CCDR | I47: Terminated for Cause | J47: Full-Time | K47: Zone A | L47: Temporary | M47: Involuntary | N47: Former treat check special economy. | O47: Software Engineering | P47: Underground | Q47: 22967 | R47: MA | S47: Laborer | T47: Male | U47: 65978 | V47: White | W47: Single | X47: Fully Meets | Y47: 3 | Z47: =VLOOKUP(A47,Table3[],3,0) -> 3 | AA47: =VLOOKUP(A47,'employee_engagement survey data'!A47:E511,4,0) -> 5 | AB47: =VLOOKUP(A47,'employee_engagement survey data'!A47:E286,5,0) -> 4 | AC47: =VLOOKUP(A47,training_and_development!A47:F84,3,0) -> Leadership Development | AD47: =VLOOKUP(A47,training_and_development!A47:E436,4,0) -> Internal | AE47: =VLOOKUP(A47,training_and_development!A47:F3044,5,0) -> Failed | AF47: =VLOOKUP(A47,training_and_development!A46:G66,6,0) -> Lake Jose | AG47: =VLOOKUP(A47,training_and_development!A47:H55,7,0) -> Jason Morgan | AH47: =VLOOKUP(A47,training_and_development!A47:H50,8,0) -> 2
A48: 1047 | B48: Sincere Jimenez | C48: 44527 | D48: N/A | E48: Software Engineer | F48: Vanessa Ramirez | G48: jair.silva@bilearner.com | H48: SVG | I48: Voluntarily Terminated | J48: Contract | K48: Zone A | L48: Part-Time | M48: Unk | N48: N/A | O48: Software Engineering | P48: Field Operations | Q48: 17495 | R48: MA | S48: Technician | T48: Female | U48: 73877 | V48: Hispanic | W48: Single | X48: Fully Meets | Y48: 3 | Z48: =VLOOKUP(A48,Table3[],3,0) -> 4 | AA48: =VLOOKUP(A48,'employee_engagement survey data'!A48:E512,4,0) -> 2 | AB48: =VLOOKUP(A48,'employee_engagement survey data'!A48:E287,5,0) -> 3 | AC48: =VLOOKUP(A48,training_and_development!A48:F85,3,0) -> Project Management | AD48: =VLOOKUP(A48,training_and_development!A48:E437,4,0) -> Internal | AE48: =VLOOKUP(A48,training_and_development!A48:F3045,5,0) -> Completed | AF48: =VLOOKUP(A48,training_and_development!A47:G67,6,0) -> Smithland | AG48: =VLOOKUP(A48,training_and_development!A48:H56,7,0) -> James Phelps | AH48: =VLOOKUP(A48,training_and_development!A48:H51,8,0) -> 2
A49: 1048 | B49: Stephen Daugherty | C49: 43798 | D49: N/A | E49: Software Engineer | F49: Joshua Pittman | G49: litzy.conner@bilearner.com | H49: EW | I49: Voluntarily Terminated | J49: Part-Time | K49: Zone A | L49: Temporary | M49: Unk | N49: N/A | O49: Software Engineering | P49: General - Con | Q49: 20655 | R49: MA | S49: Helper | T49: Male | U49: 48971 | V49: Asian | W49: Widowed | X49: Fully Meets | Y49: 3 | Z49: =VLOOKUP(A49,Table3[],3,0) -> 3 | AA49: =VLOOKUP(A49,'employee_engagement survey data'!A49:E513,4,0) -> 1 | AB49: =VLOOKUP(A49,'employee_engagement survey data'!A49:E288,5,0) -> 4 | AC49: =VLOOKUP(A49,training_and_development!A49:F86,3,0) -> Leadership Development | AD49: =VLOOKUP(A49,training_and_development!A49:E438,4,0) -> Internal | AE49: =VLOOKUP(A49,training_and_development!A49:F3046,5,0) -> Completed | AF49: =VLOOKUP(A49,training_and_development!A48:G68,6,0) -> Powelltown | AG49: =VLOOKUP(A49,training_and_development!A49:H57,7,0) -> Ronald Rivera | AH49: =VLOOKUP(A49,training_and_development!A49:H52,8,0) -> 5
A50: 1049 | B50: Demarion Morrow | C50: 43615 | D50: 44184 | E50: Software Engineer | F50: Patricia Brewer | G50: joanna.burnett@bilearner.com | H50: MSC | I50: Voluntarily Terminated | J50: Part-Time | K50: Zone B | L50: Part-Time | M50: Involuntary | N50: Plan capital firm foreign. | O50: Software Engineering | P50: Field Operations | Q50: 19993 | R50: MA | S50: Technician | T50: Male | U50: 16259 | V50: White | W50: Married | X50: Fully Meets | Y50: 3 | Z50: =VLOOKUP(A50,Table3[],3,0) -> 3 | AA50: =VLOOKUP(A50,'employee_engagement survey data'!A50:E514,4,0) -> 5 | AB50: =VLOOKUP(A50,'employee_engagement survey data'!A50:E289,5,0) -> 2 | AC50: =VLOOKUP(A50,training_and_development!A50:F87,3,0) -> Leadership Development | AD50: =VLOOKUP(A50,training_and_development!A50:E439,4,0) -> Internal | AE50: =VLOOKUP(A50,training_and_development!A50:F3047,5,0) -> Completed | AF50: =VLOOKUP(A50,training_and_development!A49:G69,6,0) -> Gonzalezfort | AG50: =VLOOKUP(A50,training_and_development!A50:H58,7,0) -> Dr. Patricia Johnson | AH50: =VLOOKUP(A50,training_and_development!A50:H53,8,0) -> 2
A51: 1050 | B51: Steven Schneider | C51: 44158 | D51: N/A | E51: Software Engineer | F51: Jerry Suarez | G51: armani.porter@bilearner.com | H51: TNS | I51: Voluntarily Terminated | J51: Contract | K51: Zone B | L51: Temporary | M51: Unk | N51: N/A | O51: Software Engineering | P51: Finance & Accounting | Q51: 34154 | R51: MA | S51: Accounting | T51: Male | U51: 64114 | V51: Black | W51: Widowed | X51: Fully Meets | Y51: 3 | Z51: =VLOOKUP(A51,Table3[],3,0) -> 4 | AA51: =VLOOKUP(A51,'employee_engagement survey data'!A51:E515,4,0) -> 5 | AB51: =VLOOKUP(A51,'employee_engagement survey data'!A51:E290,5,0) -> 1 | AC51: =VLOOKUP(A51,training_and_development!A51:F88,3,0) -> Customer Service | AD51: =VLOOKUP(A51,training_and_development!A51:E440,4,0) -> Internal | AE51: =VLOOKUP(A51,training_and_development!A51:F3048,5,0) -> Completed | AF51: =VLOOKUP(A51,training_and_development!A50:G70,6,0) -> Samanthaport | AG51: =VLOOKUP(A51,training_and_development!A51:H59,7,0) -> James Reed | AH51: =VLOOKUP(A51,training_and_development!A51:H54,8,0) -> 1
A52: 1051 | B52: Devon Hinton | C52: 44659 | D52: 44937 | E52: Software Engineer | F52: Allison York | G52: taylor.sanders@bilearner.com | H52: PYZ | I52: Terminated for Cause | J52: Full-Time | K52: Zone C | L52: Part-Time | M52: Involuntary | N52: Her office place. | O52: Software Engineering | P52: Field Operations | Q52: 29705 | R52: MA | S52: Operator | T52: Male | U52: 14669 | V52: White | W52: Divorced | X52: Fully Meets | Y52: 3 | Z52: =VLOOKUP(A52,Table3[],3,0) -> 2 | AA52: =VLOOKUP(A52,'employee_engagement survey data'!A52:E516,4,0) -> 4 | AB52: =VLOOKUP(A52,'employee_engagement survey data'!A52:E291,5,0) -> 5 | AC52: =VLOOKUP(A52,training_and_development!A52:F89,3,0) -> Leadership Development | AD52: =VLOOKUP(A52,training_and_development!A52:E441,4,0) -> Internal | AE52: =VLOOKUP(A52,training_and_development!A52:F3049,5,0) -> Completed | AF52: =VLOOKUP(A52,training_and_development!A51:G71,6,0) -> Hardingfort | AG52: =VLOOKUP(A52,training_and_development!A52:H60,7,0) -> Mark Morgan | AH52: =VLOOKUP(A52,training_and_development!A52:H55,8,0) -> 3
A53: 1052 | B53: Jacquelyn Johns | C53: 44252 | D53: 44351 | E53: Shared Services Manager | F53: Christopher Romero | G53: ava.pace@bilearner.com | H53: WBL | I53: Voluntarily Terminated | J53: Contract | K53: Zone B | L53: Part-Time | M53: Voluntary | N53: Plant enjoy these drive themselves never hit PM. | O53: Software Engineering | P53: General - Con | Q53: 29393 | R53: MA | S53: Foreman | T53: Female | U53: 52448 | V53: Hispanic | W53: Single | X53: Fully Meets | Y53: 3 | Z53: =VLOOKUP(A53,Table3[],3,0) -> 1 | AA53: =VLOOKUP(A53,'employee_engagement survey data'!A53:E517,4,0) -> 4 | AB53: =VLOOKUP(A53,'employee_engagement survey data'!A53:E292,5,0) -> 4 | AC53: =VLOOKUP(A53,training_and_development!A53:F90,3,0) -> Communication Skills | AD53: =VLOOKUP(A53,training_and_development!A53:E442,4,0) -> Internal | AE53: =VLOOKUP(A53,training_and_development!A53:F3050,5,0) -> Failed | AF53: =VLOOKUP(A53,training_and_development!A52:G72,6,0) -> Larryview | AG53: =VLOOKUP(A53,training_and_development!A53:H61,7,0) -> Robin Becker | AH53: =VLOOKUP(A53,training_and_development!A53:H56,8,0) -> 4
A54: 1053 | B54: Blaine Keith | C54: 43537 | D54: 44293 | E54: Shared Services Manager | F54: Timothy Hansen | G54: delaney.bruce@bilearner.com | H54: NEL | I54: Voluntarily Terminated | J54: Contract | K54: Zone C | L54: Full-Time | M54: Resignation | N54: Wind commercial in ahead will realize. | O54: Software Engineering | P54: Project Management - Con | Q54: 17373 | R54: MA | S54: Project Manager | T54: Female | U54: 43336 | V54: Hispanic | W54: Divorced | X54: Fully Meets | Y54: 3 | Z54: =VLOOKUP(A54,Table3[],3,0) -> 2 | AA54: =VLOOKUP(A54,'employee_engagement survey data'!A54:E518,4,0) -> 1 | AB54: =VLOOKUP(A54,'employee_engagement survey data'!A54:E293,5,0) -> 4 | AC54: =VLOOKUP(A54,training_and_development!A54:F91,3,0) -> Communication Skills | AD54: =VLOOKUP(A54,training_and_development!A54:E443,4,0) -> External | AE54: =VLOOKUP(A54,training_and_development!A54:F3051,5,0) -> Completed | AF54: =VLOOKUP(A54,training_and_development!A53:G73,6,0) -> Valdezfort | AG54: =VLOOKUP(A54,training_and_development!A54:H62,7,0) -> Erika Roberts | AH54: =VLOOKUP(A54,training_and_development!A54:H57,8,0) -> 4
A55: 1054 | B55: Phillip Salazar | C55: 44969 | D55: N/A | E55: Software Engineer | F55: Christopher Romero | G55: jair.bullock@bilearner.com | H55: PL | I55: Voluntarily Terminated | J55: Part-Time | K55: Zone A | L55: Full-Time | M55: Unk | N55: N/A | O55: Software Engineering | P55: Engineers | Q55: 34099 | R55: MA | S55: Project Manager | T55: Male | U55: 56271 | V55: White | W55: Single | X55: Fully Meets | Y55: 3 | Z55: =VLOOKUP(A55,Table3[],3,0) -> 1 | AA55: =VLOOKUP(A55,'employee_engagement survey data'!A55:E519,4,0) -> 5 | AB55: =VLOOKUP(A55,'employee_engagement survey data'!A55:E294,5,0) -> 2 | AC55: =VLOOKUP(A55,training_and_development!A55:F92,3,0) -> Technical Skills | AD55: =VLOOKUP(A55,training_and_development!A55:E444,4,0) -> External | AE55: =VLOOKUP(A55,training_and_development!A55:F3052,5,0) -> Failed | AF55: =VLOOKUP(A55,training_and_development!A54:G74,6,0) -> Tammyfurt | AG55: =VLOOKUP(A55,training_and_development!A55:H63,7,0) -> Cynthia Porter | AH55: =VLOOKUP(A55,training_and_development!A55:H58,8,0) -> 3
A56: 1055 | B56: Chaz Webb | C56: 43351 | D56: N/A | E56: Software Engineer | F56: Alec Hernandez | G56: kayla.farrell@bilearner.com | H56: PYZ | I56: Terminated for Cause | J56: Contract | K56: Zone C | L56: Full-Time | M56: Unk | N56: N/A | O56: Software Engineering | P56: Field Operations | Q56: 35027 | R56: MA | S56: Laborer | T56: Female | U56: 56708 | V56: White | W56: Widowed | X56: Fully Meets | Y56: 3 | Z56: =VLOOKUP(A56,Table3[],3,0) -> 3 | AA56: =VLOOKUP(A56,'employee_engagement survey data'!A56:E520,4,0) -> 4 | AB56: =VLOOKUP(A56,'employee_engagement survey data'!A56:E295,5,0) -> 1 | AC56: =VLOOKUP(A56,training_and_development!A56:F93,3,0) -> Customer Service | AD56: =VLOOKUP(A56,training_and_development!A56:E445,4,0) -> Internal | AE56: =VLOOKUP(A56,training_and_development!A56:F3053,5,0) -> Completed | AF56: =VLOOKUP(A56,training_and_development!A55:G75,6,0) -> West Robert | AG56: =VLOOKUP(A56,training_and_development!A56:H64,7,0) -> Anna Petty | AH56: =VLOOKUP(A56,training_and_development!A56:H59,8,0) -> 2
A57: 1056 | B57: Desmond Anderson | C57: 44518 | D57: N/A | E57: Software Engineer | F57: Kari Bishop | G57: carl.desimone@bilearner.com | H57: SVG | I57: Voluntarily Terminated | J57: Contract | K57: Zone C | L57: Temporary | M57: Unk | N57: N/A | O57: Software Engineering | P57: Wireline Construction | Q57: 15950 | R57: MA | S57: Driver | T57: Male | U57: 12869 | V57: Hispanic | W57: Widowed | X57: Fully Meets | Y57: 3 | Z57: =VLOOKUP(A57,Table3[],3,0) -> 4 | AA57: =VLOOKUP(A57,'employee_engagement survey data'!A57:E521,4,0) -> 2 | AB57: =VLOOKUP(A57,'employee_engagement survey data'!A57:E296,5,0) -> 2 | AC57: =VLOOKUP(A57,training_and_development!A57:F94,3,0) -> Leadership Development | AD57: =VLOOKUP(A57,training_and_development!A57:E446,4,0) -> Internal | AE57: =VLOOKUP(A57,training_and_development!A57:F3054,5,0) -> Completed | AF57: =VLOOKUP(A57,training_and_development!A56:G76,6,0) -> South Julieville | AG57: =VLOOKUP(A57,training_and_development!A57:H65,7,0) -> Julie Cole | AH57: =VLOOKUP(A57,training_and_development!A57:H60,8,0) -> 2
A58: 1057 | B58: Sophie Decker | C58: 45108 | D58: N/A | E58: Software Engineer | F58: Justin Grant | G58: linda.anderson@bilearner.com | H58: TNS | I58: Voluntarily Terminated | J58: Full-Time | K58: Zone A | L58: Full-Time | M58: Unk | N58: N/A | O58: Software Engineering | P58: Wireline Construction | Q58: 36095 | R58: MA | S58: Foreman | T58: Male | U58: 18240 | V58: Asian | W58: Widowed | X58: Fully Meets | Y58: 3 | Z58: =VLOOKUP(A58,Table3[],3,0) -> 3 | AA58: =VLOOKUP(A58,'employee_engagement survey data'!A58:E522,4,0) -> 2 | AB58: =VLOOKUP(A58,'employee_engagement survey data'!A58:E297,5,0) -> 5 | AC58: =VLOOKUP(A58,training_and_development!A58:F95,3,0) -> Project Management | AD58: =VLOOKUP(A58,training_and_development!A58:E447,4,0) -> Internal | AE58: =VLOOKUP(A58,training_and_development!A58:F3055,5,0) -> Failed | AF58: =VLOOKUP(A58,training_and_development!A57:G77,6,0) -> East Amanda | AG58: =VLOOKUP(A58,training_and_development!A58:H66,7,0) -> Andrew Herrera | AH58: =VLOOKUP(A58,training_and_development!A58:H61,8,0) -> 4
A59: 1058 | B59: Lena Bryan | C59: 44669 | D59: N/A | E59: Software Engineer | F59: Sarah Sims | G59: nilson.fernandes@bilearner.com | H59: WBL | I59: Voluntarily Terminated | J59: Contract | K59: Zone C | L59: Temporary | M59: Unk | N59: N/A | O59: Software Engineering | P59: Billable Consultants | Q59: 15413 | R59: MA | S59: Technician | T59: Male | U59: 77311 | V59: Hispanic | W59: Married | X59: Fully Meets | Y59: 3 | Z59: =VLOOKUP(A59,Table3[],3,0) -> 4 | AA59: =VLOOKUP(A59,'employee_engagement survey data'!A59:E523,4,0) -> 2 | AB59: =VLOOKUP(A59,'employee_engagement survey data'!A59:E298,5,0) -> 1 | AC59: =VLOOKUP(A59,training_and_development!A59:F96,3,0) -> Project Management | AD59: =VLOOKUP(A59,training_and_development!A59:E448,4,0) -> External | AE59: =VLOOKUP(A59,training_and_development!A59:F3056,5,0) -> Failed | AF59: =VLOOKUP(A59,training_and_development!A58:G78,6,0) -> South Jesusport | AG59: =VLOOKUP(A59,training_and_development!A59:H67,7,0) -> Amanda Christian | AH59: =VLOOKUP(A59,training_and_development!A59:H62,8,0) -> 1
A60: 1059 | B60: Kelsie Mccormick | C60: 45045 | D60: N/A | E60: Software Engineer | F60: Emily Brennan | G60: alain.robinson@bilearner.com | H60: BPC | I60: Voluntarily Terminated | J60: Part-Time | K60: Zone C | L60: Full-Time | M60: Unk | N60: N/A | O60: Software Engineering | P60: Engineers | Q60: 27172 | R60: MA | S60: Engineer | T60: Female | U60: 63959 | V60: Asian | W60: Widowed | X60: Fully Meets | Y60: 3 | Z60: =VLOOKUP(A60,Table3[],3,0) -> 4 | AA60: =VLOOKUP(A60,'employee_engagement survey data'!A60:E524,4,0) -> 3 | AB60: =VLOOKUP(A60,'employee_engagement survey data'!A60:E299,5,0) -> 3 | AC60: =VLOOKUP(A60,training_and_development!A60:F97,3,0) -> Technical Skills | AD60: =VLOOKUP(A60,training_and_development!A60:E449,4,0) -> Internal | AE60: =VLOOKUP(A60,training_and_development!A60:F3057,5,0) -> Failed | AF60: =VLOOKUP(A60,training_and_development!A59:G79,6,0) -> Brianville | AG60: =VLOOKUP(A60,training_and_development!A60:H68,7,0) -> Victoria Vasquez | AH60: =VLOOKUP(A60,training_and_development!A60:H63,8,0) -> 3
A61: 1060 | B61: Frida Livingston | C61: 43383 | D61: 43459 | E61: Shared Services Manager | F61: Sandra Black | G61: seffi.shields@bilearner.com | H61: CCDR | I61: Voluntarily Terminated | J61: Part-Time | K61: Zone B | L61: Full-Time | M61: Voluntary | N61: Improve center sure Mr respond for recent. | O61: Software Engineering | P61: General - Con | Q61: 27795 | R61: MA | S61: Project Manager | T61: Female | U61: 20331 | V61: Black | W61: Single | X61: Fully Meets | Y61: 3 | Z61: =VLOOKUP(A61,Table3[],3,0) -> 5 | AA61: =VLOOKUP(A61,'employee_engagement survey data'!A61:E525,4,0) -> 5 | AB61: =VLOOKUP(A61,'employee_engagement survey data'!A61:E300,5,0) -> 4 | AC61: =VLOOKUP(A61,training_and_development!A61:F98,3,0) -> Project Management | AD61: =VLOOKUP(A61,training_and_development!A61:E450,4,0) -> Internal | AE61: =VLOOKUP(A61,training_and_development!A61:F3058,5,0) -> Completed | AF61: =VLOOKUP(A61,training_and_development!A60:G80,6,0) -> East Andres | AG61: =VLOOKUP(A61,training_and_development!A61:H69,7,0) -> Cindy Schultz | AH61: =VLOOKUP(A61,training_and_development!A61:H64,8,0) -> 1
A62: 1061 | B62: Isai Alvarado | C62: 44885 | D62: N/A | E62: Shared Services Manager | F62: Laura Norman | G62: samuel.maclennan@bilearner.com | H62: EW | I62: Voluntarily Terminated | J62: Part-Time | K62: Zone C | L62: Part-Time | M62: Unk | N62: N/A | O62: Software Engineering | P62: General - Sga | Q62: 34110 | R62: MA | S62: Specialist | T62: Female | U62: 45515 | V62: Other | W62: Single | X62: Fully Meets | Y62: 3 | Z62: =VLOOKUP(A62,Table3[],3,0) -> 3 | AA62: =VLOOKUP(A62,'employee_engagement survey data'!A62:E526,4,0) -> 3 | AB62: =VLOOKUP(A62,'employee_engagement survey data'!A62:E301,5,0) -> 1 | AC62: =VLOOKUP(A62,training_and_development!A62:F99,3,0) -> Project Management | AD62: =VLOOKUP(A62,training_and_development!A62:E451,4,0) -> Internal | AE62: =VLOOKUP(A62,training_and_development!A62:F3059,5,0) -> Failed | AF62: =VLOOKUP(A62,training_and_development!A61:G81,6,0) -> Paigefurt | AG62: =VLOOKUP(A62,training_and_development!A62:H70,7,0) -> Nathan Mitchell | AH62: =VLOOKUP(A62,training_and_development!A62:H65,8,0) -> 2
A63: 1062 | B63: Travis Vasquez | C63: 43603 | D63: 43844 | E63: Software Engineer | F63: Amanda Hale | G63: shakira.perry@bilearner.com | H63: BPC | I63: Voluntarily Terminated | J63: Part-Time | K63: Zone A | L63: Part-Time | M63: Involuntary | N63: Rise activity learn step power simple sure. | O63: Software Engineering | P63: Engineers | Q63: 25510 | R63: MA | S63: Program Manager | T63: Male | U63: 59717 | V63: Hispanic | W63: Married | X63: Fully Meets | Y63: 3 | Z63: =VLOOKUP(A63,Table3[],3,0) -> 3 | AA63: =VLOOKUP(A63,'employee_engagement survey data'!A63:E527,4,0) -> 2 | AB63: =VLOOKUP(A63,'employee_engagement survey data'!A63:E302,5,0) -> 1 | AC63: =VLOOKUP(A63,training_and_development!A63:F100,3,0) -> Technical Skills | AD63: =VLOOKUP(A63,training_and_development!A63:E452,4,0) -> Internal | AE63: =VLOOKUP(A63,training_and_development!A63:F3060,5,0) -> Failed | AF63: =VLOOKUP(A63,training_and_development!A62:G82,6,0) -> Carolinemouth | AG63: =VLOOKUP(A63,training_and_development!A63:H71,7,0) -> Taylor Barron | AH63: =VLOOKUP(A63,training_and_development!A63:H66,8,0) -> 5
A64: 1063 | B64: Jazlene Maynard | C64: 44369 | D64: N/A | E64: Software Engineer | F64: James Baker | G64: enola.chivukula@bilearner.com | H64: CCDR | I64: Terminated for Cause | J64: Full-Time | K64: Zone B | L64: Temporary | M64: Unk | N64: N/A | O64: Software Engineering | P64: Aerial | Q64: 16546 | R64: MA | S64: Foreman | T64: Female | U64: 15748 | V64: Black | W64: Single | X64: Fully Meets | Y64: 3 | Z64: =VLOOKUP(A64,Table3[],3,0) -> 5 | AA64: =VLOOKUP(A64,'employee_engagement survey data'!A64:E528,4,0) -> 2 | AB64: =VLOOKUP(A64,'employee_engagement survey data'!A64:E303,5,0) -> 4 | AC64: =VLOOKUP(A64,training_and_development!A64:F101,3,0) -> Technical Skills | AD64: =VLOOKUP(A64,training_and_development!A64:E453,4,0) -> Internal | AE64: =VLOOKUP(A64,training_and_development!A64:F3061,5,0) -> Completed | AF64: =VLOOKUP(A64,training_and_development!A63:G83,6,0) -> Onealland | AG64: =VLOOKUP(A64,training_and_development!A64:H72,7,0) -> Eric Harris | AH64: =VLOOKUP(A64,training_and_development!A64:H67,8,0) -> 1
A65: 1064 | B65: Wyatt Donovan | C65: 44650 | D65: 44664 | E65: Software Engineer | F65: Terry Durham | G65: alexandra.kirill@bilearner.com | H65: SVG | I65: Voluntarily Terminated | J65: Part-Time | K65: Zone A | L65: Part-Time | M65: Retirement | N65: North help rock stage someone book. | O65: Software Engineering | P65: Field Operations | Q65: 31832 | R65: MA | S65: Technician | T65: Male | U65: 67106 | V65: White | W65: Divorced | X65: Fully Meets | Y65: 3 | Z65: =VLOOKUP(A65,Table3[],3,0) -> 5 | AA65: =VLOOKUP(A65,'employee_engagement survey data'!A65:E529,4,0) -> 4 | AB65: =VLOOKUP(A65,'employee_engagement survey data'!A65:E304,5,0) -> 4 | AC65: =VLOOKUP(A65,training_and_development!A65:F102,3,0) -> Leadership Development | AD65: =VLOOKUP(A65,training_and_development!A65:E454,4,0) -> External | AE65: =VLOOKUP(A65,training_and_development!A65:F3062,5,0) -> Completed | AF65: =VLOOKUP(A65,training_and_development!A64:G84,6,0) -> South Charlene | AG65: =VLOOKUP(A65,training_and_development!A65:H73,7,0) -> Jacqueline Barton | AH65: =VLOOKUP(A65,training_and_development!A65:H68,8,0) -> 1
A66: 1065 | B66: Nathaly Cooper | C66: 43340 | D66: N/A | E66: Software Engineer | F66: Erik Simon | G66: ryker.logan@bilearner.com | H66: EW | I66: Voluntarily Terminated | J66: Contract | K66: Zone C | L66: Temporary | M66: Unk | N66: N/A | O66: Software Engineering | P66: Engineers | Q66: 34876 | R66: MA | S66: Engineer | T66: Male | U66: 33438 | V66: Other | W66: Widowed | X66: Fully Meets | Y66: 3 | Z66: =VLOOKUP(A66,Table3[],3,0) -> 5 | AA66: =VLOOKUP(A66,'employee_engagement survey data'!A66:E530,4,0) -> 3 | AB66: =VLOOKUP(A66,'employee_engagement survey data'!A66:E305,5,0) -> 4 | AC66: =VLOOKUP(A66,training_and_development!A66:F103,3,0) -> Technical Skills | AD66: =VLOOKUP(A66,training_and_development!A66:E455,4,0) -> External | AE66: =VLOOKUP(A66,training_and_development!A66:F3063,5,0) -> Completed | AF66: =VLOOKUP(A66,training_and_development!A65:G85,6,0) -> East Leah | AG66: =VLOOKUP(A66,training_and_development!A66:H74,7,0) -> Kara Frazier MD | AH66: =VLOOKUP(A66,training_and_development!A66:H69,8,0) -> 4
A67: 1066 | B67: Gage Weeks | C67: 44557 | D67: 44931 | E67: Software Engineer | F67: Summer Moreno | G67: payten.middleton@bilearner.com | H67: MSC | I67: Voluntarily Terminated | J67: Full-Time | K67: Zone C | L67: Temporary | M67: Voluntary | N67: Face garden central since several food. | O67: Software Engineering | P67: Catv | Q67: 29699 | R67: MA | S67: Operator | T67: Male | U67: 61106 | V67: Hispanic | W67: Single | X67: Fully Meets | Y67: 3 | Z67: =VLOOKUP(A67,Table3[],3,0) -> 4 | AA67: =VLOOKUP(A67,'employee_engagement survey data'!A67:E531,4,0) -> 3 | AB67: =VLOOKUP(A67,'employee_engagement survey data'!A67:E306,5,0) -> 5 | AC67: =VLOOKUP(A67,training_and_development!A67:F104,3,0) -> Communication Skills | AD67: =VLOOKUP(A67,training_and_development!A67:E456,4,0) -> Internal | AE67: =VLOOKUP(A67,training_and_development!A67:F3064,5,0) -> Completed | AF67: =VLOOKUP(A67,training_and_development!A66:G86,6,0) -> Brandonberg | AG67: =VLOOKUP(A67,training_and_development!A67:H75,7,0) -> Travis Knox | AH67: =VLOOKUP(A67,training_and_development!A67:H70,8,0) -> 5
A68: 1067 | B68: Gavin Frye | C68: 44149 | D68: N/A | E68: Software Engineer | F68: Carla Cox | G68: harrison.hunt@bilearner.com | H68: TNS | I68: Voluntarily Terminated | J68: Part-Time | K68: Zone A | L68: Temporary | M68: Unk | N68: N/A | O68: Software Engineering | P68: Field Operations | Q68: 17874 | R68: MA | S68: Technician | T68: Female | U68: 25160 | V68: White | W68: Married | X68: Fully Meets | Y68: 3 | Z68: =VLOOKUP(A68,Table3[],3,0) -> 3 | AA68: =VLOOKUP(A68,'employee_engagement survey data'!A68:E532,4,0) -> 2 | AB68: =VLOOKUP(A68,'employee_engagement survey data'!A68:E307,5,0) -> 5 | AC68: =VLOOKUP(A68,training_and_development!A68:F105,3,0) -> Project Management | AD68: =VLOOKUP(A68,training_and_development!A68:E457,4,0) -> External | AE68: =VLOOKUP(A68,training_and_development!A68:F3065,5,0) -> Completed | AF68: =VLOOKUP(A68,training_and_development!A67:G87,6,0) -> Toddtown | AG68: =VLOOKUP(A68,training_and_development!A68:H76,7,0) -> Joseph Long | AH68: =VLOOKUP(A68,training_and_development!A68:H71,8,0) -> 5
A69: 1068 | B69: Amber Ross | C69: 44470 | D69: N/A | E69: Software Engineer | F69: Mary Mendoza | G69: orlando.henderson@bilearner.com | H69: PYZ | I69: Voluntarily Terminated | J69: Full-Time | K69: Zone B | L69: Part-Time | M69: Unk | N69: N/A | O69: Software Engineering | P69: Wireline Construction | Q69: 36153 | R69: MA | S69: Project Manager | T69: Female | U69: 52694 | V69: Black | W69: Widowed | X69: Fully Meets | Y69: 3 | Z69: =VLOOKUP(A69,Table3[],3,0) -> 3 | AA69: =VLOOKUP(A69,'employee_engagement survey data'!A69:E533,4,0) -> 2 | AB69: =VLOOKUP(A69,'employee_engagement survey data'!A69:E308,5,0) -> 2 | AC69: =VLOOKUP(A69,training_and_development!A69:F106,3,0) -> Communication Skills | AD69: =VLOOKUP(A69,training_and_development!A69:E458,4,0) -> External | AE69: =VLOOKUP(A69,training_and_development!A69:F3066,5,0) -> Completed | AF69: =VLOOKUP(A69,training_and_development!A68:G88,6,0) -> Richardmouth | AG69: =VLOOKUP(A69,training_and_development!A69:H77,7,0) -> Ashley Wright | AH69: =VLOOKUP(A69,training_and_development!A69:H72,8,0) -> 1
A70: 1069 | B70: Wyatt Edwards | C70: 43386 | D70: 45074 | E70: Shared Services Manager | F70: Cassandra Smith | G70: sierra.macias@bilearner.com | H70: WBL | I70: Voluntarily Terminated | J70: Full-Time | K70: Zone B | L70: Part-Time | M70: Resignation | N70: Really full stand face explain would keep energy. | O70: Software Engineering | P70: General - Con | Q70: 27650 | R70: MA | S70: Foreman | T70: Female | U70: 30264 | V70: Other | W70: Widowed | X70: Fully Meets | Y70: 3 | Z70: =VLOOKUP(A70,Table3[],3,0) -> 3 | AA70: =VLOOKUP(A70,'employee_engagement survey data'!A70:E534,4,0) -> 1 | AB70: =VLOOKUP(A70,'employee_engagement survey data'!A70:E309,5,0) -> 2 | AC70: =VLOOKUP(A70,training_and_development!A70:F107,3,0) -> Communication Skills | AD70: =VLOOKUP(A70,training_and_development!A70:E459,4,0) -> Internal | AE70: =VLOOKUP(A70,training_and_development!A70:F3067,5,0) -> Failed | AF70: =VLOOKUP(A70,training_and_development!A69:G89,6,0) -> South Angelaview | AG70: =VLOOKUP(A70,training_and_development!A70:H78,7,0) -> Brandi Petersen | AH70: =VLOOKUP(A70,training_and_development!A70:H73,8,0) -> 5
A71: 1070 | B71: Karla Reed | C71: 43449 | D71: 44709 | E71: Shared Services Manager | F71: Warren Baker | G71: pierce.robbins@bilearner.com | H71: NEL | I71: Voluntarily Terminated | J71: Full-Time | K71: Zone C | L71: Temporary | M71: Resignation | N71: Or add data indicate account father early these. | O71: Software Engineering | P71: General - Sga | Q71: 36103 | R71: MA | S71: Project Manager | T71: Male | U71: 22326 | V71: Black | W71: Married | X71: Fully Meets | Y71: 3 | Z71: =VLOOKUP(A71,Table3[],3,0) -> 3 | AA71: =VLOOKUP(A71,'employee_engagement survey data'!A71:E535,4,0) -> 1 | AB71: =VLOOKUP(A71,'employee_engagement survey data'!A71:E310,5,0) -> 2 | AC71: =VLOOKUP(A71,training_and_development!A71:F108,3,0) -> Technical Skills | AD71: =VLOOKUP(A71,training_and_development!A71:E460,4,0) -> Internal | AE71: =VLOOKUP(A71,training_and_development!A71:F3068,5,0) -> Failed | AF71: =VLOOKUP(A71,training_and_development!A70:G90,6,0) -> Robertside | AG71: =VLOOKUP(A71,training_and_development!A71:H79,7,0) -> Zachary Wilson | AH71: =VLOOKUP(A71,training_and_development!A71:H74,8,0) -> 1
A72: 1071 | B72: Yadira Mcmillan | C72: 43552 | D72: 44121 | E72: Software Engineer | F72: Amy Bell | G72: gretchen.richard@bilearner.com | H72: PL | I72: Voluntarily Terminated | J72: Contract | K72: Zone A | L72: Part-Time | M72: Involuntary | N72: Guy ten dream. Thing he care series. | O72: Software Engineering | P72: Field Operations | Q72: 25012 | R72: MA | S72: Laborer | T72: Male | U72: 30139 | V72: Black | W72: Married | X72: Fully Meets | Y72: 3 | Z72: =VLOOKUP(A72,Table3[],3,0) -> 1 | AA72: =VLOOKUP(A72,'employee_engagement survey data'!A72:E536,4,0) -> 2 | AB72: =VLOOKUP(A72,'employee_engagement survey data'!A72:E311,5,0) -> 2 | AC72: =VLOOKUP(A72,training_and_development!A72:F109,3,0) -> Communication Skills | AD72: =VLOOKUP(A72,training_and_development!A72:E461,4,0) -> Internal | AE72: =VLOOKUP(A72,training_and_development!A72:F3069,5,0) -> Completed | AF72: =VLOOKUP(A72,training_and_development!A71:G91,6,0) -> Johnport | AG72: =VLOOKUP(A72,training_and_development!A72:H80,7,0) -> Amanda Medina | AH72: =VLOOKUP(A72,training_and_development!A72:H75,8,0) -> 5
A73: 1072 | B73: Fernando Mcconnell | C73: 43461 | D73: N/A | E73: Software Engineer | F73: Teresa Lopez | G73: maximilian.craig@bilearner.com | H73: BPC | I73: Voluntarily Terminated | J73: Part-Time | K73: Zone C | L73: Part-Time | M73: Unk | N73: N/A | O73: Software Engineering | P73: Field Operations | Q73: 28145 | R73: MA | S73: Operator | T73: Female | U73: 93329 | V73: Asian | W73: Widowed | X73: Fully Meets | Y73: 3 | Z73: =VLOOKUP(A73,Table3[],3,0) -> 2 | AA73: =VLOOKUP(A73,'employee_engagement survey data'!A73:E537,4,0) -> 2 | AB73: =VLOOKUP(A73,'employee_engagement survey data'!A73:E312,5,0) -> 3 | AC73: =VLOOKUP(A73,training_and_development!A73:F110,3,0) -> Technical Skills | AD73: =VLOOKUP(A73,training_and_development!A73:E462,4,0) -> Internal | AE73: =VLOOKUP(A73,training_and_development!A73:F3070,5,0) -> Completed | AF73: =VLOOKUP(A73,training_and_development!A72:G92,6,0) -> Mendozamouth | AG73: =VLOOKUP(A73,training_and_development!A73:H81,7,0) -> Melissa Campos | AH73: =VLOOKUP(A73,training_and_development!A73:H76,8,0) -> 5
A74: 1073 | B74: Sean Bean | C74: 43596 | D74: N/A | E74: Software Engineer | F74: Kimberly Holland | G74: raymond.ayers@bilearner.com | H74: CCDR | I74: Terminated for Cause | J74: Full-Time | K74: Zone A | L74: Full-Time | M74: Unk | N74: N/A | O74: Software Engineering | P74: Field Operations | Q74: 36062 | R74: MA | S74: Foreman | T74: Male | U74: 67825 | V74: White | W74: Single | X74: Fully Meets | Y74: 3 | Z74: =VLOOKUP(A74,Table3[],3,0) -> 4 | AA74: =VLOOKUP(A74,'employee_engagement survey data'!A74:E538,4,0) -> 4 | AB74: =VLOOKUP(A74,'employee_engagement survey data'!A74:E313,5,0) -> 2 | AC74: =VLOOKUP(A74,training_and_development!A74:F111,3,0) -> Project Management | AD74: =VLOOKUP(A74,training_and_development!A74:E463,4,0) -> Internal | AE74: =VLOOKUP(A74,training_and_development!A74:F3071,5,0) -> Failed | AF74: =VLOOKUP(A74,training_and_development!A73:G93,6,0) -> Ivanburgh | AG74: =VLOOKUP(A74,training_and_development!A74:H82,7,0) -> Ryan Hunter | AH74: =VLOOKUP(A74,training_and_development!A74:H77,8,0) -> 4
A75: 1074 | B75: Lilianna Mccall | C75: 44246 | D75: 44981 | E75: Software Engineer | F75: Robert Garcia | G75: vincent.wyatt@bilearner.com | H75: SVG | I75: Terminated for Cause | J75: Full-Time | K75: Zone A | L75: Temporary | M75: Voluntary | N75: Professional usually hospital worker among. | O75: Software Engineering | P75: General - Con | Q75: 30505 | R75: MA | S75: Laborer | T75: Male | U75: 86545 | V75: Asian | W75: Divorced | X75: Fully Meets | Y75: 3 | Z75: =VLOOKUP(A75,Table3[],3,0) -> 3 | AA75: =VLOOKUP(A75,'employee_engagement survey data'!A75:E539,4,0) -> 4 | AB75: =VLOOKUP(A75,'employee_engagement survey data'!A75:E314,5,0) -> 1 | AC75: =VLOOKUP(A75,training_and_development!A75:F112,3,0) -> Project Management | AD75: =VLOOKUP(A75,training_and_development!A75:E464,4,0) -> Internal | AE75: =VLOOKUP(A75,training_and_development!A75:F3072,5,0) -> Completed | AF75: =VLOOKUP(A75,training_and_development!A74:G94,6,0) -> Davisberg | AG75: =VLOOKUP(A75,training_and_development!A75:H83,7,0) -> Ashley Garrett | AH75: =VLOOKUP(A75,training_and_development!A75:H78,8,0) -> 5
A76: 1075 | B76: Salvador Thomas | C76: 44870 | D76: 45032 | E76: Software Engineer | F76: Nicholas Martinez | G76: micah.stanley@bilearner.com | H76: EW | I76: Voluntarily Terminated | J76: Part-Time | K76: Zone B | L76: Full-Time | M76: Involuntary | N76: Health American identify meeting. | O76: Software Engineering | P76: Engineers | Q76: 24951 | R76: MA | S76: Engineer | T76: Male | U76: 76670 | V76: Asian | W76: Married | X76: Fully Meets | Y76: 3 | Z76: =VLOOKUP(A76,Table3[],3,0) -> 1 | AA76: =VLOOKUP(A76,'employee_engagement survey data'!A76:E540,4,0) -> 2 | AB76: =VLOOKUP(A76,'employee_engagement survey data'!A76:E315,5,0) -> 3 | AC76: =VLOOKUP(A76,training_and_development!A76:F113,3,0) -> Project Management | AD76: =VLOOKUP(A76,training_and_development!A76:E465,4,0) -> Internal | AE76: =VLOOKUP(A76,training_and_development!A76:F3073,5,0) -> Completed | AF76: =VLOOKUP(A76,training_and_development!A75:G95,6,0) -> East Darryl | AG76: =VLOOKUP(A76,training_and_development!A76:H84,7,0) -> Ronald Ortiz | AH76: =VLOOKUP(A76,training_and_development!A76:H79,8,0) -> 4
A77: 1076 | B77: Jair Silva | C77: 43912 | D77: 44102 | E77: Software Engineer | F77: Carlos Barnes | G77: calvin.braun@bilearner.com | H77: MSC | I77: Terminated for Cause | J77: Contract | K77: Zone C | L77: Part-Time | M77: Retirement | N77: Gun bill spend anyone. | O77: Software Engineering | P77: General - Eng | Q77: 15734 | R77: MA | S77: Administrative | T77: Female | U77: 29368 | V77: White | W77: Widowed | X77: Fully Meets | Y77: 3 | Z77: =VLOOKUP(A77,Table3[],3,0) -> 1 | AA77: =VLOOKUP(A77,'employee_engagement survey data'!A77:E541,4,0) -> 3 | AB77: =VLOOKUP(A77,'employee_engagement survey data'!A77:E316,5,0) -> 1 | AC77: =VLOOKUP(A77,training_and_development!A77:F114,3,0) -> Technical Skills | AD77: =VLOOKUP(A77,training_and_development!A77:E466,4,0) -> External | AE77: =VLOOKUP(A77,training_and_development!A77:F3074,5,0) -> Failed | AF77: =VLOOKUP(A77,training_and_development!A76:G96,6,0) -> Jamieville | AG77: =VLOOKUP(A77,training_and_development!A77:H85,7,0) -> Becky Hebert | AH77: =VLOOKUP(A77,training_and_development!A77:H80,8,0) -> 4
A78: 1077 | B78: Derek Moreno | C78: 43498 | D78: N/A | E78: Software Engineer | F78: Allison Jacobs | G78: cale.bender@bilearner.com | H78: TNS | I78: Terminated for Cause | J78: Contract | K78: Zone B | L78: Temporary | M78: Unk | N78: N/A | O78: Software Engineering | P78: Wireless | Q78: 33734 | R78: MA | S78: Foreman | T78: Female | U78: 97585 | V78: Black | W78: Single | X78: Fully Meets | Y78: 3 | Z78: =VLOOKUP(A78,Table3[],3,0) -> 5 | AA78: =VLOOKUP(A78,'employee_engagement survey data'!A78:E542,4,0) -> 2 | AB78: =VLOOKUP(A78,'employee_engagement survey data'!A78:E317,5,0) -> 4 | AC78: =VLOOKUP(A78,training_and_development!A78:F115,3,0) -> Project Management | AD78: =VLOOKUP(A78,training_and_development!A78:E467,4,0) -> Internal | AE78: =VLOOKUP(A78,training_and_development!A78:F3075,5,0) -> Failed | AF78: =VLOOKUP(A78,training_and_development!A77:G97,6,0) -> West Brookechester | AG78: =VLOOKUP(A78,training_and_development!A78:H86,7,0) -> Joshua Kirk | AH78: =VLOOKUP(A78,training_and_development!A78:H81,8,0) -> 1
A79: 1078 | B79: Litzy Conner | C79: 43885 | D79: 44363 | E79: Software Engineer | F79: Angela Ramsey | G79: elianna.schmitt@bilearner.com | H79: PYZ | I79: Voluntarily Terminated | J79: Contract | K79: Zone C | L79: Temporary | M79: Voluntary | N79: Crime west best industry right alone begin. | O79: Software Engineering | P79: Aerial | Q79: 35508 | R79: MA | S79: Foreman | T79: Female | U79: 42710 | V79: Asian | W79: Divorced | X79: Fully Meets | Y79: 3 | Z79: =VLOOKUP(A79,Table3[],3,0) -> 3 | AA79: =VLOOKUP(A79,'employee_engagement survey data'!A79:E543,4,0) -> 3 | AB79: =VLOOKUP(A79,'employee_engagement survey data'!A79:E318,5,0) -> 4 | AC79: =VLOOKUP(A79,training_and_development!A79:F116,3,0) -> Project Management | AD79: =VLOOKUP(A79,training_and_development!A79:E468,4,0) -> External | AE79: =VLOOKUP(A79,training_and_development!A79:F3076,5,0) -> Completed | AF79: =VLOOKUP(A79,training_and_development!A78:G98,6,0) -> Villanuevaborough | AG79: =VLOOKUP(A79,training_and_development!A79:H87,7,0) -> Patrick Bryant | AH79: =VLOOKUP(A79,training_and_development!A79:H82,8,0) -> 1
A80: 1079 | B80: Joanna Burnett | C80: 44293 | D80: 44682 | E80: Shared Services Manager | F80: Malik Smith | G80: ernest.willis@bilearner.com | H80: WBL | I80: Voluntarily Terminated | J80: Part-Time | K80: Zone B | L80: Full-Time | M80: Resignation | N80: Story knowledge policy. Board tax treatment. | O80: Software Engineering | P80: Project Management - Eng | Q80: 36627 | R80: MA | S80: Manager | T80: Female | U80: 21279 | V80: Hispanic | W80: Divorced | X80: Fully Meets | Y80: 3 | Z80: =VLOOKUP(A80,Table3[],3,0) -> 2 | AA80: =VLOOKUP(A80,'employee_engagement survey data'!A80:E544,4,0) -> 2 | AB80: =VLOOKUP(A80,'employee_engagement survey data'!A80:E319,5,0) -> 1 | AC80: =VLOOKUP(A80,training_and_development!A80:F117,3,0) -> Communication Skills | AD80: =VLOOKUP(A80,training_and_development!A80:E469,4,0) -> External | AE80: =VLOOKUP(A80,training_and_development!A80:F3077,5,0) -> Failed | AF80: =VLOOKUP(A80,training_and_development!A79:G99,6,0) -> North Jon | AG80: =VLOOKUP(A80,training_and_development!A80:H88,7,0) -> Maria Jones | AH80: =VLOOKUP(A80,training_and_development!A80:H83,8,0) -> 5
A81: 1080 | B81: Abdullah Frederick | C81: 44149 | D81: N/A | E81: Shared Services Manager | F81: Jessica Lewis | G81: davis.roberts@bilearner.com | H81: NEL | I81: Voluntarily Terminated | J81: Part-Time | K81: Zone C | L81: Full-Time | M81: Unk | N81: N/A | O81: Software Engineering | P81: Fielders | Q81: 32359 | R81: MA | S81: Engineer | T81: Male | U81: 17976 | V81: Black | W81: Widowed | X81: Fully Meets | Y81: 3 | Z81: =VLOOKUP(A81,Table3[],3,0) -> 3 | AA81: =VLOOKUP(A81,'employee_engagement survey data'!A81:E545,4,0) -> 1 | AB81: =VLOOKUP(A81,'employee_engagement survey data'!A81:E320,5,0) -> 3 | AC81: =VLOOKUP(A81,training_and_development!A81:F118,3,0) -> Customer Service | AD81: =VLOOKUP(A81,training_and_development!A81:E470,4,0) -> External | AE81: =VLOOKUP(A81,training_and_development!A81:F3078,5,0) -> Completed | AF81: =VLOOKUP(A81,training_and_development!A80:G100,6,0) -> Mcleanburgh | AG81: =VLOOKUP(A81,training_and_development!A81:H89,7,0) -> Sandra Joseph | AH81: =VLOOKUP(A81,training_and_development!A81:H84,8,0) -> 4
A82: 1081 | B82: Armani Porter | C82: 44578 | D82: 44783 | E82: Software Engineer | F82: Kayla Ibarra | G82: meadow.avery@bilearner.com | H82: EW | I82: Voluntarily Terminated | J82: Contract | K82: Zone B | L82: Part-Time | M82: Involuntary | N82: Imagine plant southern sound reduce. | O82: Software Engineering | P82: General - Con | Q82: 23978 | R82: MA | S82: Laborer | T82: Male | U82: 53628 | V82: Asian | W82: Divorced | X82: Fully Meets | Y82: 3 | Z82: =VLOOKUP(A82,Table3[],3,0) -> 1 | AA82: =VLOOKUP(A82,'employee_engagement survey data'!A82:E546,4,0) -> 3 | AB82: =VLOOKUP(A82,'employee_engagement survey data'!A82:E321,5,0) -> 3 | AC82: =VLOOKUP(A82,training_and_development!A82:F119,3,0) -> Communication Skills | AD82: =VLOOKUP(A82,training_and_development!A82:E471,4,0) -> External | AE82: =VLOOKUP(A82,training_and_development!A82:F3079,5,0) -> Failed | AF82: =VLOOKUP(A82,training_and_development!A81:G101,6,0) -> Brandonview | AG82: =VLOOKUP(A82,training_and_development!A82:H90,7,0) -> Samuel Wilson | AH82: =VLOOKUP(A82,training_and_development!A82:H85,8,0) -> 3
A83: 1082 | B83: Taylor Sanders | C83: 44441 | D83: 45104 | E83: Software Engineer | F83: Ryan Mathews | G83: allyson.owen@bilearner.com | H83: MSC | I83: Voluntarily Terminated | J83: Part-Time | K83: Zone B | L83: Part-Time | M83: Retirement | N83: Resource top fear shake green view great which. | O83: Software Engineering | P83: General - Con | Q83: 27822 | R83: MA | S83: Technician | T83: Male | U83: 84761 | V83: Other | W83: Married | X83: Fully Meets | Y83: 3 | Z83: =VLOOKUP(A83,Table3[],3,0) -> 1 | AA83: =VLOOKUP(A83,'employee_engagement survey data'!A83:E547,4,0) -> 4 | AB83: =VLOOKUP(A83,'employee_engagement survey data'!A83:E322,5,0) -> 1 | AC83: =VLOOKUP(A83,training_and_development!A83:F120,3,0) -> Customer Service | AD83: =VLOOKUP(A83,training_and_development!A83:E472,4,0) -> External | AE83: =VLOOKUP(A83,training_and_development!A83:F3080,5,0) -> Failed | AF83: =VLOOKUP(A83,training_and_development!A82:G102,6,0) -> New Colinfort | AG83: =VLOOKUP(A83,training_and_development!A83:H91,7,0) -> Angela Colon | AH83: =VLOOKUP(A83,training_and_development!A83:H86,8,0) -> 5
A84: 1083 | B84: Iliana Randall | C84: 45137 | D84: N/A | E84: Software Engineer | F84: Melissa Scott | G84: francisco.simon@bilearner.com | H84: NEL | I84: Voluntarily Terminated | J84: Part-Time | K84: Zone A | L84: Full-Time | M84: Unk | N84: N/A | O84: Software Engineering | P84: Aerial | Q84: 23020 | R84: MA | S84: Supervisor | T84: Female | U84: 2187 | V84: Asian | W84: Divorced | X84: Fully Meets | Y84: 3 | Z84: =VLOOKUP(A84,Table3[],3,0) -> 5 | AA84: =VLOOKUP(A84,'employee_engagement survey data'!A84:E548,4,0) -> 5 | AB84: =VLOOKUP(A84,'employee_engagement survey data'!A84:E323,5,0) -> 3 | AC84: =VLOOKUP(A84,training_and_development!A84:F121,3,0) -> Project Management | AD84: =VLOOKUP(A84,training_and_development!A84:E473,4,0) -> External | AE84: =VLOOKUP(A84,training_and_development!A84:F3081,5,0) -> Completed | AF84: =VLOOKUP(A84,training_and_development!A83:G103,6,0) -> North Brandy | AG84: =VLOOKUP(A84,training_and_development!A84:H92,7,0) -> Molly Hughes | AH84: =VLOOKUP(A84,training_and_development!A84:H87,8,0) -> 4
A85: 1084 | B85: Luke Henderson | C85: 45104 | D85: N/A | E85: Software Engineer | F85: Robert Schmitt | G85: chaya.boyd@bilearner.com | H85: PL | I85: Voluntarily Terminated | J85: Contract | K85: Zone C | L85: Part-Time | M85: Unk | N85: N/A | O85: Software Engineering | P85: Executive | Q85: 32732 | R85: MA | S85: Administrator | T85: Male | U85: 76615 | V85: White | W85: Single | X85: Fully Meets | Y85: 3 | Z85: =VLOOKUP(A85,Table3[],3,0) -> 1 | AA85: =VLOOKUP(A85,'employee_engagement survey data'!A85:E549,4,0) -> 2 | AB85: =VLOOKUP(A85,'employee_engagement survey data'!A85:E324,5,0) -> 4 | AC85: =VLOOKUP(A85,training_and_development!A85:F122,3,0) -> Leadership Development | AD85: =VLOOKUP(A85,training_and_development!A85:E474,4,0) -> External | AE85: =VLOOKUP(A85,training_and_development!A85:F3082,5,0) -> Completed | AF85: =VLOOKUP(A85,training_and_development!A84:G104,6,0) -> West Jessicatown | AG85: =VLOOKUP(A85,training_and_development!A85:H93,7,0) -> Morgan Thomas | AH85: =VLOOKUP(A85,training_and_development!A85:H88,8,0) -> 3
A86: 1085 | B86: Madelyn Lambert | C86: 44647 | D86: N/A | E86: Software Engineer | F86: Patricia Wallace | G86: wyatt.spence@bilearner.com | H86: PYZ | I86: Voluntarily Terminated | J86: Contract | K86: Zone B | L86: Full-Time | M86: Unk | N86: N/A | O86: Software Engineering | P86: General - Con | Q86: 19063 | R86: MA | S86: Lineman | T86: Male | U86: 18707 | V86: Other | W86: Divorced | X86: Fully Meets | Y86: 3 | Z86: =VLOOKUP(A86,Table3[],3,0) -> 5 | AA86: =VLOOKUP(A86,'employee_engagement survey data'!A86:E550,4,0) -> 5 | AB86: =VLOOKUP(A86,'employee_engagement survey data'!A86:E325,5,0) -> 3 | AC86: =VLOOKUP(A86,training_and_development!A86:F123,3,0) -> Customer Service | AD86: =VLOOKUP(A86,training_and_development!A86:E475,4,0) -> External | AE86: =VLOOKUP(A86,training_and_development!A86:F3083,5,0) -> Completed | AF86: =VLOOKUP(A86,training_and_development!A85:G105,6,0) -> East Katherinetown | AG86: =VLOOKUP(A86,training_and_development!A86:H94,7,0) -> Bradley Petersen | AH86: =VLOOKUP(A86,training_and_development!A86:H89,8,0) -> 5
A87: 1086 | B87: Ava Pace | C87: 44785 | D87: 44854 | E87: Software Engineer | F87: Justin Young | G87: jayleen.oconnell@bilearner.com | H87: SVG | I87: Voluntarily Terminated | J87: Contract | K87: Zone A | L87: Temporary | M87: Voluntary | N87: Thousand both simple network let. | O87: Software Engineering | P87: Field Operations | Q87: 26875 | R87: MA | S87: Supervisor | T87: Female | U87: 23203 | V87: Black | W87: Single | X87: Fully Meets | Y87: 3 | Z87: =VLOOKUP(A87,Table3[],3,0) -> 1 | AA87: =VLOOKUP(A87,'employee_engagement survey data'!A87:E551,4,0) -> 1 | AB87: =VLOOKUP(A87,'employee_engagement survey data'!A87:E326,5,0) -> 5 | AC87: =VLOOKUP(A87,training_and_development!A87:F124,3,0) -> Leadership Development | AD87: =VLOOKUP(A87,training_and_development!A87:E476,4,0) -> External | AE87: =VLOOKUP(A87,training_and_development!A87:F3084,5,0) -> Completed | AF87: =VLOOKUP(A87,training_and_development!A86:G106,6,0) -> East Robertside | AG87: =VLOOKUP(A87,training_and_development!A87:H95,7,0) -> Patrick Andrews | AH87: =VLOOKUP(A87,training_and_development!A87:H90,8,0) -> 2
A88: 1087 | B88: Delaney Bruce | C88: 44750 | D88: 45142 | E88: Software Engineer | F88: Robert Salinas | G88: carlie.wilkerson@bilearner.com | H88: TNS | I88: Voluntarily Terminated | J88: Part-Time | K88: Zone A | L88: Part-Time | M88: Voluntary | N88: Party explain perhaps. | O88: Software Engineering | P88: Field Operations | Q88: 27246 | R88: MA | S88: Tower Hand | T88: Female | U88: 18844 | V88: Other | W88: Married | X88: Fully Meets | Y88: 3 | Z88: =VLOOKUP(A88,Table3[],3,0) -> 1 | AA88: =VLOOKUP(A88,'employee_engagement survey data'!A88:E552,4,0) -> 5 | AB88: =VLOOKUP(A88,'employee_engagement survey data'!A88:E327,5,0) -> 2 | AC88: =VLOOKUP(A88,training_and_development!A88:F125,3,0) -> Technical Skills | AD88: =VLOOKUP(A88,training_and_development!A88:E477,4,0) -> Internal | AE88: =VLOOKUP(A88,training_and_development!A88:F3085,5,0) -> Failed | AF88: =VLOOKUP(A88,training_and_development!A87:G107,6,0) -> Heatherview | AG88: =VLOOKUP(A88,training_and_development!A88:H96,7,0) -> Ryan Crawford | AH88: =VLOOKUP(A88,training_and_development!A88:H91,8,0) -> 5
A89: 1088 | B89: Jair Bullock | C89: 44058 | D89: 44219 | E89: Software Engineer | F89: Mary Anderson | G89: kaylyn.patrick@bilearner.com | H89: WBL | I89: Voluntarily Terminated | J89: Contract | K89: Zone B | L89: Part-Time | M89: Resignation | N89: Specific fire rate fly clearly. | O89: Software Engineering | P89: General - Con | Q89: 33336 | R89: MA | S89: Foreman | T89: Female | U89: 64815 | V89: White | W89: Widowed | X89: Fully Meets | Y89: 3 | Z89: =VLOOKUP(A89,Table3[],3,0) -> 4 | AA89: =VLOOKUP(A89,'employee_engagement survey data'!A89:E553,4,0) -> 3 | AB89: =VLOOKUP(A89,'employee_engagement survey data'!A89:E328,5,0) -> 1 | AC89: =VLOOKUP(A89,training_and_development!A89:F126,3,0) -> Leadership Development | AD89: =VLOOKUP(A89,training_and_development!A89:E478,4,0) -> External | AE89: =VLOOKUP(A89,training_and_development!A89:F3086,5,0) -> Failed | AF89: =VLOOKUP(A89,training_and_development!A88:G108,6,0) -> North Elizabeth | AG89: =VLOOKUP(A89,training_and_development!A89:H97,7,0) -> Keith Richardson | AH89: =VLOOKUP(A89,training_and_development!A89:H92,8,0) -> 2
A90: 1089 | B90: Kayla Farrell | C90: 45073 | D90: 45091 | E90: Software Engineer | F90: Jennifer Stevens | G90: evie.pope@bilearner.com | H90: BPC | I90: Voluntarily Terminated | J90: Full-Time | K90: Zone A | L90: Temporary | M90: Involuntary | N90: Your plant win seem hair him career style. | O90: Software Engineering | P90: Wireline Construction | Q90: 19478 | R90: MA | S90: Groundman | T90: Female | U90: 69860 | V90: Black | W90: Married | X90: Fully Meets | Y90: 3 | Z90: =VLOOKUP(A90,Table3[],3,0) -> 3 | AA90: =VLOOKUP(A90,'employee_engagement survey data'!A90:E554,4,0) -> 1 | AB90: =VLOOKUP(A90,'employee_engagement survey data'!A90:E329,5,0) -> 5 | AC90: =VLOOKUP(A90,training_and_development!A90:F127,3,0) -> Technical Skills | AD90: =VLOOKUP(A90,training_and_development!A90:E479,4,0) -> Internal | AE90: =VLOOKUP(A90,training_and_development!A90:F3087,5,0) -> Completed | AF90: =VLOOKUP(A90,training_and_development!A89:G109,6,0) -> North Amanda | AG90: =VLOOKUP(A90,training_and_development!A90:H98,7,0) -> Jasmin Walker | AH90: =VLOOKUP(A90,training_and_development!A90:H93,8,0) -> 2
A91: 1090 | B91: Taylor Gamble | C91: 44928 | D91: N/A | E91: Shared Services Manager | F91: Jennifer Murphy | G91: nayeli.kelley@bilearner.com | H91: CCDR | I91: Voluntarily Terminated | J91: Part-Time | K91: Zone C | L91: Full-Time | M91: Unk | N91: N/A | O91: Software Engineering | P91: Field Operations | Q91: 23982 | R91: MA | S91: Technician | T91: Female | U91: 93542 | V91: Black | W91: Divorced | X91: Fully Meets | Y91: 3 | Z91: =VLOOKUP(A91,Table3[],3,0) -> 4 | AA91: =VLOOKUP(A91,'employee_engagement survey data'!A91:E555,4,0) -> 3 | AB91: =VLOOKUP(A91,'employee_engagement survey data'!A91:E330,5,0) -> 4 | AC91: =VLOOKUP(A91,training_and_development!A91:F128,3,0) -> Communication Skills | AD91: =VLOOKUP(A91,training_and_development!A91:E480,4,0) -> External | AE91: =VLOOKUP(A91,training_and_development!A91:F3088,5,0) -> Completed | AF91: =VLOOKUP(A91,training_and_development!A90:G110,6,0) -> Wrightton | AG91: =VLOOKUP(A91,training_and_development!A91:H99,7,0) -> Tracy Sanchez | AH91: =VLOOKUP(A91,training_and_development!A91:H94,8,0) -> 1
A92: 1091 | B92: Carl Desimone | C92: 43420 | D92: 44289 | E92: Production Technician I | F92: Daniel Booth | G92: dorian.fox@bilearner.com | H92: PYZ | I92: Voluntarily Terminated | J92: Contract | K92: Zone B | L92: Temporary | M92: Involuntary | N92: Fine use card current agent. | O92: Production | P92: General - Sga | Q92: 31650 | R92: MA | S92: Supervisor | T92: Male | U92: 2061 | V92: Asian | W92: Single | X92: Fully Meets | Y92: 3 | Z92: =VLOOKUP(A92,Table3[],3,0) -> 2 | AA92: =VLOOKUP(A92,'employee_engagement survey data'!A92:E556,4,0) -> 4 | AB92: =VLOOKUP(A92,'employee_engagement survey data'!A92:E331,5,0) -> 3 | AC92: =VLOOKUP(A92,training_and_development!A92:F129,3,0) -> Customer Service | AD92: =VLOOKUP(A92,training_and_development!A92:E481,4,0) -> Internal | AE92: =VLOOKUP(A92,training_and_development!A92:F3089,5,0) -> Failed | AF92: =VLOOKUP(A92,training_and_development!A91:G111,6,0) -> Port Patricia | AG92: =VLOOKUP(A92,training_and_development!A92:H100,7,0) -> Jennifer Bailey | AH92: =VLOOKUP(A92,training_and_development!A92:H95,8,0) -> 2
A93: 1092 | B93: Sophia Theamstern | C93: 44754 | D93: N/A | E93: Production Technician I | F93: Martin Jackson | G93: gunnar.webster@bilearner.com | H93: PYZ | I93: Voluntarily Terminated | J93: Part-Time | K93: Zone C | L93: Full-Time | M93: Unk | N93: N/A | O93: Production | P93: Field Operations | Q93: 25595 | R93: MA | S93: Clerk | T93: Female | U93: 2066 | V93: Hispanic | W93: Divorced | X93: Fully Meets | Y93: 3 | Z93: =VLOOKUP(A93,Table3[],3,0) -> 1 | AA93: =VLOOKUP(A93,'employee_engagement survey data'!A93:E557,4,0) -> 4 | AB93: =VLOOKUP(A93,'employee_engagement survey data'!A93:E332,5,0) -> 1 | AC93: =VLOOKUP(A93,training_and_development!A93:F130,3,0) -> Communication Skills | AD93: =VLOOKUP(A93,training_and_development!A93:E482,4,0) -> Internal | AE93: =VLOOKUP(A93,training_and_development!A93:F3090,5,0) -> Completed | AF93: =VLOOKUP(A93,training_and_development!A92:G112,6,0) -> Wilkinsfurt | AG93: =VLOOKUP(A93,training_and_development!A93:H101,7,0) -> Heather Gutierrez | AH93: =VLOOKUP(A93,training_and_development!A93:H96,8,0) -> 5
A94: 1093 | B94: Kara Harrison | C94: 44911 | D94: N/A | E94: Production Technician I | F94: Elizabeth Richards | G94: patrick.mckinney@bilearner.com | H94: NEL | I94: Voluntarily Terminated | J94: Contract | K94: Zone B | L94: Part-Time | M94: Unk | N94: N/A | O94: Production | P94: Engineers | Q94: 28971 | R94: MA | S94: Engineer | T94: Female | U94: 1886 | V94: Asian | W94: Widowed | X94: Fully Meets | Y94: 3 | Z94: =VLOOKUP(A94,Table3[],3,0) -> 3 | AA94: =VLOOKUP(A94,'employee_engagement survey data'!A94:E558,4,0) -> 1 | AB94: =VLOOKUP(A94,'employee_engagement survey data'!A94:E333,5,0) -> 4 | AC94: =VLOOKUP(A94,training_and_development!A94:F131,3,0) -> Customer Service | AD94: =VLOOKUP(A94,training_and_development!A94:E483,4,0) -> External | AE94: =VLOOKUP(A94,training_and_development!A94:F3091,5,0) -> Failed | AF94: =VLOOKUP(A94,training_and_development!A93:G113,6,0) -> West Matthew | AG94: =VLOOKUP(A94,training_and_development!A94:H102,7,0) -> George Burns | AH94: =VLOOKUP(A94,training_and_development!A94:H97,8,0) -> 5
A95: 1094 | B95: Ming Huynh | C95: 45054 | D95: N/A | E95: Production Technician II | F95: Jose Bray | G95: reagan.odonnell@bilearner.com | H95: EW | I95: Terminated for Cause | J95: Part-Time | K95: Zone A | L95: Full-Time | M95: Unk | N95: N/A | O95: Production | P95: Field Operations | Q95: 34411 | R95: MA | S95: Foreman | T95: Female | U95: 1742 | V95: Other | W95: Single | X95: Fully Meets | Y95: 3 | Z95: =VLOOKUP(A95,Table3[],3,0) -> 5 | AA95: =VLOOKUP(A95,'employee_engagement survey data'!A95:E559,4,0) -> 4 | AB95: =VLOOKUP(A95,'employee_engagement survey data'!A95:E334,5,0) -> 5 | AC95: =VLOOKUP(A95,training_and_development!A95:F132,3,0) -> Communication Skills | AD95: =VLOOKUP(A95,training_and_development!A95:E484,4,0) -> Internal | AE95: =VLOOKUP(A95,training_and_development!A95:F3092,5,0) -> Failed | AF95: =VLOOKUP(A95,training_and_development!A94:G114,6,0) -> South Joshuatown | AG95: =VLOOKUP(A95,training_and_development!A95:H103,7,0) -> Richard Mckee | AH95: =VLOOKUP(A95,training_and_development!A95:H98,8,0) -> 4
A96: 1095 | B96: Karen Mancuso | C96: 45023 | D96: N/A | E96: Production Technician II | F96: Jamie Frye | G96: roy.morse@bilearner.com | H96: WBL | I96: Voluntarily Terminated | J96: Full-Time | K96: Zone A | L96: Temporary | M96: Unk | N96: N/A | O96: Production | P96: Engineers | Q96: 15308 | R96: MA | S96: Engineer | T96: Female | U96: 2176 | V96: Hispanic | W96: Divorced | X96: Fully Meets | Y96: 3 | Z96: =VLOOKUP(A96,Table3[],3,0) -> 1 | AA96: =VLOOKUP(A96,'employee_engagement survey data'!A96:E560,4,0) -> 2 | AB96: =VLOOKUP(A96,'employee_engagement survey data'!A96:E335,5,0) -> 1 | AC96: =VLOOKUP(A96,training_and_development!A96:F133,3,0) -> Customer Service | AD96: =VLOOKUP(A96,training_and_development!A96:E485,4,0) -> Internal | AE96: =VLOOKUP(A96,training_and_development!A96:F3093,5,0) -> Completed | AF96: =VLOOKUP(A96,training_and_development!A95:G115,6,0) -> New Kimberly | AG96: =VLOOKUP(A96,training_and_development!A96:H104,7,0) -> Jeremy Schneider | AH96: =VLOOKUP(A96,training_and_development!A96:H99,8,0) -> 4
A97: 1096 | B97: Linda Anderson | C97: 44607 | D97: 44853 | E97: Production Technician I | F97: Adam Hunt | G97: rafael.buchanan@bilearner.com | H97: PYZ | I97: Voluntarily Terminated | J97: Part-Time | K97: Zone C | L97: Part-Time | M97: Voluntary | N97: Issue loss day provide everyone white. | O97: Production | P97: Shop (Fleet) | Q97: 26675 | R97: MA | S97: Mechanic | T97: Female | U97: 1844 | V97: Asian | W97: Married | X97: Fully Meets | Y97: 3 | Z97: =VLOOKUP(A97,Table3[],3,0) -> 1 | AA97: =VLOOKUP(A97,'employee_engagement survey data'!A97:E561,4,0) -> 3 | AB97: =VLOOKUP(A97,'employee_engagement survey data'!A97:E336,5,0) -> 2 | AC97: =VLOOKUP(A97,training_and_development!A97:F134,3,0) -> Technical Skills | AD97: =VLOOKUP(A97,training_and_development!A97:E486,4,0) -> External | AE97: =VLOOKUP(A97,training_and_development!A97:F3094,5,0) -> Failed | AF97: =VLOOKUP(A97,training_and_development!A96:G116,6,0) -> Alexandriachester | AG97: =VLOOKUP(A97,training_and_development!A97:H105,7,0) -> Adam Robinson | AH97: =VLOOKUP(A97,training_and_development!A97:H100,8,0) -> 5
A98: 1097 | B98: Nilson Fernandes | C98: 45124 | D98: 45141 | E98: Production Technician I | F98: Jeffrey Saunders | G98: jamarion.mitchell@bilearner.com | H98: SVG | I98: Voluntarily Terminated | J98: Contract | K98: Zone B | L98: Part-Time | M98: Involuntary | N98: Blue star hospital work. | O98: Production | P98: Field Operations | Q98: 36374 | R98: MA | S98: Technician | T98: Male | U98: 2132 | V98: Hispanic | W98: Divorced | X98: Fully Meets | Y98: 3 | Z98: =VLOOKUP(A98,Table3[],3,0) -> 1 | AA98: =VLOOKUP(A98,'employee_engagement survey data'!A98:E562,4,0) -> 2 | AB98: =VLOOKUP(A98,'employee_engagement survey data'!A98:E337,5,0) -> 5 | AC98: =VLOOKUP(A98,training_and_development!A98:F135,3,0) -> Customer Service | AD98: =VLOOKUP(A98,training_and_development!A98:E487,4,0) -> Internal | AE98: =VLOOKUP(A98,training_and_development!A98:F3095,5,0) -> Completed | AF98: =VLOOKUP(A98,training_and_development!A97:G117,6,0) -> Port Danielmouth | AG98: =VLOOKUP(A98,training_and_development!A98:H106,7,0) -> Ryan Bradley | AH98: =VLOOKUP(A98,training_and_development!A98:H101,8,0) -> 1
A99: 1098 | B99: Alain Robinson | C99: 43588 | D99: 45079 | E99: Production Technician I | F99: Stephanie Griffin | G99: gabrielle.hardy@bilearner.com | H99: PL | I99: Voluntarily Terminated | J99: Part-Time | K99: Zone A | L99: Temporary | M99: Involuntary | N99: Meet fight night. Image room nation. | O99: Production | P99: General - Eng | Q99: 33979 | R99: MA | S99: Engineer | T99: Male | U99: 1420 | V99: Asian | W99: Widowed | X99: Fully Meets | Y99: 3 | Z99: =VLOOKUP(A99,Table3[],3,0) -> 2 | AA99: =VLOOKUP(A99,'employee_engagement survey data'!A99:E563,4,0) -> 2 | AB99: =VLOOKUP(A99,'employee_engagement survey data'!A99:E338,5,0) -> 2 | AC99: =VLOOKUP(A99,training_and_development!A99:F136,3,0) -> Leadership Development | AD99: =VLOOKUP(A99,training_and_development!A99:E488,4,0) -> External | AE99: =VLOOKUP(A99,training_and_development!A99:F3096,5,0) -> Failed | AF99: =VLOOKUP(A99,training_and_development!A98:G118,6,0) -> Rachelshire | AG99: =VLOOKUP(A99,training_and_development!A99:H107,7,0) -> Kimberly Smith | AH99: =VLOOKUP(A99,training_and_development!A99:H102,8,0) -> 5
A100: 1099 | B100: Seffi Shields | C100: 44645 | D100: 44673 | E100: Production Technician I | F100: Robert Sullivan | G100: savion.stokes@bilearner.com | H100: SVG | I100: Voluntarily Terminated | J100: Part-Time | K100: Zone A | L100: Part-Time | M100: Retirement | N100: Person say might throw war scientist. | O100: Production | P100: Field Operations | Q100: 26291 | R100: MA | S100: Laborer | T100: Female | U100: 2149 | V100: Other | W100: Single | X100: Fully Meets | Y100: 3 | Z100: =VLOOKUP(A100,Table3[],3,0) -> 1 | AA100: =VLOOKUP(A100,'employee_engagement survey data'!A100:E564,4,0) -> 5 | AB100: =VLOOKUP(A100,'employee_engagement survey data'!A100:E339,5,0) -> 5 | AC100: =VLOOKUP(A100,training_and_development!A100:F137,3,0) -> Project Management | AD100: =VLOOKUP(A100,training_and_development!A100:E489,4,0) -> External | AE100: =VLOOKUP(A100,training_and_development!A100:F3097,5,0) -> Failed | AF100: =VLOOKUP(A100,training_and_development!A99:G119,6,0) -> Arthurmouth | AG100: =VLOOKUP(A100,training_and_development!A100:H108,7,0) -> Linda Carter | AH100: =VLOOKUP(A100,training_and_development!A100:H103,8,0) -> 5
...

Sheet Pivot table representation
A3: EMPLOYEE COUNT & WORKFORCE STATUS ANALYSIS | E3: Employee Training Program Analysis | I3: Employee Rating
A4: Row Labels | B4: Count of EmpID | C4: Count of EmpID2 | I4: Row Labels | J4: Count of EmpID | K4: Count of EmpID2 | L4: Average of Current Employee Rating
A5: Active | B5: 1661 | C5: 0.55366667 | E5: Row Labels | F5: Sum of Training Cost | G5: Count of Training Outcome | I5: 3 | J5: 1530 | K5: 0.51 | L5: 3
A6: Future Start | B6: 58 | C6: 0.019333333 | E6: Communication Skills | F6: 365023.24 | G6: 0.22433333 | I6: 2 | J6: 510 | K6: 0.17 | L6: 2
A7: Leave of Absence | B7: 74 | C7: 0.024666667 | E7: Completed | F7: 197284.38 | G7: 0.12066667 | I7: 4 | J7: 419 | K7: 0.13966667 | L7: 4
A8: Terminated for Cause | B8: 272 | C8: 0.090666667 | E8: Failed | F8: 167738.86 | G8: 0.10366667 | I8: 1 | J8: 271 | K8: 0.090333333 | L8: 1
A9: Voluntarily Terminated | B9: 935 | C9: 0.31166667 | E9: Customer Service | F9: 320575.04 | G9: 0.18833333 | I9: 5 | J9: 270 | K9: 0.09 | L9: 5
A10: Grand Total | B10: 3000 | C10: 1 | E10: Completed | F10: 172891.95 | G10: 0.099333333 | I10: Grand Total | J10: 3000 | K10: 1 | L10: 2.969
E11: Failed | F11: 147683.09 | G11: 0.089
E12: Leadership Development | F12: 323902.03 | G12: 0.19133333
A13: Employee Department type Analysis | E13: Completed | F13: 169387.15 | G13: 0.101
A14: Row Labels | B14: Count of EmpID | C14: Count of EmpID2 | E14: Failed | F14: 154514.88 | G14: 0.090333333 | I14: Applicant Status
A15: Production | B15: 2020 | C15: 0.67333333 | E15: Project Management | F15: 343313.17 | G15: 0.203 | I15: Row Labels | J15: Count of Applicant ID
A16: IT/IS | B16: 430 | C16: 0.14333333 | E16: Completed | F16: 166620.03 | G16: 0.097333333 | I16: Applied | J16: 611
A17: Sales | B17: 331 | C17: 0.11033333 | E17: Failed | F17: 176693.14 | G17: 0.10566667 | I17: In Review | J17: 595
A18: Software Engineering | B18: 115 | C18: 0.038333333 | E18: Technical Skills | F18: 323072.61 | G18: 0.193 | I18: Interviewing | J18: 590
A19: Admin Offices | B19: 80 | C19: 0.026666667 | E19: Completed | F19: 141300.25 | G19: 0.084666667 | I19: Offered | J19: 610
A20: Executive Office | B20: 24 | C20: 0.008 | E20: Failed | F20: 181772.36 | G20: 0.10833333 | I20: Rejected | J20: 594
A21: Grand Total | B21: 3000 | C21: 1 | E21: Grand Total | F21: 1675886.1 | G21: 1 | I21: Grand Total | J21: 3000
B39: Employee Payzone Analysis
B40: Row Labels | C40: Count of EmpID
B41: Zone A | C41: 1062
B42: Zone B | C42: 985
B43: Zone C | C43: 953
B44: Grand Total | C44: 3000

Sheet Pivot chart
V16: Training Type | W16: Internal
B18: Applicant Status | F18: Training & Development Table | K18: Employee Engagement Survey_Score Comparison Table | O18: Gender Code | P18: Count of EmpID | Q18: Percentage | V18: Row Labels | W18: Count of Training Duration(Days)
B19: Row Labels | C19: Count of Applicant ID | F19: Count of Employee ID | G19: Column Labels | K19: Average of Engagement Score | L19: Average of Satisfaction Score | M19: Average of Work/Life Balance Score | O19: Female | P19: 1682 | Q19: 0.56066667 | V19: Qtr1 | W19: 404
B20: Applied | C20: 611 | F20: Training Program name | G20: Completed | H20: Failed | I20: Grand Total | K20: 2.9396667 | L20: 3.022 | M20: 2.989 | O20: Male | P20: 1318 | Q20: 0.43933333 | V20: Qtr2 | W20: 368
B21: In Review | C21: 595 | F21: Communication Skills | G21: 362 | H21: 311 | I21: 673 | O21: Grand Total | P21: 3000 | Q21: 1 | V21: Qtr3 | W21: 364
B22: Interviewing | C22: 590 | F22: Customer Service | G22: 298 | H22: 267 | I22: 565 | V22: Qtr4 | W22: 373
B23: Offered | C23: 610 | F23: Leadership Development | G23: 303 | H23: 271 | I23: 574 | V23: Grand Total | W23: 1509
B24: Rejected | C24: 594 | F24: Project Management | G24: 292 | H24: 317 | I24: 609
B25: Grand Total | C25: 3000 | F25: Technical Skills | G25: 254 | H25: 325 | I25: 579
F26: Grand Total | G26: 1509 | H26: 1491 | I26: 3000
B36: EMPLOYEE COUNT & WORKFORCE STATUS ANALYSIS
B37: Employee status | C37: Count of EmpID | D37: Count of EmpID2
B38: Active | C38: 1661 | D38: 0.55366667
B39: Future Start | C39: 58 | D39: 0.019333333
B40: Leave of Absence | C40: 74 | D40: 0.024666667
B41: Terminated for Cause | C41: 272 | D41: 0.090666667
B42: Voluntarily Terminated | C42: 935 | D42: 0.31166667
B43: Grand Total | C43: 3000 | D43: 1
